Workbook
Name mth: 目录!$C$1

Sheet 目录
C1: 8
A2: =CONCATENATE("综合成本表(2025年"&mth&"月)") -> 综合成本表(2025年8月)
A3: 公司名称：融氏公司
A4: 序 号 | B4: 报表名称 | C4: 备 注
A5: 1 | B5: 编制说明
A6: 2 | B6: 与账面对比
A7: 3 | B7: 分销
A8: 4 | B8: 所有装置汇总-含税
A9: 5 | B9: 果糖装置汇总-含税
A10: 6 | B10: 麦芽糖浆-含税
A11: 7 | B11: F55-含税
A12: 8 | B12: F55OEM-含税
A13: 9 | B13: F42-含税
A14: 10 | B14: F60-含税
A15: 11 | B15: 成本分配表
A16: 12 | B16: 基础表
A17: 13 | B17: 销售收入与运费表

Sheet 说明
B2: 编制说明：
B3: 表格 | C3: 项目 | D3: 说明
B4: 基础表： | C4: 产量 | D4: 包括商品量绝干量，绝干比例
C5: 淀粉 | D5: 只录入自投部分淀粉消耗量、消耗成本；还需录入淀粉水分，以折算折成13个水的淀粉消耗量、单位成本
C6: 辅料 | D6: 存在联产产品的，如果F42/葡萄糖浆的消耗是定额的，则需要录入定额消耗，如果全部按照绝干比例分配的，则不需要录入
D7: 树脂没有消耗，但有成本，衡水需要将计入在建的成本分摊
C8: 动力能源
C9: 蒸汽
C10: 电
C11: 水
C12: 天然气
C13: 污水
C14: 固定成本：
C15: 折旧 | D15: 需要分车间、管理费用、销售费用
C16: 人工 | D16: 需要分车间、管理费用、销售费用，需要含外包劳务，但不含装卸运输费的劳务
C17: 制造费用 | D17: 录入总制造费用，减去人工、折旧，如果有外包劳务，需要录入并减去，但装卸费、运输费的劳务不减去。
C18: 管理费用 | D18: 录入总管理费用，减去人工、折旧、保安保洁的劳务
C19: 销售费用 | D19: 录入总制造费用，减去人工、折旧、运输费
C20: 财务费用 | D20: 包含利息、手续费支出，汇兑损益在其他项目中
C21: 其他 | D21: 包含营业外收支（不含大额补贴）、汇兑损益、营业税金及附加
B22: 分配表： | C22: 原料、辅料、动力能源 | D22: 对于有消耗数量、消耗成本的，分配表只分配数量，展现表成本用单价*数量计算得出 只有消耗成本的，如污水、固定成本，
D23: 辅料消耗，如果F42采用定额，则F42的辅料消耗量需要在基础表中录入， 如果F42辅料消耗量按照绝干量分配，则不需要录入，各企业需要特别注意。
C24: 污水、树脂及固定成本 | D24: 分配表直接分配成本
D25: 目前为按照绝干产量分配，也可以按照产值分配。
D26: 其他固定成本只分配给果葡糖浆正常产品
B27: 展现表 | C27: 分产品表： | D27: 收入与运费：从销售收入与运费表中取数。销售收入、运输费总额为单吨运费*产量，总数与账面运费由差异
D28: 原辅料、动力能源：从分配表中取单价、总消耗；单耗为总消耗除以总产量；F42表直接取F55的单价；
D29: 原辅料、动力能源的总成本、收入为单价、单位成本与产量的乘积
D30: 各项固定成本、辅料中的树脂总成本直接从分配表取数，单位成本为总成本除以总产量
C31: 汇总表： | D31: 汇总F55、F55(OEM)、F42；总产量统一折成77%干物；
D32: 汇总表的总成本、总消耗为各分产品的总成本、总消耗之和；各项单耗为总消耗除以总产量
D33: 由于F55（OEM）各项消耗没有分开列示，故汇总表辅料、动力能源从分配表中取数。
D34: 淀粉消耗量只包括F55、F42消耗量，故汇总表的单耗偏低。
C35: 不含税表与含税表 | D35: 含税表从不含税表中取数，涉及价格的乘以税率，不涉及价格的直接取数
D36: 含税表中的增值税为测算税额，部分不重要项目增值税税率不必与实际税率完全一致

Sheet 装置汇总
A1: =CONCATENATE("汇总综合成本利润表_不含税(2025年"&mth&"月)") -> 汇总综合成本利润表_不含税(2025年8月) | I1: =CONCATENATE("汇总综合成本利润表_不含税(2025年1-"&mth&"月)") -> 汇总综合成本利润表_不含税(2025年1-8月)
A3: 全部产品 | E3: 本月产量： | F3: =OFFSET(基础表!C30,0,mth-1,1,1)/0.77 -> 0 | G3: 吨 | M3: 本年产量： | N3: =基础表!O30/0.77 -> 97033.583 | O3: 吨
B4: 单位 | C4: 单价 | D4: 单耗 | E4: 单位成本 | F4: 总耗量 | G4: 总成本 | J4: 单位 | K4: 单价 | L4: 单耗 | M4: 单位成本 | N4: 总耗量 | O4: 总成本
A5: 一、收入 | E5: =E6-E7 -> 0 | G5: =G6-G7 -> #DIV/0! | I5: 一、收入 | M5: =M6-M7 -> 2872.7247 | O5: =O6-O7 -> 2.7875077e+08
A6: （一）销售价格 | E6: =IF(F$3=0,0,G6/F$3) -> 0 | G6: =专用糖!G6+'F55'!G6+'F42'!G6+'F60'!G6+风味糖!G6+调味糖!G6+'F90'!G6 -> 0 | I6: （一）销售价格 | M6: =IF($N$3=0,,O6/$N$3) -> 3002.6793 | O6: =专用糖!O6+'F55'!O6+'F42'!O6+'F60'!O6+风味糖!O6+调味糖!O6+'F90'!O6 -> 2.9136073e+08
A7: （二）物流费 | E7: =IF($F$3=0,,G7/$F$3) -> 0 | G7: =专用糖!G7+'F55'!G7+'F42'!G7+'F60'!G7+风味糖!G7+调味糖!G7+'F90'!G7 -> #DIV/0! | I7: （二）物流费 | M7: =IF($N$3=0,,O7/$N$3) -> 129.95458 | O7: =专用糖!O7+'F55'!O7+'F42'!O7+'F60'!O7+风味糖!O7+调味糖!O7+'F90'!O7 -> 12609958
A8: 1、运费 | E8: =IF($F$3=0,,G8/$F$3) -> 0 | G8: =专用糖!G8+'F55'!G8+'F42'!G8+'F60'!G8+风味糖!G8+调味糖!G8+'F90'!G8 -> #DIV/0! | I8: 1、运费 | M8: =IF($N$3=0,,O8/$N$3) -> 65.61797 | O8: =专用糖!O8+'F55'!O8+'F42'!O8+'F60'!O8+风味糖!O8+调味糖!O8+'F90'!O8 -> 6367146.8
A9: 2、包装费、租赁费等 | E9: =IF($F$3=0,,G9/$F$3) -> 0 | G9: =专用糖!G9+'F55'!G9+'F42'!G9+'F60'!G9+风味糖!G9+调味糖!G9+'F90'!G9 -> #DIV/0! | I9: 2、包装费、租赁费等 | M9: =IF($N$3=0,,O9/$N$3) -> 64.336607 | O9: =专用糖!O9+'F55'!O9+'F42'!O9+'F60'!O9+风味糖!O9+调味糖!O9+'F90'!O9 -> 6242811.5
A10: 二、变动成本 | E10: =E11+E14+E16+E21+E24+E15 -> #DIV/0! | G10: =G11+G14+G16+G21+G24+G15 -> #DIV/0! | I10: 二、变动成本 | M10: =M11+M14+M16+M21+M24+M15 -> #DIV/0! | O10: =O11+O14+O16+O21+O24+O15 -> #DIV/0!
A11: (一)淀粉 | B11: 吨 | C11: =C12 -> #DIV/0! | D11: =IF(C11=0,0,E11/C11) -> #DIV/0! | E11: =E12+E13 -> #DIV/0! | F11: =F12 -> 0 | G11: =G12+G13 -> 0 | I11: (一)淀粉 | J11: 吨 | K11: =IF(N11=0,0,O11/N11) -> 2512.1589 | L11: =L12 -> 0.84614503 | M11: =M12+M13 -> 2125.6507 | N11: =N12 -> 82104.484 | O11: =O12+O13 -> 2.0625951e+08
A12: 1、淀粉(14%) | B12: 吨 | C12: =E12/D12 -> #DIV/0! | D12: =IF(F3=0,,F12/F3) -> 0 | E12: =G12/F3 -> #DIV/0! | F12: =专用糖!F12+'F55'!F12+'F42'!F12+'F60'!F12+'F90'!F12 -> 0 | G12: =专用糖!G12+'F55'!G12+'F42'!G12+'F60'!G12+'F90'!G12 -> 0 | I12: 1、淀粉(14%) | J12: 吨 | K12: =M12/L12 -> 2498.9643 | L12: =IF(N3=0,,N12/N3) -> 0.84614503 | M12: =O12/N3 -> 2114.4862 | N12: =专用糖!N12+'F55'!N12+'F42'!N12+'F60'!N12+'F90'!N12 -> 82104.484 | O12: =专用糖!O12+'F55'!O12+'F42'!O12+'F60'!O12+'F90'!O12 -> 2.0517617e+08
A13: 2、淀粉糖 | E13: =G13/F3 -> #DIV/0! | G13: =调味糖!G11+风味糖!G11 -> 0 | I13: 2、淀粉糖 | M13: =O13/N3 -> 11.164507 | O13: =风味糖!O11+调味糖!O11 -> 1083332.1
A14: (二）辅料 | E14: =G14/F3 -> #DIV/0! | G14: =专用糖!G13+'F55'!G13+'F42'!G13+'F60'!G13+风味糖!G20+调味糖!G20+'F90'!G13 -> #DIV/0! | I14: (二）辅料 | M14: =O14/N3 -> #DIV/0! | O14: =专用糖!O13+'F55'!O13+'F42'!O13+'F60'!O13+风味糖!O20+调味糖!O20+'F90'!O13 -> #DIV/0!
A15: (三)包装物 | E15: =G15/F3 -> #DIV/0! | G15: =果糖汇总!G25+专用糖!G27+风味糖!G57 -> 0 | I15: (三)包装物 | M15: =O15/N3 -> 0 | O15: =果糖汇总!O25+专用糖!O27+风味糖!O57 -> 0
A16: (四)动力能源 | E16: =SUM(E17:E20) -> 0 | G16: =SUM(G17:G20) -> 0 | I16: (四)动力能源 | M16: =SUM(M17:M20) -> #DIV/0! | O16: =SUM(O17:O20) -> #DIV/0!
A17: 1、蒸汽 | B17: 吨 | C17: =IF(G17=0,0,G17/F17) -> 0 | D17: =IF($F$3=0,0,F17/$F$3) -> 0 | E17: =C17*D17 -> 0 | F17: =专用糖!F29+'F55'!F27+'F42'!F27+'F60'!F27+风味糖!F59+'F90'!F27+调味糖!F52 -> #DIV/0! | G17: =专用糖!G29+'F55'!G27+'F42'!G27+'F60'!G27+调味糖!G52+风味糖!G59+'F90'!G27 -> 0 | I17: 1、蒸汽 | J17: 吨 | K17: =IF(O17=0,0,O17/N17) -> #DIV/0! | L17: =IF($N$3=0,0,N17/$N$3) -> #DIV/0! | M17: =K17*L17 -> #DIV/0! | N17: =专用糖!N29+'F55'!N27+'F42'!N27+'F60'!N27+风味糖!N59+'F90'!N27 -> #DIV/0! | O17: =专用糖!O29+'F55'!O27+'F42'!O27+'F60'!O27+调味糖!O52+风味糖!O577+'F90'!O27 -> #DIV/0!
A18: 2、电 | B18: 度 | C18: =IF(G18=0,0,G18/F18) -> 0 | D18: =IF($F$3=0,0,F18/$F$3) -> 0 | E18: =C18*D18 -> 0 | F18: =专用糖!F30+'F55'!F28+'F42'!F28+'F60'!F28+风味糖!F60+'F90'!F28+调味糖!F53 -> #DIV/0! | G18: =专用糖!G30+'F55'!G28+'F42'!G28+'F60'!G28+调味糖!G53+风味糖!G60+'F90'!G28 -> 0 | I18: 2、电 | J18: 度 | K18: =IF(O18=0,0,O18/N18) -> #DIV/0! | L18: =IF($N$3=0,0,N18/$N$3) -> #DIV/0! | M18: =K18*L18 -> #DIV/0! | N18: =专用糖!N30+'F55'!N28+'F42'!N28+'F60'!N28+风味糖!N60+'F90'!N28+调味糖!N53 -> #DIV/0! | O18: =专用糖!O30+'F55'!O28+'F42'!O28+'F60'!O28+调味糖!O53+风味糖!O60+'F90'!O28 -> #DIV/0!
A19: 3、水 | B19: 吨 | C19: =IF(G19=0,0,G19/F19) -> 0 | D19: =IF($F$3=0,0,F19/$F$3) -> 0 | E19: =C19*D19 -> 0 | F19: =专用糖!F31+'F55'!F29+'F42'!F29+'F60'!F29+风味糖!F61+'F90'!F29+调味糖!F54 -> #DIV/0! | G19: =专用糖!G31+'F55'!G29+'F42'!G29+'F60'!G29+调味糖!G54+风味糖!G61+'F90'!G29 -> 0 | I19: 3、水 | J19: 吨 | K19: =IF(O19=0,0,O19/N19) -> #DIV/0! | L19: =IF($N$3=0,0,N19/$N$3) -> #DIV/0! | M19: =K19*L19 -> #DIV/0! | N19: =专用糖!N31+'F55'!N29+'F42'!N29+'F60'!N29+风味糖!N61+调味糖!N54+'F90'!N29 -> #DIV/0! | O19: =专用糖!O31+'F55'!O29+'F42'!O29+'F60'!O29+调味糖!O54+风味糖!O61+'F90'!O29 -> #DIV/0!
A20: 4、其他 | B20: M3 | I20: 4、其他 | J20: M3 | K20: =IF(O20=0,0,O20/N20) -> 0 | L20: =IF($N$3=0,0,N20/$N$3) -> 0 | M20: =K20*L20 -> 0 | N20: =专用糖!N32+'F55'!N30+'F42'!N30+'F60'!N30+'F90'!N30 -> 0 | O20: =专用糖!O32+'F55'!O30+'F42'!O30+'F60'!O30+'F90'!O30 -> 0
A21: (五)排污费 | E21: =IF(F$3=0,0,G21/F$3) -> 0 | G21: =专用糖!G33+'F55'!G31+'F42'!G31+'F60'!G31+调味糖!G56+风味糖!G63+'F90'!G31 -> #DIV/0! | I21: (五)排污费 | M21: =IF(N$3=0,0,O21/N$3) -> #DIV/0! | O21: =专用糖!O33+'F55'!O31+'F42'!O31+'F60'!O31+调味糖!O56+风味糖!O63+'F90'!O31 -> #DIV/0!
A22: 1.污水处理 | E22: =E21 -> 0 | G22: =G21 -> #DIV/0! | I22: 1.污水处理 | M22: =M21 -> #DIV/0! | O22: =O21 -> #DIV/0!
A23: 2.污水固定成本 | I23: 2.污水固定成本
A24: (六)增值税 | I24: (六)增值税
A25: 三、边际贡献 | E25: =E5-E10 -> #DIV/0! | G25: =G5-G10 -> #DIV/0! | I25: 三、边际贡献 | M25: =M5-M10 -> #DIV/0! | O25: =O5-O10 -> #DIV/0!
A26: 四、固定成本 | E26: =SUM(E27:E33) -> 0 | G26: =SUM(G27:G33) -> #DIV/0! | I26: 四、固定成本 | M26: =IF(N$3=0,0,O26/N$3) -> #DIV/0! | O26: =SUM(O27:O33) -> #DIV/0!
A27: （一）折旧与摊销 | E27: =IF(F$3=0,0,G27/F$3) -> 0 | G27: =专用糖!G39+'F55'!G37+'F42'!G37+'F60'!G37+调味糖!G62+风味糖!G69+'F90'!G37 -> #DIV/0! | I27: （一）折旧与摊销 | M27: =IF(N$3=0,0,O27/N$3) -> #DIV/0! | O27: =专用糖!O39+'F55'!O37+'F42'!O37+'F60'!O37+调味糖!O62+风味糖!O69+'F90'!O37 -> #DIV/0!
A28: （二）工资 | E28: =IF(F$3=0,0,G28/F$3) -> 0 | G28: =专用糖!G40+'F55'!G38+'F42'!G38+'F60'!G38+调味糖!G63+风味糖!G70+'F90'!G38 -> #DIV/0! | I28: （二）工资 | M28: =IF(N$3=0,0,O28/N$3) -> #DIV/0! | O28: =专用糖!O40+'F55'!O38+'F42'!O38+'F60'!O38+调味糖!O63+风味糖!O70+'F90'!O38 -> #DIV/0!
A29: （三）制造费用 | E29: =IF(F$3=0,0,G29/F$3) -> 0 | G29: =专用糖!G41+'F55'!G39+'F42'!G39+'F60'!G39+调味糖!G64+风味糖!G71+'F90'!G39 -> #DIV/0! | I29: （三）制造费用 | M29: =IF(N$3=0,0,O29/N$3) -> #DIV/0! | O29: =专用糖!O41+'F55'!O39+'F42'!O39+'F60'!O39+调味糖!O64+风味糖!O71+'F90'!O39 -> #DIV/0!
A30: （四）销售费用 | E30: =IF(F$3=0,0,G30/F$3) -> 0 | G30: =专用糖!G42+'F55'!G40+'F42'!G40+'F60'!G40+调味糖!G65+风味糖!G72+'F90'!G40 -> #DIV/0! | I30: （四）销售费用 | M30: =IF(N$3=0,0,O30/N$3) -> #DIV/0! | O30: =专用糖!O42+'F55'!O40+'F42'!O40+'F60'!O40+调味糖!O65+风味糖!O72+'F90'!O40 -> #DIV/0!
A31: （五）管理费用 | E31: =IF(F$3=0,0,G31/F$3) -> 0 | G31: =专用糖!G43+'F55'!G41+'F42'!G41+'F60'!G41+调味糖!G66+风味糖!G73+'F90'!G41 -> #DIV/0! | I31: （五）管理费用 | M31: =IF(N$3=0,0,O31/N$3) -> #DIV/0! | O31: =专用糖!O43+'F55'!O41+'F42'!O41+'F60'!O41+调味糖!O66+风味糖!O73+'F90'!O41 -> #DIV/0!
A32: （六）财务费用 | E32: =IF(F$3=0,0,G32/F$3) -> 0 | G32: =专用糖!G44+'F55'!G42+'F42'!G42+'F60'!G42+调味糖!G67+风味糖!G74+'F90'!G42 -> #DIV/0! | I32: （六）财务费用 | M32: =IF(N$3=0,0,O32/N$3) -> #DIV/0! | O32: =专用糖!O44+'F55'!O42+'F42'!O42+'F60'!O42+调味糖!O67+风味糖!O74+'F90'!O42 -> #DIV/0!
A33: （七）其他 | E33: =IF(F$3=0,0,G33/F$3) -> 0 | G33: =专用糖!G45+'F55'!G43+'F42'!G43+'F60'!G43+调味糖!G68+风味糖!G75+'F90'!G43 -> #DIV/0! | I33: （七） 其他 | M33: =IF(N$3=0,0,O33/N$3) -> #DIV/0! | O33: =专用糖!O45+'F55'!O43+'F42'!O43+'F60'!O43+调味糖!O68+风味糖!O75+'F90'!O43 -> #DIV/0!
A34: 其中：税金及附加 | E34: =IF(F$3=0,0,G34/F$3) -> 0 | G34: =果糖汇总!G44+专用糖!G46+调味糖!G69+风味糖!G76 -> #DIV/0! | I34: 其中：税金及附加 | M34: =IF(N$3=0,0,O34/N$3) -> #DIV/0! | O34: =果糖汇总!O44+专用糖!O46+调味糖!O69+风味糖!O76 -> #DIV/0!
A35: 其他业务收支 | E35: =IF(F$3=0,0,G35/F$3) -> 0 | G35: =果糖汇总!G45+专用糖!G47+调味糖!G70+风味糖!G77 -> #DIV/0! | I35: 其他业务收支 | M35: =IF(N$3=0,0,O35/N$3) -> #DIV/0! | O35: =果糖汇总!O45+专用糖!O47+调味糖!O70+风味糖!O77 -> #DIV/0!
A36: 营业外收支 | E36: =IF(F$3=0,0,G36/F$3) -> 0 | G36: =果糖汇总!G46+专用糖!G48+调味糖!G71+风味糖!G78 -> #DIV/0! | I36: 营业外收支 | M36: =IF(N$3=0,0,O36/N$3) -> #DIV/0! | O36: =果糖汇总!O46+专用糖!O48+调味糖!O71+风味糖!O78 -> #DIV/0!
A37: 投资收益+公允价值变动损益 | E37: =IF(F$3=0,0,G37/F$3) -> 0 | G37: =果糖汇总!G47+专用糖!G49+调味糖!G72+风味糖!G79 -> #DIV/0! | I37: 投资收益+公允价值变动损益 | M37: =IF(N$3=0,0,O37/N$3) -> #DIV/0! | O37: =果糖汇总!O47+专用糖!O49+调味糖!O72+风味糖!O79 -> #DIV/0!
A38: 其他收益 | E38: =IF(F$3=0,0,G38/F$3) -> 0 | G38: =果糖汇总!G48+专用糖!G50+调味糖!G73+风味糖!G80 -> #DIV/0! | I38: 其他收益 | M38: =IF(N$3=0,0,O38/N$3) -> #DIV/0! | O38: =果糖汇总!O48+专用糖!O50+调味糖!O73+风味糖!O80 -> #DIV/0!
A39: 资产减值损失 | E39: =IF(F$3=0,0,G39/F$3) -> 0 | G39: =果糖汇总!G49+专用糖!G51+调味糖!G74+风味糖!G81 -> #DIV/0! | I39: 资产减值损失 | M39: =IF(N$3=0,0,O39/N$3) -> #DIV/0! | O39: =果糖汇总!O49+专用糖!O51+调味糖!O74+风味糖!O81 -> #DIV/0!
A40: 其他 | E40: =IF(F$3=0,0,G40/F$3) -> 0 | G40: =果糖汇总!G50+专用糖!G52+调味糖!G75+风味糖!G82 -> #DIV/0! | I40: 其他 | M40: =IF(N$3=0,0,O40/N$3) -> #DIV/0! | O40: =果糖汇总!O50+专用糖!O52+调味糖!O75+风味糖!O82 -> #DIV/0!
A41: 五、完全成本 | B41: 元 | E41: =E10+E26 -> #DIV/0! | G41: =G10+G26 -> #DIV/0! | I41: 五、完全成本 | J41: 元 | M41: =M10+M26 -> #DIV/0! | O41: =O10+O26 -> #DIV/0!
A42: 六、利润总额 | E42: =E25-E26 -> #DIV/0! | G42: =G25-G26 -> #DIV/0! | I42: 六、利润总额 | M42: =M25-M26 -> #DIV/0! | O42: =O25-O26 -> #DIV/0!
A43: 七、现金流 | E43: =E42+E27 -> #DIV/0! | G43: =G42+G27 -> #DIV/0! | I43: 七、现金流 | M43: =M42+M27 -> #DIV/0! | O43: =O42+O27 -> #DIV/0!
A44: 加工费 | B44: 元 | E44: =E10+E26-E11-E15 -> #DIV/0! | G44: =G10+G26-G11-G15 -> #DIV/0! | I44: 加工费 | J44: 元 | M44: =M10+M26-M11-M15 -> #DIV/0! | O44: =O10+O26-O11-O15 -> #DIV/0!
A45: 其他业务收支-糖渣 | E45: =IF(F$3=0,0,G45/F$3) -> 0 | G45: =果糖汇总!G55+专用糖!G57+风味糖!G87+调味糖!G80 -> #DIV/0! | I45: 其他业务收支-糖渣 | M45: =IF(N$3=0,0,O45/N$3) -> #DIV/0! | O45: =果糖汇总!O55+专用糖!O57+风味糖!O87 -> #DIV/0!

Sheet 装置汇总-含税
A1: =CONCATENATE("汇总综合成本利润表_含税(2025年"&mth&"月)") -> 汇总综合成本利润表_含税(2025年8月) | I1: =CONCATENATE("汇总综合成本利润表_含税(2025年1-"&mth&"月)") -> 汇总综合成本利润表_含税(2025年1-8月)
E3: 本月折77固形物产量： | F3: =装置汇总!F3 -> 0 | G3: 吨 | M3: 本年折77固形物产量： | N3: =装置汇总!N3 -> 97033.583 | O3: 吨
B4: 单位 | C4: 单价 | D4: 单耗 | E4: 单位成本 | F4: 总耗量 | G4: 总成本 | J4: 单位 | K4: 单价 | L4: 单耗 | M4: 单位成本 | N4: 总耗量 | O4: 总成本
A5: 一、收入 | E5: =E6-E7 -> 0 | G5: =G6-G7 -> 0 | I5: 一、收入 | M5: =M6-M7 -> 3184.9767 | O5: =O6-O7 -> 3.090497e+08
A6: （一）销售价格 | E6: =IF(F$3=0,0,G6/F$3) -> 0 | G6: ='果糖汇总-含税'!G6+'专用糖-含税'!G6+'风味糖-含税'!G6+'调味糖-含税'!G6 -> 0 | I6: （一）销售价格 | M6: =IF($N$3=0,,O6/$N$3) -> 3317.406 | O6: ='果糖汇总-含税'!O6+'专用糖-含税'!O6+'风味糖-含税'!O6 -> 3.2189979e+08
A7: （二）物流费 | E7: =IF($F$3=0,,G7/$F$3) -> 0 | G7: ='果糖汇总-含税'!G7+'专用糖-含税'!G7+'风味糖-含税'!G7+'调味糖-含税'!G7 -> 0 | I7: （二）物流费 | M7: =IF($N$3=0,,O7/$N$3) -> 132.42929 | O7: ='果糖汇总-含税'!O7+'专用糖-含税'!O7+'风味糖-含税'!O7 -> 12850088
A8: 1、运费 | E8: =IF($F$3=0,,G8/$F$3) -> 0 | G8: ='果糖汇总-含税'!G8+'专用糖-含税'!G8+'风味糖-含税'!G8+'调味糖-含税'!G8 -> #DIV/0! | I8: 1、运费 | M8: =IF($N$3=0,,O8/$N$3) -> 69.461384 | O8: ='果糖汇总-含税'!O8+'专用糖-含税'!O8+'风味糖-含税'!O8 -> 6740086.9
A9: 2、包装费、租赁费等 | E9: =IF($F$3=0,,G9/$F$3) -> 0 | G9: ='果糖汇总-含税'!G9+'专用糖-含税'!G9+'风味糖-含税'!G9+'调味糖-含税'!G9 -> #DIV/0! | I9: 2、包装费、租赁费等 | M9: =IF($N$3=0,,O9/$N$3) -> 62.967902 | O9: ='果糖汇总-含税'!O9+'专用糖-含税'!O9+'风味糖-含税'!O9 -> 6110001.2
A10: 二、变动成本 | E10: =E11+E14+E16+E21+E24+E15 -> #DIV/0! | G10: =G11+G14+G16+G21+G24+G15 -> #DIV/0! | I10: 二、变动成本 | M10: =M11+M14+M16+M21+M24+M15 -> #DIV/0! | O10: =O11+O14+O16+O21+O24+O15 -> #DIV/0!
A11: (一)淀粉 | B11: 吨 | C11: =C12 -> #DIV/0! | D11: =D12 -> 0 | E11: =E12 -> #DIV/0! | F11: =F12 -> 0 | G11: =G12 -> 0 | I11: (一)淀粉 | J11: 吨 | K11: =IF(N11=0,0,O11/N11) -> 2823.8297 | L11: =IF(K11=0,0,M11/K11) -> 0.84614503 | M11: =M12 -> 2389.3694 | N11: =N12 -> 82104.484 | O11: =O12 -> 2.3184908e+08
A12: 1、淀粉(14%) | B12: 吨 | C12: =装置汇总!C12*1.13 -> #DIV/0! | D12: =装置汇总!D12 -> 0 | E12: =装置汇总!E12*1.13 -> #DIV/0! | F12: =装置汇总!F12 -> 0 | G12: =装置汇总!G12*1.13 -> 0 | I12: 1、淀粉(14%) | J12: 吨 | K12: =装置汇总!K12*1.13 -> 2823.8297 | L12: =装置汇总!L12 -> 0.84614503 | M12: =装置汇总!M12*1.13 -> 2389.3694 | N12: =装置汇总!N12 -> 82104.484 | O12: =装置汇总!O12*1.13 -> 2.3184908e+08
A13: 2、淀粉糖 | I13: 2、淀粉糖
A14: (二)辅助材料 | E14: =装置汇总!E14*1.13 -> #DIV/0! | G14: =装置汇总!G14*1.13 -> #DIV/0! | I14: (二)辅助材料 | M14: =装置汇总!M14*1.13 -> #DIV/0! | O14: =装置汇总!O14*1.13 -> #DIV/0!
A15: (三)包装物 | E15: =装置汇总!E15*1.13 -> #DIV/0! | G15: =装置汇总!G15*1.13 -> 0 | I15: (三)包装物 | M15: =装置汇总!M15*1.13 -> 0 | O15: =装置汇总!O15*1.13 -> 0
A16: (四)动力能源 | E16: =SUM(E17:E20) -> 0 | G16: =SUM(G17:G20) -> 0 | I16: (四)动力能源 | M16: =SUM(M17:M20) -> #DIV/0! | O16: =SUM(O17:O20) -> #DIV/0!
A17: 1、蒸汽 | B17: 吨 | C17: =IF(G17=0,0,G17/F17) -> 0 | D17: =装置汇总!D17 -> 0 | E17: =C17*D17 -> 0 | F17: =装置汇总!F17 -> #DIV/0! | G17: ='专用糖-含税'!G29+'F55-含税'!G27+'F42-含税'!G27+'F60-含税'!G27+'风味糖-含税'!G59+'F90-含税 '!G27+'调味糖-含税'!G51 -> 0 | I17: 1、蒸汽 | J17: 吨 | K17: =IF(O17=0,0,O17/N17) -> #DIV/0! | L17: =装置汇总!L17 -> #DIV/0! | M17: =K17*L17 -> #DIV/0! | N17: =装置汇总!N17 -> #DIV/0! | O17: ='专用糖-含税'!O29+'F55-含税'!O27+'F42-含税'!O27+'F60-含税'!O27+'风味糖-含税'!O59 -> #DIV/0!
A18: 2、电 | B18: 度 | C18: =IF(G18=0,0,G18/F18) -> 0 | D18: =装置汇总!D18 -> 0 | E18: =装置汇总!E18*1.13 -> 0 | F18: =装置汇总!F18 -> #DIV/0! | G18: =装置汇总!G18*1.13 -> 0 | I18: 2、电 | J18: 度 | K18: =IF(O18=0,0,O18/N18) -> #DIV/0! | L18: =装置汇总!L18 -> #DIV/0! | M18: =装置汇总!M18*1.13 -> #DIV/0! | N18: =装置汇总!N18 -> #DIV/0! | O18: =装置汇总!O18*1.13 -> #DIV/0!
A19: 3、水 | B19: 吨 | C19: =IF(G19=0,0,G19/F19) -> 0 | D19: =装置汇总!D19 -> 0 | E19: =D19*C19 -> 0 | F19: =装置汇总!F19 -> #DIV/0! | G19: ='果糖汇总-含税'!G29+'专用糖-含税'!G31+'风味糖-含税'!G61+'调味糖-含税'!G53 -> 0 | I19: 3、水 | J19: 吨 | K19: =IF(O19=0,0,O19/N19) -> #DIV/0! | L19: =装置汇总!L19 -> #DIV/0! | M19: =L19*K19 -> #DIV/0! | N19: =装置汇总!N19 -> #DIV/0! | O19: ='果糖汇总-含税'!O29+'专用糖-含税'!O31+'风味糖-含税'!O61 -> #DIV/0!
A20: 4、其他 | I20: 4、其他
A21: (五)排污费 | E21: =装置汇总!E21*1.13 -> 0 | G21: =装置汇总!G21*1.13 -> #DIV/0! | I21: (五)排污费 | M21: =装置汇总!M21*1.13 -> #DIV/0! | O21: =装置汇总!O21*1.13 -> #DIV/0!
A22: 1.污水处理 | E22: =E21 -> 0 | G22: =G21 -> #DIV/0! | I22: 1.污水处理 | M22: =M21 -> #DIV/0! | O22: =O21 -> #DIV/0!
A23: 2.污水固定成本 | I23: 2.污水固定成本
A24: (六)增值税 | E24: =SUM(E5,-E11,-E14,-E16,-E21)-SUM(装置汇总!E5,-装置汇总!E11,-装置汇总!E14,-装置汇总!E16,-装置汇总!E21) -> #DIV/0! | G24: =SUM(G5,-G11,-G14,-G16,-G21,-G15)-SUM(装置汇总!G5,-装置汇总!G11,-装置汇总!G14,-装置汇总!G16,-装置汇总!G21,-装置汇总!G15) -> #DIV/0! | I24: (六)增值税 | M24: =SUM(M5,-M11,-M14,-M16,-M21)-SUM(装置汇总!M5,-装置汇总!M11,-装置汇总!M14,-装置汇总!M16,-装置汇总!M21) -> #DIV/0! | O24: =SUM(O5,-O11,-O14,-O16,-O21,-O15)-SUM(装置汇总!O5,-装置汇总!O11,-装置汇总!O14,-装置汇总!O16,-装置汇总!O21,-装置汇总!O15) -> #DIV/0!
A25: 三、边际贡献 | E25: =E5-E10 -> #DIV/0! | G25: =G5-G10 -> #DIV/0! | I25: 三、边际贡献 | M25: =M5-M10 -> #DIV/0! | O25: =O5-O10 -> #DIV/0!
A26: 四、固定成本 | E26: =SUM(E27:E33) -> 0 | G26: =SUM(G27:G33) -> #DIV/0! | I26: 四、固定成本 | M26: =SUM(M27:M33) -> #DIV/0! | O26: =SUM(O27:O33) -> #DIV/0!
A27: （一）折旧与摊销 | E27: =IF(F$3=0,0,G27/F$3) -> 0 | G27: =装置汇总!G27 -> #DIV/0! | I27: （一）折旧与摊销 | M27: =IF(N$3=0,0,O27/N$3) -> #DIV/0! | O27: =装置汇总!O27 -> #DIV/0!
A28: （二）工资 | E28: =IF(F$3=0,0,G28/F$3) -> 0 | G28: =装置汇总!G28 -> #DIV/0! | I28: （二）工资 | M28: =IF(N$3=0,0,O28/N$3) -> #DIV/0! | O28: =装置汇总!O28 -> #DIV/0!
A29: （三）制造费用 | E29: =IF(F$3=0,0,G29/F$3) -> 0 | G29: =装置汇总!G29 -> #DIV/0! | I29: （三）制造费用 | M29: =IF(N$3=0,0,O29/N$3) -> #DIV/0! | O29: =装置汇总!O29 -> #DIV/0!
A30: （四）销售费用 | E30: =IF(F$3=0,0,G30/F$3) -> 0 | G30: =装置汇总!G30 -> #DIV/0! | I30: （四）销售费用 | M30: =IF(N$3=0,0,O30/N$3) -> #DIV/0! | O30: =装置汇总!O30 -> #DIV/0!
A31: （五）管理费用 | E31: =IF(F$3=0,0,G31/F$3) -> 0 | G31: =装置汇总!G31 -> #DIV/0! | I31: （五）管理费用 | M31: =IF(N$3=0,0,O31/N$3) -> #DIV/0! | O31: =装置汇总!O31 -> #DIV/0!
A32: （六）财务费用 | E32: =IF(F$3=0,0,G32/F$3) -> 0 | G32: =装置汇总!G32 -> #DIV/0! | I32: （六）财务费用 | M32: =IF(N$3=0,0,O32/N$3) -> #DIV/0! | O32: =装置汇总!O32 -> #DIV/0!
A33: （七）其他 | E33: =IF(F$3=0,0,G33/F$3) -> 0 | G33: =装置汇总!G33 -> #DIV/0! | I33: （七） 其他 | M33: =IF(N$3=0,0,O33/N$3) -> #DIV/0! | O33: =装置汇总!O33 -> #DIV/0!
A34: 其中：税金及附加 | E34: =IF(F$3=0,0,G34/F$3) -> 0 | G34: =装置汇总!G34 -> #DIV/0! | I34: 其中：税金及附加 | M34: =IF(N$3=0,0,O34/N$3) -> #DIV/0! | O34: =装置汇总!O34 -> #DIV/0!
A35: 其他业务收支 | E35: =IF(F$3=0,0,G35/F$3) -> 0 | G35: =装置汇总!G35 -> #DIV/0! | I35: 其他业务收支 | M35: =IF(N$3=0,0,O35/N$3) -> #DIV/0! | O35: =装置汇总!O35 -> #DIV/0!
A36: 营业外收支 | E36: =IF(F$3=0,0,G36/F$3) -> 0 | G36: =装置汇总!G36 -> #DIV/0! | I36: 营业外收支 | M36: =IF(N$3=0,0,O36/N$3) -> #DIV/0! | O36: =装置汇总!O36 -> #DIV/0!
A37: 投资收益+公允价值变动损益 | E37: =IF(F$3=0,0,G37/F$3) -> 0 | G37: =装置汇总!G37 -> #DIV/0! | I37: 投资收益+公允价值变动损益 | M37: =IF(N$3=0,0,O37/N$3) -> #DIV/0! | O37: =装置汇总!O37 -> #DIV/0!
A38: 其他收益 | E38: =IF(F$3=0,0,G38/F$3) -> 0 | G38: =装置汇总!G38 -> #DIV/0! | I38: 其他收益 | M38: =IF(N$3=0,0,O38/N$3) -> #DIV/0! | O38: =装置汇总!O38 -> #DIV/0!
... A40: 其他 | E40: =IF(F$3=0,0,G40/F$3) -> 0 | G40: =装置汇总!G40 -> #DIV/0! | I40: 其他 | M40: =IF(N$3=0,0,O40/N$3) -> #DIV/0! | O40: =装置汇总!O40 -> #DIV/0!
A41: 五、完全成本 | B41: 元 | E41: =E10+E26 -> #DIV/0! | G41: =G10+G26 -> #DIV/0! | I41: 五、完全成本 | J41: 元 | M41: =M10+M26 -> #DIV/0! | O41: =O10+O26 -> #DIV/0!
A42: 六、利润总额 | B42: 元 | E42: =E25-E26 -> #DIV/0! | G42: =G25-G26 -> #DIV/0! | I42: 六、利润总额 | J42: 元 | M42: =M25-M26 -> #DIV/0! | O42: =O25-O26 -> #DIV/0!
A43: 七、现金流 | B43: 元 | E43: =E42+E27 -> #DIV/0! | G43: =G42+G27 -> #DIV/0! | I43: 七、现金流 | J43: 元 | M43: =M42+M27 -> #DIV/0! | O43: =O42+O27 -> #DIV/0!
A44: 加工费 | B44: 元 | E44: =E10+E26-E11-E15 -> #DIV/0! | G44: =G10+G26-G11-G15 -> #DIV/0! | I44: 加工费 | J44: 元 | M44: =M10+M26-M11-M15 -> #DIV/0! | O44: =O10+O26-O11-O15 -> #DIV/0!
A45: 其他业务收支-糖渣 | E45: =IF(F$3=0,0,G45/F$3) -> 0 | G45: =装置汇总!G45 -> #DIV/0! | I45: 其他业务收支-糖渣 | M45: =IF(N$3=0,0,O45/N$3) -> #DIV/0! | O45: =装置汇总!O45 -> #DIV/0!
A48: 含税与不含税校验 | E48: =E25-装置汇总!E25 -> #DIV/0! | G48: =G25-装置汇总!G25 -> #DIV/0! | L48: check | M48: =M25-装置汇总!M25 -> #DIV/0! | O48: =O25-装置汇总!O25 -> #DIV/0!

Sheet F60
A1: =CONCATENATE("果葡糖浆F60综合成本利润表_不含税(2025年"&mth&"月)") -> 果葡糖浆F60综合成本利润表_不含税(2025年8月) | I1: =CONCATENATE("果葡糖浆F60综合成本利润表_不含税(2025年1-"&mth&"月)") -> 果葡糖浆F60综合成本利润表_不含税(2025年1-8月)
A3: 产量 | E3: 本月产量 | F3: =OFFSET(基础表!C10,0,mth-1,1,1) -> 0 | G3: 吨 | M3: 本年产量 | N3: =基础表!O10 -> 6845.043 | O3: 吨
B4: 单位 | C4: 单价 | D4: 单耗 | E4: 单位成本 | F4: 总耗量 | G4: 总成本 | J4: 单位 | K4: 单价 | L4: 单耗 | M4: 单位成本 | N4: 总耗量 | O4: 总成本
A5: 一、收入 | E5: =E6-E7 -> #DIV/0! | G5: =G6-G7 -> #DIV/0! | I5: 一、收入 | M5: =M6-M7 -> 3131.9523 | O5: =O6-O7 -> 21438348
A6: （一）销售价格 | E6: =OFFSET(销售收入及运费!C71,0,mth-1,1,1) -> 0 | G6: =E6*$F$3 -> 0 | I6: （一）销售价格 | M6: =销售收入及运费!O71 -> 3852.7044 | O6: =M6*$N$3 -> 26371927
A7: （二）运费 | E7: =E8+E9 -> #DIV/0! | G7: =E7*$F$3 -> #DIV/0! | I7: （二）运费 | M7: =M8+M9 -> 720.75213 | O7: =M7*$N$3 -> 4933579.3
A8: 1、运费 | E8: =OFFSET(销售收入及运费!C128,0,mth-1,1,1)/1.09/OFFSET(销售收入及运费!C11,0,mth-1,1,1) -> #DIV/0! | G8: =E8*$F$3 -> #DIV/0! | I8: 1、运费 | M8: =销售收入及运费!O128/1.09/销售收入及运费!O11 -> 211.24352 | O8: =M8*$N$3 -> 1445971
A9: 2、包装费、租赁费等 | E9: =(OFFSET(销售收入及运费!C148,0,mth-1,1,1)/1.13+OFFSET(销售收入及运费!C168,0,mth-1,1,1)/1.13)/OFFSET(销售收入及运费!C11,0,mth-1,1,1) -> #DIV/0! | G9: =E9*$F$3 -> #DIV/0! | I9: 2、包装费、租赁费等 | M9: =(销售收入及运费!O148/1.13+销售收入及运费!O168/1.13)/销售收入及运费!O11 -> 509.50861 | O9: =M9*$N$3 -> 3487608.3
A10: 二、变动成本 | E10: =E11+E13+E26+E31+E25 -> 0 | G10: =G11+G13+G26+G31+G25 -> #DIV/0! | I10: 二、变动成本 | M10: =M11+M13+M26+M31+M25 -> #DIV/0! | O10: =O11+O13+O26+O31+O25 -> #DIV/0!
A11: (一)淀粉 | B11: 吨 | C11: =C12 -> 0 | D11: =IF(C11=0,0,E11/C11) -> 0 | E11: =E12 -> 0 | F11: =F12 -> 0 | G11: =G12 -> 0 | I11: (一)淀粉 | J11: 吨 | K11: =IF(N11=0,0,O11/N11) -> 2502.5327 | L11: =IF(K11=0,0,M11/K11) -> 0.82529689 | M11: =M12 -> 2065.3324 | N11: =N12 -> 5649.1927 | O11: =O12 -> 14137289
A12: 1、淀粉(14%) | B12: 吨 | C12: =OFFSET(分配表!C68,0,mth-1,1,1) -> 0 | D12: =IF(VALUE($F$3)=0,0,F12/$F$3) -> 0 | E12: =C12*D12 -> 0 | F12: =OFFSET(分配表!C82,0,mth-1,1,1) -> 0 | G12: =E12*F3 -> 0 | I12: 1、淀粉(14%) | J12: 吨 | K12: =分配表!O68 -> 2502.5327 | L12: =IF($N$3=0,0,N12/$N$3) -> 0.82529689 | M12: =K12*L12 -> 2065.3324 | N12: =分配表!O82 -> 5649.1927 | O12: =K12*N12 -> 14137289
A13: (二）辅料 | E13: =SUM(E14:E24) -> 0 | G13: =SUM(G14:G24) -> #DIV/0! | I13: (二）辅料 | M13: =SUM(M14:M24) -> #DIV/0! | O13: =SUM(O14:O24) -> #DIV/0!
A14: 盐酸(折百) | C14: ='F55'!C14 -> 0 | D14: =IF(VALUE($F$3)=0,0,F14/$F$3) -> 0 | E14: =C14*D14 -> 0 | F14: =OFFSET(分配表!C153,0,mth-1,1,1) -> 0 | G14: =E14*$F$3 -> 0 | I14: 盐酸(折百) | K14: ='F55'!K14 -> 1.0336348 | L14: =IF($N$3=0,0,N14/$N$3) -> 4.448574 | M14: =K14*L14 -> 4.5982007 | N14: =分配表!O153 -> 30450.68 | O14: =M14*$N$3 -> 31474.881
A15: 氢氧化钠(折百) | C15: ='F55'!C15 -> 0 | D15: =IF(VALUE($F$3)=0,0,F15/$F$3) -> 0 | E15: =C15*D15 -> 0 | F15: =OFFSET(分配表!C154,0,mth-1,1,1) -> 0 | G15: =E15*$F$3 -> 0 | I15: 氢氧化钠(折百) | K15: ='F55'!K15 -> 3.1653036 | L15: =IF($N$3=0,0,N15/$N$3) -> 4.9385811 | M15: =K15*L15 -> 15.632109 | N15: =分配表!O154 -> 33804.8 | O15: =M15*$N$3 -> 107002.46
A16: 硅藻土 | C16: ='F55'!C16 -> 0 | D16: =IF(VALUE($F$3)=0,0,F16/$F$3) -> 0 | E16: =C16*D16 -> 0 | F16: =OFFSET(分配表!C155,0,mth-1,1,1) -> 0 | G16: =E16*$F$3 -> 0 | I16: 硅藻土 | K16: ='F55'!K16 -> 2.60487 | L16: =IF($N$3=0,0,N16/$N$3) -> 0.74784044 | M16: =K16*L16 -> 1.9480272 | N16: =分配表!O155 -> 5119 | O16: =M16*$N$3 -> 13334.33
A17: 活性炭 | C17: ='F55'!C17 -> 0 | D17: =IF(VALUE($F$3)=0,0,F17/$F$3) -> 0 | E17: =C17*D17 -> 0 | F17: =OFFSET(分配表!C157,0,mth-1,1,1) -> 0 | G17: =E17*$F$3 -> 0 | I17: 活性炭 | K17: ='F55'!K17 -> 7.0797015 | L17: =IF($N$3=0,0,N17/$N$3) -> 1.5528025 | M17: =K17*L17 -> 10.993378 | N17: =分配表!O157 -> 10629 | O17: =M17*$N$3 -> 75250.147
A18: 淀粉酶 | C18: ='F55'!C18 -> 0 | D18: =IF(VALUE($F$3)=0,0,F18/$F$3) -> 0 | E18: =C18*D18 -> 0 | F18: =OFFSET(分配表!C158,0,mth-1,1,1) -> 0 | G18: =E18*$F$3 -> 0 | I18: 淀粉酶 | K18: ='F55'!K18 -> 47.801409 | L18: =IF($N$3=0,0,N18/$N$3) -> 0.080642298 | M18: =K18*L18 -> 3.8548155 | N18: =分配表!O158 -> 552 | O18: =M18*$N$3 -> 26386.378
A19: 复合糖化酶 | C19: ='F55'!C19 -> 0 | D19: =IF(VALUE($F$3)=0,0,F19/$F$3) -> 0 | E19: =C19*D19 -> 0 | F19: =OFFSET(分配表!C159,0,mth-1,1,1) -> 0 | G19: =E19*$F$3 -> 0 | I19: 复合糖化酶 | K19: ='F55'!K19 -> 32.197431 | L19: =IF($N$3=0,0,N19/$N$3) -> 0.15660968 | M19: =K19*L19 -> 5.0424294 | N19: =分配表!O159 -> 1072 | O19: =M19*$N$3 -> 34515.646
A20: 异构酶 | C20: ='F55'!C20 -> 0 | D20: =IF(VALUE($F$3)=0,0,F20/$F$3) -> 0 | E20: =C20*D20 -> 0 | F20: =OFFSET(分配表!C160,0,mth-1,1,1) -> 0 | G20: =E20*$F$3 -> 0 | I20: 异构酶 | K20: ='F55'!K20 -> 218.57702 | L20: =IF($N$3=0,0,N20/$N$3) -> 0.095499765 | M20: =K20*L20 -> 20.874054 | N20: =分配表!O160 -> 653.7 | O20: =M20*$N$3 -> 142883.8
A21: 硫酸镁(食品级) | C21: ='F55'!C21 -> 0 | D21: =IF(VALUE($F$3)=0,0,F21/$F$3) -> 0 | E21: =C21*D21 -> 0 | F21: =OFFSET(分配表!C161,0,mth-1,1,1) -> 0 | G21: =E21*$F$3 -> 0 | I21: 硫酸镁(食品级) | K21: ='F55'!K21 -> 0.97947435 | L21: =IF($N$3=0,0,N21/$N$3) -> 0.48341552 | M21: =K21*L21 -> 0.4734931 | N21: =分配表!O161 -> 3309 | O21: =M21*$N$3 -> 3241.0806
A22: 焦亚硫酸钠(食品级) | C22: ='F55'!C22 -> 0 | D22: =IF(VALUE($F$3)=0,0,F22/$F$3) -> 0 | E22: =C22*D22 -> 0 | F22: =OFFSET(分配表!C162,0,mth-1,1,1) -> 0 | G22: =E22*$F$3 -> 0 | I22: 焦亚硫酸钠 | K22: ='F55'!K22 -> 1.8560801 | L22: =IF($N$3=0,0,N22/$N$3) -> 0.28429332 | M22: =K22*L22 -> 0.52767118 | N22: =分配表!O162 -> 1946 | O22: =M22*$N$3 -> 3611.9319
A23: 树脂 | E23: =IF(VALUE($F$3)=0,0,G23/$F$3) -> 0 | F23: =OFFSET(分配表!C163,0,mth-1,1,1) -> 0 | G23: =OFFSET(分配表!C209,0,mth-1,1,1) -> #DIV/0! | I23: 树脂 | M23: =IF($N$3=0,0,O23/$N$3) -> #DIV/0! | N23: =分配表!O163 -> 0 | O23: =分配表!O209 -> #DIV/0!
A24: 其他 | E24: =IF(VALUE($F$3)=0,0,G24/$F$3) -> 0 | G24: =OFFSET(分配表!C220,0,mth-1) -> #DIV/0! | I24: 其他 | M24: =O24/N3 -> #DIV/0! | O24: =分配表!O220 -> #DIV/0!
A25: (三)包装物 | I25: (三)包装物
A26: (四)动力能源 | E26: =SUM(E27:E30) -> 0 | G26: =SUM(G27:G30) -> 0 | I26: (四)动力能源 | M26: =SUM(M27:M30) -> #DIV/0! | O26: =SUM(O27:O30) -> #DIV/0!
A27: 1、蒸汽 | B27: 吨 | C27: ='F55'!C27 -> 0 | D27: =IF(VALUE($F$3)=0,0,F27/$F$3) -> 0 | E27: =C27*D27 -> 0 | F27: =OFFSET(分配表!C312,0,mth-1,1,1) -> 0 | G27: =E27*F$3 -> 0 | I27: 1、蒸汽 | J27: 吨 | K27: ='F55'!K27 -> 374.79903 | L27: =IF($N$3=0,0,N27/$N$3) -> 0.30291994 | M27: =K27*L27 -> 113.5341 | N27: =分配表!O312 -> 2073.5 | O27: =M27*N$3 -> 777145.78
A28: 2、电 | B28: 度 | C28: ='F55'!C28 -> 0 | D28: =IF(VALUE($F$3)=0,0,F28/$F$3) -> 0 | E28: =C28*D28 -> 0 | F28: =OFFSET(分配表!C331,0,mth-1,1,1) -> #DIV/0! | G28: =E28*F$3 -> 0 | I28: 2、电 | J28: 度 | K28: ='F55'!K28 -> 0.6806368 | L28: =IF($N$3=0,0,N28/$N$3) -> #DIV/0! | M28: =K28*L28 -> #DIV/0! | N28: =分配表!O331 -> #DIV/0! | O28: =M28*N$3 -> #DIV/0!
A29: 3、水 | B29: 吨 | C29: ='F55'!C29 -> 0 | D29: =IF(VALUE($F$3)=0,0,F29/$F$3) -> 0 | E29: =C29*D29 -> 0 | F29: =OFFSET(分配表!C349,0,mth-1,1,1) -> #DIV/0! | G29: =E29*F$3 -> 0 | I29: 3、水 | J29: 吨 | K29: ='F55'!K29 -> 5.8950402 | L29: =IF($N$3=0,0,N29/$N$3) -> #DIV/0! | M29: =K29*L29 -> #DIV/0! | N29: =分配表!O349 -> #DIV/0! | O29: =M29*N$3 -> #DIV/0!
A30: 4、其他 | B30: 吨 | C30: ='F55'!C30 -> 0 | D30: =IF(VALUE($F$3)=0,0,F30/$F$3) -> 0 | E30: =C30*D30 -> 0 | G30: =E30*F$3 -> 0 | I30: 4、其他 | J30: 吨 | K30: ='F55'!K30 -> 0 | L30: =IF($N$3=0,0,N30/$N$3) -> 0 | M30: =K30*L30 -> 0 | O30: =M30*N$3 -> 0
A31: (五)排污费 | E31: =IF(VALUE($F$3)=0,0,G31/$F$3) -> 0 | G31: =OFFSET(分配表!C377,0,mth-1,1,1) -> #DIV/0! | I31: (五)排污费 | M31: =IF($N$3=0,,O31/$N$3) -> #DIV/0! | O31: =分配表!O377 -> #DIV/0!
A32: 1.污水处理 | E32: =E31 -> 0 | G32: =G31 -> #DIV/0! | I32: 1.污水处理 | M32: =M31 -> #DIV/0! | O32: =O31 -> #DIV/0!
A33: 2.污水固定成本 | I33: 2.污水固定成本
A34: (六)增值税 | I34: (六)增值税
A35: 三、边际贡献 | E35: =E5-E10 -> #DIV/0! | G35: =G5-G10 -> #DIV/0! | I35: 三、边际贡献 | M35: =M5-M10 -> #DIV/0! | O35: =O5-O10 -> #DIV/0!
A36: 四、固定成本 | E36: =SUM(E37:E43) -> 0 | G36: =SUM(G37:G43) -> #DIV/0! | I36: 四、固定成本 | M36: =IF(N$3=0,0,O36/N$3) -> #DIV/0! | O36: =SUM(O37:O43) -> #DIV/0!
A37: （一）折旧与摊销 | E37: =IF(VALUE($F$3)=0,0,G37/$F$3) -> 0 | G37: =OFFSET(分配表!C410,0,mth-1,1,1) -> #DIV/0! | I37: （一）折旧与摊销 | M37: =IF($N$3=0,0,O37/$N$3) -> #DIV/0! | O37: =分配表!O410 -> #DIV/0!
A38: （二）工资 | E38: =IF(VALUE($F$3)=0,0,G38/$F$3) -> 0 | G38: =OFFSET(分配表!C430,0,mth-1,1,1) -> #DIV/0! | I38: （二）工资 | M38: =IF($N$3=0,0,O38/$N$3) -> #DIV/0! | O38: =分配表!O430 -> #DIV/0!
A39: （三）制造费用 | E39: =IF(VALUE($F$3)=0,0,G39/$F$3) -> 0 | G39: =OFFSET(分配表!C450,0,mth-1,1,1) -> #DIV/0! | I39: （三）制造费用 | M39: =IF($N$3=0,0,O39/$N$3) -> #DIV/0! | O39: =分配表!O450 -> #DIV/0!
A40: （四）销售费用 | E40: =IF(VALUE($F$3)=0,0,G40/$F$3) -> 0 | G40: =OFFSET(分配表!C470,0,mth-1,1,1) -> #DIV/0! | I40: （四）销售费用 | M40: =IF($N$3=0,0,O40/$N$3) -> #DIV/0! | O40: =分配表!O470 -> #DIV/0!
A41: （五）管理费用 | E41: =IF(VALUE($F$3)=0,0,G41/$F$3) -> 0 | G41: =OFFSET(分配表!C490,0,mth-1,1,1) -> #DIV/0! | I41: （五）管理费用 | M41: =IF($N$3=0,0,O41/$N$3) -> #DIV/0! | O41: =分配表!O490 -> #DIV/0!
A42: （六）财务费用 | E42: =IF(VALUE($F$3)=0,0,G42/$F$3) -> 0 | G42: =OFFSET(分配表!C506,0,mth-1,1,1) -> #DIV/0! | I42: （六）财务费用 | M42: =IF($N$3=0,0,O42/$N$3) -> #DIV/0! | O42: =分配表!O506 -> #DIV/0!
A43: （七）其他 | E43: =IF(VALUE($F$3)=0,0,G43/$F$3) -> 0 | G43: =OFFSET(分配表!C528,0,mth-1,1,1) -> #DIV/0! | I43: （七） 其他 | M43: =IF($N$3=0,0,O43/$N$3) -> #DIV/0! | O43: =分配表!O528 -> #DIV/0!
A44: 其中：税金及附加 | E44: =IF(VALUE($F$3)=0,0,G44/$F$3) -> 0 | G44: =OFFSET(分配表!C540,0,mth-1,1,1) -> #DIV/0! | I44: 其中：税金及附加 | M44: =IF($N$3=0,0,O44/$N$3) -> #DIV/0! | O44: =分配表!O540 -> #DIV/0!
A45: 其他业务收支 | E45: =IF(VALUE($F$3)=0,0,G45/$F$3) -> 0 | G45: =OFFSET(分配表!C552,0,mth-1,1,1) -> #DIV/0! | I45: 其他业务收支 | M45: =IF($N$3=0,0,O45/$N$3) -> #DIV/0! | O45: =分配表!O552 -> #DIV/0!
A46: 营业外收支 | E46: =IF(VALUE($F$3)=0,0,G46/$F$3) -> 0 | G46: =OFFSET(分配表!C600,0,mth-1,1,1) -> #DIV/0! | I46: 营业外收支 | M46: =IF($N$3=0,0,O46/$N$3) -> #DIV/0! | O46: =分配表!O600 -> #DIV/0!
A47: 投资收益+公允价值变动损益 | E47: =IF(VALUE($F$3)=0,0,G47/$F$3) -> 0 | G47: =OFFSET(分配表!C564,0,mth-1,1,1) -> #DIV/0! | I47: 投资收益+公允价值变动损益 | M47: =IF($N$3=0,0,O47/$N$3) -> #DIV/0! | O47: =分配表!O564 -> #DIV/0!
A48: 其他收益 | E48: =IF(VALUE($F$3)=0,0,G48/$F$3) -> 0 | G48: =OFFSET(分配表!C576,0,mth-1,1,1) -> #DIV/0! | I48: 其他收益 | M48: =IF($N$3=0,0,O48/$N$3) -> #DIV/0! | O48: =分配表!O576 -> #DIV/0!
A49: 资产减值损失 | E49: =IF(VALUE($F$3)=0,0,G49/$F$3) -> 0 | G49: =OFFSET(分配表!C588,0,mth-1,1,1) -> #DIV/0! | I49: 资产减值损失 | M49: =IF($N$3=0,0,O49/$N$3) -> #DIV/0! | O49: =分配表!O588 -> #DIV/0!
A50: 其他 | E50: =IF(VALUE($F$3)=0,0,G50/$F$3) -> 0 | G50: =OFFSET(分配表!C612,0,mth-1,1,1) -> #DIV/0! | I50: 其他 | M50: =IF($N$3=0,0,O50/$N$3) -> #DIV/0! | O50: =分配表!O612 -> #DIV/0!
A51: 五、完全成本 | B51: 元 | E51: =E36+E10 -> 0 | G51: =G36+G10 -> #DIV/0! | I51: 五、完全成本 | J51: 元 | M51: =M36+M10 -> #DIV/0! | O51: =O36+O10 -> #DIV/0!
A52: 六、利润总额 | E52: =E35-E36 -> #DIV/0! | G52: =G35-G36 -> #DIV/0! | I52: 六、利润总额 | M52: =M35-M36 -> #DIV/0! | O52: =O35-O36 -> #DIV/0!
A53: 七、现金流 | E53: =E52+E37 -> #DIV/0! | G53: =G52+G37 -> #DIV/0! | I53: 七、现金流 | M53: =M52+M37 -> #DIV/0! | O53: =O52+O37 -> #DIV/0!
A54: 加工费 | B54: 元 | E54: =E10-E11+E36-E25 -> 0 | G54: =G10-G11+G36-G25 -> #DIV/0! | I54: 加工费 | J54: 元 | M54: =M10-M11+M36-M25 -> #DIV/0! | O54: =O10-O11+O36-O25 -> #DIV/0!
A55: 其他业务收支-糖渣 | E55: =IF(VALUE($F$3)=0,0,G55/$F$3) -> 0 | G55: =OFFSET(分配表!C625,0,mth-1,1,1) -> #DIV/0! | I55: 其他业务收支-糖渣 | M55: =IF($N$3=0,0,O55/$N$3) -> #DIV/0! | O55: =分配表!O625 -> #DIV/0!

Sheet F55
A1: =CONCATENATE("果葡糖浆F55综合成本利润表_不含税(2025年"&mth&"月)") -> 果葡糖浆F55综合成本利润表_不含税(2025年8月) | I1: =CONCATENATE("果葡糖浆F55综合成本利润表_不含税(2025年1-"&mth&"月)") -> 果葡糖浆F55综合成本利润表_不含税(2025年1-8月)
A3: 自产部分 | E3: 自产产量 | F3: =OFFSET(基础表!C6,0,mth-1,1,1) -> 0 | M3: 自产产量 | N3: =基础表!O6 -> 49280.176 | O3: 吨
B4: 单位 | C4: 单价 | D4: 单耗 | E4: 单位成本 | F4: 总耗量 | G4: 总成本 | J4: 单位 | K4: 单价 | L4: 单耗 | M4: 单位成本 | N4: 总耗量 | O4: 总成本
A5: 一、收入 | E5: =E6-E7 -> #DIV/0! | G5: =G6-G7 -> #DIV/0! | I5: 一、收入 | M5: =M6-M7 -> 2655.2821 | O5: =O6-O7 -> 1.3085277e+08
A6: （一）销售价格 | E6: =OFFSET(销售收入及运费!C66,0,mth-1,1,1) -> 0 | G6: =E6*$F$3 -> 0 | I6: （一）销售价格 | M6: =销售收入及运费!O66 -> 2712.7846 | O6: =M6*$N$3 -> 1.336865e+08
A7: （二）物流费 | E7: =E8+E9 -> #DIV/0! | G7: =E7*$F$3 -> #DIV/0! | I7: （二）物流费 | M7: =M8+M9 -> 57.502534 | O7: =M7*$N$3 -> 2833735
A8: 1、运费 | E8: =OFFSET(销售收入及运费!C123,0,mth-1,1,1)/1.09/OFFSET(销售收入及运费!C6,0,mth-1,1,1) -> #DIV/0! | G8: =E8*$F$3 -> #DIV/0! | I8: 1、运费 | M8: =销售收入及运费!O123/1.09/销售收入及运费!O6 -> 44.847494 | O8: =M8*$N$3 -> 2210092.4
A9: 2、包装费、租赁费等 | E9: =(OFFSET(销售收入及运费!C143,0,mth-1,1,1)/1.13+OFFSET(销售收入及运费!C163,0,mth-1,1,1)/1.13)/OFFSET(销售收入及运费!C6,0,mth-1,1,1) -> #DIV/0! | G9: =E9*$F$3 -> #DIV/0! | I9: 2、包装费、租赁费等 | M9: =(销售收入及运费!O143/1.13+销售收入及运费!O163/1.13)/销售收入及运费!O6 -> 12.655039 | O9: =M9*$N$3 -> 623642.57
A10: 二、变动成本 | E10: =E11+E13+E26+E31+E34+E25 -> 0 | G10: =G11+G13+G26+G31+G25 -> #DIV/0! | I10: 二、变动成本 | M10: =M11+M13+M26+M31+M34+M25 -> #DIV/0! | O10: =O11+O13+O26+O31+O25 -> #DIV/0!
A11: (一)淀粉 | B11: 吨 | C11: =C12 -> 0 | D11: =IF(C11=0,0,E11/C11) -> 0 | E11: =E12 -> 0 | F11: =F12 -> 0 | G11: =G12 -> 0 | I11: (一)淀粉 | J11: 吨 | K11: =IF(N11=0,0,O11/N11) -> 2499.441 | L11: =IF(K11=0,0,M11/K11) -> 0.84877003 | M11: =M12 -> 2121.4506 | N11: =N12 -> 41827.536 | O11: =O12 -> 1.0454546e+08
A12: 1、淀粉(14%) | B12: 吨 | C12: =OFFSET(分配表!C65,0,mth-1,1,1) -> 0 | D12: =IF(VALUE($F$3)=0,0,F12/$F$3) -> 0 | E12: =C12*D12 -> 0 | F12: =OFFSET(分配表!C78,0,mth-1,1,1) -> 0 | G12: =E12*F3 -> 0 | I12: 1、淀粉(14%) | J12: 吨 | K12: =分配表!O65 -> 2499.441 | L12: =IF($N$3=0,,N12/$N$3) -> 0.84877003 | M12: =K12*L12 -> 2121.4506 | N12: =分配表!O78 -> 41827.536 | O12: =K12*N12 -> 1.0454546e+08
A13: (二）辅料 | E13: =SUM(E14:E24) -> 0 | G13: =SUM(G14:G24) -> #DIV/0! | I13: (二）辅料 | M13: =SUM(M14:M24) -> #DIV/0! | O13: =SUM(O14:O24) -> #DIV/0!
A14: 盐酸(折百) | C14: =OFFSET(分配表!C179,0,mth-1,1,1) -> 0 | D14: =IF(VALUE($F$3)=0,0,F14/$F$3) -> 0 | E14: =C14*D14 -> 0 | F14: =OFFSET(分配表!C101,0,mth-1) -> 0 | G14: =E14*$F$3 -> 0 | I14: 盐酸(折百) | K14: =分配表!O179 -> 1.0336348 | L14: =IF($N$3=0,,N14/$N$3) -> 4.5578743 | M14: =K14*L14 -> 4.7111774 | N14: =分配表!O101 -> 224612.85 | O14: =M14*$N$3 -> 232167.65
A15: 氢氧化钠(折百) | C15: =OFFSET(分配表!C180,0,mth-1,1,1) -> 0 | D15: =IF(VALUE($F$3)=0,0,F15/$F$3) -> 0 | E15: =C15*D15 -> 0 | F15: =OFFSET(分配表!C102,0,mth-1) -> 0 | G15: =E15*$F$3 -> 0 | I15: 氢氧化钠(折百) | K15: =分配表!O180 -> 3.1653036 | L15: =IF($N$3=0,,N15/$N$3) -> 5.0625869 | M15: =K15*L15 -> 16.024625 | N15: =分配表!O102 -> 249485.17 | O15: =M15*$N$3 -> 789696.32
A16: 硅藻土 | C16: =OFFSET(分配表!C181,0,mth-1,1,1) -> 0 | D16: =IF(VALUE($F$3)=0,0,F16/$F$3) -> 0 | E16: =C16*D16 -> 0 | F16: =OFFSET(分配表!C103,0,mth-1) -> 0 | G16: =E16*$F$3 -> 0 | I16: 硅藻土 | K16: =分配表!O181 -> 2.60487 | L16: =IF($N$3=0,,N16/$N$3) -> 0.76650844 | M16: =K16*L16 -> 1.9966549 | N16: =分配表!O103 -> 37773.671 | O16: =M16*$N$3 -> 98395.503
A17: 活性炭 | C17: =OFFSET(分配表!C183,0,mth-1,1,1) -> 0 | D17: =IF(VALUE($F$3)=0,0,F17/$F$3) -> 0 | E17: =C17*D17 -> 0 | F17: =OFFSET(分配表!C105,0,mth-1) -> 0 | G17: =E17*$F$3 -> 0 | I17: 活性炭 | K17: =分配表!O183 -> 7.0797015 | L17: =IF($N$3=0,,N17/$N$3) -> 1.5998718 | M17: =K17*L17 -> 11.326615 | N17: =分配表!O105 -> 78841.965 | O17: =M17*$N$3 -> 558177.58
A18: 淀粉酶 | C18: =OFFSET(分配表!C184,0,mth-1,1,1) -> 0 | D18: =IF(VALUE($F$3)=0,0,F18/$F$3) -> 0 | E18: =C18*D18 -> 0 | F18: =OFFSET(分配表!C106,0,mth-1) -> 0 | G18: =E18*$F$3 -> 0 | I18: 淀粉酶 | K18: =分配表!O184 -> 47.801409 | L18: =IF($N$3=0,,N18/$N$3) -> 0.082519047 | M18: =K18*L18 -> 3.9445268 | N18: =分配表!O106 -> 4066.5532 | O18: =M18*$N$3 -> 194386.97
A19: 复合糖化酶 | C19: =OFFSET(分配表!C185,0,mth-1,1,1) -> 0 | D19: =IF(VALUE($F$3)=0,0,F19/$F$3) -> 0 | E19: =C19*D19 -> 0 | F19: =OFFSET(分配表!C107,0,mth-1) -> 0 | G19: =E19*$F$3 -> 0 | I19: 复合糖化酶 | K19: =分配表!O185 -> 32.197431 | L19: =IF($N$3=0,,N19/$N$3) -> 0.16120776 | M19: =K19*L19 -> 5.1904757 | N19: =分配表!O107 -> 7944.3467 | O19: =M19*$N$3 -> 255787.56
A20: 异构酶 | C20: =OFFSET(分配表!C186,0,mth-1,1,1) -> 0 | D20: =IF(VALUE($F$3)=0,0,F20/$F$3) -> 0 | E20: =C20*D20 -> 0 | F20: =OFFSET(分配表!C108,0,mth-1) -> 0 | G20: =E20*$F$3 -> 0 | I20: 异构酶 | K20: =分配表!O186 -> 218.57702 | L20: =IF($N$3=0,,N20/$N$3) -> 0.097700032 | M20: =K20*L20 -> 21.354982 | N20: =分配表!O108 -> 4814.6748 | O20: =M20*$N$3 -> 1052377.3
A21: 硫酸镁 | C21: =OFFSET(分配表!C187,0,mth-1,1,1) -> 0 | D21: =IF(VALUE($F$3)=0,0,F21/$F$3) -> 0 | E21: =C21*D21 -> 0 | F21: =OFFSET(分配表!C109,0,mth-1) -> 0 | G21: =E21*$F$3 -> 0 | I21: 硫酸镁 | K21: =分配表!O187 -> 0.97947435 | L21: =IF($N$3=0,,N21/$N$3) -> 0.49607959 | M21: =K21*L21 -> 0.48589723 | N21: =分配表!O109 -> 24446.89 | O21: =M21*$N$3 -> 23945.101
A22: 焦亚硫酸钠 | C22: =OFFSET(分配表!C188,0,mth-1,1,1) -> 0 | D22: =IF(VALUE($F$3)=0,0,F22/$F$3) -> 0 | E22: =C22*D22 -> 0 | F22: =OFFSET(分配表!C110,0,mth-1) -> 0 | G22: =E22*$F$3 -> 0 | I22: 焦亚硫酸钠 | K22: =分配表!O188 -> 1.8560801 | L22: =IF($N$3=0,,N22/$N$3) -> 0.29181585 | M22: =K22*L22 -> 0.54163359 | N22: =分配表!O110 -> 14380.736 | O22: =M22*$N$3 -> 26691.799
A23: 树脂 | E23: =IF(VALUE($F$3)=0,0,G23/$F$3) -> 0 | G23: =OFFSET(分配表!C205,0,mth-1,1,1) -> #DIV/0! | I23: 树脂 | M23: =IF($N$3=0,0,O23/$N$3) -> #DIV/0! | O23: =分配表!O205 -> #DIV/0!
A24: 其他 | E24: =IF(VALUE($F$3)=0,0,G24/$F$3) -> 0 | G24: =OFFSET(分配表!C216,0,mth-1,1,1) -> #DIV/0! | I24: 其他 | M24: =IF($N$3=0,0,O24/$N$3) -> #DIV/0! | O24: =分配表!O216 -> #DIV/0!
A25: (三)包装物 | I25: (三)包装物
A26: (四)动力能源 | E26: =SUM(E27:E30) -> 0 | G26: =SUM(G27:G30) -> 0 | I26: (四)动力能源 | M26: =SUM(M27:M30) -> #DIV/0! | O26: =SUM(O27:O30) -> #DIV/0!
A27: 1、蒸汽 | B27: 吨 | C27: =OFFSET(分配表!C305,0,mth-1,1,1) -> 0 | D27: =IF(VALUE($F$3)=0,0,F27/$F$3) -> 0 | E27: =C27*D27 -> 0 | F27: =OFFSET(分配表!C308,0,mth-1,1,1) -> 0 | G27: =E27*F$3 -> 0 | I27: 1、蒸汽 | J27: 吨 | K27: =分配表!O305 -> 374.79903 | L27: =IF($N$3=0,0,N27/$N$3) -> 0.30859932 | M27: =K27*L27 -> 115.66272 | N27: =分配表!O308 -> 15207.829 | O27: =M27*N$3 -> 5699879.4
A28: 2、电 | B28: 度 | C28: =OFFSET(分配表!C324,0,mth-1,1,1) -> 0 | D28: =IF(VALUE($F$3)=0,0,F28/$F$3) -> 0 | E28: =C28*D28 -> 0 | F28: =OFFSET(分配表!C327,0,mth-1,1,1) -> #DIV/0! | G28: =E28*F$3 -> 0 | I28: 2、电 | J28: 度 | K28: =分配表!O324 -> 0.6806368 | L28: =IF($N$3=0,0,N28/$N$3) -> #DIV/0! | M28: =K28*L28 -> #DIV/0! | N28: =分配表!O327 -> #DIV/0! | O28: =M28*N$3 -> #DIV/0!
A29: 3、水 | B29: 吨 | C29: =OFFSET(分配表!C343,0,mth-1,1,1) -> 0 | D29: =IF(VALUE($F$3)=0,0,F29/$F$3) -> 0 | E29: =C29*D29 -> 0 | F29: =OFFSET(分配表!C345,0,mth-1,1,1) -> #DIV/0! | G29: =E29*F$3 -> 0 | I29: 3、水 | J29: 吨 | K29: =分配表!O343 -> 5.8950402 | L29: =IF($N$3=0,0,N29/$N$3) -> #DIV/0! | M29: =K29*L29 -> #DIV/0! | N29: =分配表!O345 -> #DIV/0! | O29: =M29*N$3 -> #DIV/0!
A30: 4、其他 | B30: 吨 | C30: =OFFSET(分配表!C360,0,mth-1,1,1) -> 0 | D30: =IF(VALUE($F$3)=0,0,F30/$F$3) -> 0 | E30: =C30*D30 -> 0 | F30: =OFFSET(分配表!C362,0,mth-1,1,1) -> 0 | G30: =E30*F$3 -> 0 | I30: 4、其他 | J30: 吨 | K30: =分配表!O360 -> 0 | L30: =IF($N$3=0,0,N30/$N$3) -> 0 | M30: =K30*L30 -> 0 | N30: =分配表!O362 -> 0 | O30: =M30*N$3 -> 0
A31: (五)排污费 | E31: =IF(VALUE($F$3)=0,0,G31/$F$3) -> 0 | G31: =OFFSET(分配表!C373,0,mth-1,1,1) -> #DIV/0! | I31: (五)排污费 | M31: =IF($N$3=0,,O31/$N$3) -> #DIV/0! | O31: =分配表!O373 -> #DIV/0!
A32: 1.污水处理 | E32: =E31 -> 0 | G32: =G31 -> #DIV/0! | I32: 1.污水处理 | M32: =M31 -> #DIV/0! | O32: =O31 -> #DIV/0!
A33: 2.污水固定成本 | I33: 2.污水固定成本
A34: (六)增值税 | I34: (六)增值税
A35: 三、边际贡献 | E35: =E5-E10 -> #DIV/0! | G35: =G5-G10 -> #DIV/0! | I35: 三、边际贡献 | M35: =M5-M10 -> #DIV/0! | O35: =O5-O10 -> #DIV/0!
A36: 四、固定成本 | E36: =SUM(E37:E43) -> 0 | G36: =SUM(G37:G43) -> #DIV/0! | I36: 四、固定成本 | M36: =IF(N$3=0,0,O36/N$3) -> #DIV/0! | O36: =SUM(O37:O43) -> #DIV/0!
A37: （一）折旧与摊销 | E37: =IF(VALUE($F$3)=0,0,G37/$F$3) -> 0 | G37: =OFFSET(分配表!C406,0,mth-1,1,1) -> #DIV/0! | I37: （一）折旧与摊销 | M37: =IF($N$3=0,0,O37/$N$3) -> #DIV/0! | O37: =分配表!O406 -> #DIV/0!
A38: （二）工资 | E38: =IF(VALUE($F$3)=0,0,G38/$F$3) -> 0 | G38: =OFFSET(分配表!C426,0,mth-1,1,1) -> #DIV/0! | I38: （二）工资 | M38: =IF($N$3=0,0,O38/$N$3) -> #DIV/0! | O38: =分配表!O426 -> #DIV/0!
A39: （三）制造费用 | E39: =IF(VALUE($F$3)=0,0,G39/$F$3) -> 0 | G39: =OFFSET(分配表!C446,0,mth-1,1,1) -> #DIV/0! | I39: （三）制造费用 | M39: =IF($N$3=0,0,O39/$N$3) -> #DIV/0! | O39: =分配表!O446 -> #DIV/0!
A40: （四）销售费用 | E40: =IF(VALUE($F$3)=0,0,G40/$F$3) -> 0 | G40: =OFFSET(分配表!C466,0,mth-1,1,1) -> #DIV/0! | I40: （四）销售费用 | M40: =IF($N$3=0,0,O40/$N$3) -> #DIV/0! | O40: =分配表!O466 -> #DIV/0!
A41: （五）管理费用 | E41: =IF(VALUE($F$3)=0,0,G41/$F$3) -> 0 | G41: =OFFSET(分配表!C486,0,mth-1,1,1) -> #DIV/0! | I41: （五）管理费用 | M41: =IF($N$3=0,0,O41/$N$3) -> #DIV/0! | O41: =分配表!O486 -> #DIV/0!
A42: （六）财务费用 | E42: =IF(VALUE($F$3)=0,0,G42/$F$3) -> 0 | G42: =OFFSET(分配表!C502,0,mth-1,1,1) -> #DIV/0! | I42: （六）财务费用 | M42: =IF($N$3=0,0,O42/$N$3) -> #DIV/0! | O42: =分配表!O502 -> #DIV/0!
A43: （七）其他 | E43: =IF(VALUE($F$3)=0,0,G43/$F$3) -> 0 | G43: =OFFSET(分配表!C524,0,mth-1,1,1) -> #DIV/0! | I43: （七） 其他 | M43: =IF($N$3=0,0,O43/$N$3) -> #DIV/0! | O43: =分配表!O524 -> #DIV/0!
A44: 其中：税金及附加 | E44: =IF(VALUE($F$3)=0,0,G44/$F$3) -> 0 | G44: =OFFSET(分配表!C536,0,mth-1,1,1) -> #DIV/0! | I44: 其中：税金及附加 | M44: =IF($N$3=0,0,O44/$N$3) -> #DIV/0! | O44: =分配表!O536 -> #DIV/0!
A45: 其他业务收支 | E45: =IF(VALUE($F$3)=0,0,G45/$F$3) -> 0 | G45: =OFFSET(分配表!C548,0,mth-1,1,1) -> #DIV/0! | I45: 其他业务收支 | M45: =IF($N$3=0,0,O45/$N$3) -> #DIV/0! | O45: =分配表!O548 -> #DIV/0!
A46: 营业外收支 | E46: =IF(VALUE($F$3)=0,0,G46/$F$3) -> 0 | G46: =OFFSET(分配表!C596,0,mth-1,1,1) -> #DIV/0! | I46: 营业外收支 | M46: =IF($N$3=0,0,O46/$N$3) -> #DIV/0! | O46: =分配表!O596 -> #DIV/0!
A47: 投资收益+公允价值变动损益 | E47: =IF(VALUE($F$3)=0,0,G47/$F$3) -> 0 | G47: =OFFSET(分配表!C560,0,mth-1,1,1) -> #DIV/0! | I47: 投资收益+公允价值变动损益 | M47: =IF($N$3=0,0,O47/$N$3) -> #DIV/0! | O47: =分配表!O560 -> #DIV/0!
A48: 其他收益 | E48: =IF(VALUE($F$3)=0,0,G48/$F$3) -> 0 | G48: =OFFSET(分配表!C572,0,mth-1,1,1) -> #DIV/0! | I48: 其他收益 | M48: =IF($N$3=0,0,O48/$N$3) -> #DIV/0! | O48: =分配表!O572 -> #DIV/0!
A49: 资产减值损失 | E49: =IF(VALUE($F$3)=0,0,G49/$F$3) -> 0 | G49: =OFFSET(分配表!C584,0,mth-1,1,1) -> #DIV/0! | I49: 资产减值损失 | M49: =IF($N$3=0,0,O49/$N$3) -> #DIV/0! | O49: =分配表!O584 -> #DIV/0!
A50: 其他 | E50: =IF(VALUE($F$3)=0,0,G50/$F$3) -> 0 | G50: =OFFSET(分配表!C608,0,mth-1,1,1) -> #DIV/0! | I50: 其他 | M50: =IF($N$3=0,0,O50/$N$3) -> #DIV/0! | O50: =分配表!O608 -> #DIV/0!
A51: 五、完全成本 | B51: 元 | E51: =E36+E10 -> 0 | G51: =G36+G10 -> #DIV/0! | I51: 五、完全成本 | J51: 元 | M51: =M36+M10 -> #DIV/0! | O51: =O36+O10 -> #DIV/0!
A52: 六、利润总额 | E52: =E35-E36 -> #DIV/0! | G52: =G35-G36 -> #DIV/0! | I52: 六、利润总额 | M52: =M35-M36 -> #DIV/0! | O52: =O35-O36 -> #DIV/0!
A53: 七、现金流 | E53: =E52+E37 -> #DIV/0! | G53: =G52+G37 -> #DIV/0! | I53: 七、现金流 | M53: =M52+M37 -> #DIV/0! | O53: =O52+O37 -> #DIV/0!
A54: 加工费 | B54: 元 | E54: =E10-E11+E36-E25 -> 0 | G54: =G10-G11+G36-G25 -> #DIV/0! | I54: 加工费 | J54: 元 | M54: =M10-M11+M36-M25 -> #DIV/0! | O54: =O10-O11+O36-O25 -> #DIV/0!
A55: 其他业务收支-糖渣 | E55: =IF(VALUE($F$3)=0,0,G55/$F$3) -> 0 | G55: =OFFSET(分配表!C621,0,mth-1,1,1) -> #DIV/0! | I55: 其他业务收支-糖渣 | M55: =IF($N$3=0,0,O55/$N$3) -> #DIV/0! | O55: =分配表!O621 -> #DIV/0!

Sheet 果糖汇总
A1: =CONCATENATE("汇总综合成本利润表_不含税(2025年"&mth&"月)") -> 汇总综合成本利润表_不含税(2025年8月) | I1: =CONCATENATE("汇总综合成本利润表_不含税(2025年1-"&mth&"月)") -> 汇总综合成本利润表_不含税(2025年1-8月)
A3: 全部产品 | E3: 本月产量： | F3: =OFFSET(基础表!C25,0,mth-1,1,1)/0.77 -> 0 | G3: 吨 | M3: 本年产量： | N3: =基础表!O25/0.77 -> 57934.763 | O3: 吨
B4: 单位 | C4: 单价 | D4: 单耗 | E4: 单位成本 | F4: 总耗量 | G4: 总成本 | J4: 单位 | K4: 单价 | L4: 单耗 | M4: 单位成本 | N4: 总耗量 | O4: 总成本
A5: 一、收入 | E5: =E6-E7 -> 0 | G5: =G6-G7 -> #DIV/0! | I5: 一、收入 | M5: =M6-M7 -> 2722.3523 | O5: =O6-O7 -> 1.5771884e+08
A6: （一）销售价格 | E6: =IF(F$3=0,0,G6/F$3) -> 0 | G6: ='F55'!G6+'F42'!G6+'F60'!G6+'F90'!G6 -> 0 | I6: （一）销售价格 | M6: =IF($N$3=0,,O6/$N$3) -> 2858.5148 | O6: ='F55'!O6+'F42'!O6+'F60'!O6+'F90'!O6 -> 1.6560738e+08
A7: （二）物流费 | E7: =IF($F$3=0,,G7/$F$3) -> 0 | G7: ='F55'!G7+'F42'!G7+'F60'!G7+'F90'!G7 -> #DIV/0! | I7: （二）物流费 | M7: =IF($N$3=0,,O7/$N$3) -> 136.16246 | O7: ='F55'!O7+'F42'!O7+'F60'!O7+'F90'!O7 -> 7888540.2
A8: 1、运费 | E8: =IF($F$3=0,,G8/$F$3) -> 0 | G8: ='F55'!G8+'F42'!G8+'F60'!G8+'F90'!G8 -> #DIV/0! | I8: 1、运费 | M8: =IF($N$3=0,,O8/$N$3) -> 64.429155 | O8: ='F55'!O8+'F42'!O8+'F60'!O8+'F90'!O8 -> 3732687.8
A9: 2、包装费、租赁费等 | E9: =IF($F$3=0,,G9/$F$3) -> 0 | G9: ='F55'!G9+'F42'!G9+'F60'!G9+'F90'!G9 -> #DIV/0! | I9: 2、包装费、租赁费等 | M9: =IF($N$3=0,,O9/$N$3) -> 71.73331 | O9: ='F55'!O9+'F42'!O9+'F60'!O9+'F90'!O9 -> 4155852.3
A10: 二、变动成本 | E10: =E11+E13+E26+E31+E34+E25 -> 0 | G10: =G11+G13+G26+G31+G25 -> #DIV/0! | I10: 二、变动成本 | M10: =M11+M13+M26+M31+M34+M25 -> #DIV/0! | O10: =O11+O13+O26+O31+O25 -> #DIV/0!
A11: (一)淀粉 | B11: 吨 | C11: =C12 -> 0 | D11: =IF(C11=0,0,E11/C11) -> 0 | E11: =E12 -> 0 | F11: =F12 -> 0 | G11: =G12 -> 0 | I11: (一)淀粉 | J11: 吨 | K11: =IF(N11=0,0,O11/N11) -> 2499.4112 | L11: =L12 -> 0.84550165 | M11: =M12 -> 2113.2563 | N11: =N12 -> 48983.938 | O11: =O12 -> 1.22431e+08
A12: 1、淀粉(14%) | B12: 吨 | C12: =IF(E12=0,0,E12/D12) -> 0 | D12: =IF(F3=0,,F12/F3) -> 0 | E12: =IF(F3=0,0,G12/F3) -> 0 | F12: ='F55'!F12+'F42'!F12+'F60'!F12+'F90'!F12 -> 0 | G12: ='F55'!G12+'F42'!G12+'F60'!G12+'F90'!G12 -> 0 | I12: 1、淀粉(14%) | J12: 吨 | K12: =M12/L12 -> 2499.4112 | L12: =IF(N3=0,,N12/N3) -> 0.84550165 | M12: =O12/N3 -> 2113.2563 | N12: ='F55'!N12+'F42'!N12+'F60'!N12+'F90'!N12 -> 48983.938 | O12: ='F55'!O12+'F42'!O12+'F60'!O12+'F90'!O12 -> 1.22431e+08
A13: (二）辅料 | E13: =IF(VALUE($F$3)=0,0,G13/$F$3) -> 0 | G13: ='F55'!G13+'F42'!G13+'F60'!G13+'F90'!G13 -> #DIV/0! | I13: (二）辅料 | M13: =O13/N3 -> #DIV/0! | O13: ='F55'!O13+'F42'!O13+'F60'!O13+'F90'!O13 -> #DIV/0!
A14: 盐酸(折百) | C14: ='F55'!C14 -> 0 | D14: =IF($F$3=0,,F14/$F$3) -> 0 | E14: =C14*D14 -> 0 | F14: ='F55'!F14+'F42'!F14+'F60'!F14+'F90'!F14 -> 0 | G14: ='F55'!G14+'F42'!G14+'F60'!G14+'F90'!G14 -> 0 | I14: 盐酸(折百) | K14: ='F55'!K14 -> 1.0336348 | L14: =IF($N$3=0,,N14/$N$3) -> 4.5394438 | M14: =K14*L14 -> 4.6921269 | N14: ='F55'!N14+'F42'!N14+'F60'!N14+'F90'!N14 -> 262991.6 | O14: ='F55'!O14+'F42'!O14+'F60'!O14+'F90'!O14 -> 271837.26
A15: 氢氧化钠(折百) | C15: ='F55'!C15 -> 0 | D15: =IF($F$3=0,,F15/$F$3) -> 0 | E15: =C15*D15 -> 0 | F15: ='F55'!F15+'F42'!F15+'F60'!F15+'F90'!F15 -> 0 | G15: ='F55'!G15+'F42'!G15+'F60'!G15+'F90'!G15 -> 0 | I15: 氢氧化钠(折百) | K15: ='F55'!K15 -> 3.1653036 | L15: =IF($N$3=0,,N15/$N$3) -> 5.0423611 | M15: =K15*L15 -> 15.960604 | N15: ='F55'!N15+'F42'!N15+'F60'!N15+'F90'!N15 -> 292128 | O15: ='F55'!O15+'F42'!O15+'F60'!O15+'F90'!O15 -> 924673.82
A16: 硅藻土 | C16: ='F55'!C16 -> 0 | D16: =IF($F$3=0,,F16/$F$3) -> 0 | E16: =C16*D16 -> 0 | F16: ='F55'!F16+'F42'!F16+'F60'!F16+'F90'!F16 -> 0 | G16: ='F55'!G16+'F42'!G16+'F60'!G16+'F90'!G16 -> 0 | I16: 硅藻土 | K16: ='F55'!K16 -> 2.60487 | L16: =IF($N$3=0,,N16/$N$3) -> 0.76499838 | M16: =K16*L16 -> 1.9927213 | N16: ='F55'!N16+'F42'!N16+'F60'!N16+'F90'!N16 -> 44320 | O16: ='F55'!O16+'F42'!O16+'F60'!O16+'F90'!O16 -> 115447.84
A17: 活性炭 | C17: ='F55'!C17 -> 0 | D17: =IF($F$3=0,,F17/$F$3) -> 0 | E17: =C17*D17 -> 0 | F17: ='F55'!F17+'F42'!F17+'F60'!F17+'F90'!F17 -> 0 | G17: ='F55'!G17+'F42'!G17+'F60'!G17+'F90'!G17 -> 0 | I17: 活性炭 | K17: ='F55'!K17 -> 7.0797015 | L17: =IF($N$3=0,,N17/$N$3) -> 1.5935165 | M17: =K17*L17 -> 11.281621 | N17: ='F55'!N17+'F42'!N17+'F60'!N17+'F90'!N17 -> 92320 | O17: ='F55'!O17+'F42'!O17+'F60'!O17+'F90'!O17 -> 653598.04
A18: 淀粉酶 | C18: ='F55'!C18 -> 0 | D18: =IF($F$3=0,,F18/$F$3) -> 0 | E18: =C18*D18 -> 0 | F18: ='F55'!F18+'F42'!F18+'F60'!F18+'F90'!F18 -> 0 | G18: ='F55'!G18+'F42'!G18+'F60'!G18+'F90'!G18 -> 0 | I18: 淀粉酶 | K18: ='F55'!K18 -> 47.801409 | L18: =IF($N$3=0,,N18/$N$3) -> 0.08242029 | M18: =K18*L18 -> 3.939806 | N18: ='F55'!N18+'F42'!N18+'F60'!N18+'F90'!N18 -> 4775 | O18: ='F55'!O18+'F42'!O18+'F60'!O18+'F90'!O18 -> 228251.73
A19: 复合糖化酶 | C19: ='F55'!C19 -> 0 | D19: =IF($F$3=0,,F19/$F$3) -> 0 | E19: =C19*D19 -> 0 | F19: ='F55'!F19+'F42'!F19+'F60'!F19+'F90'!F19 -> 0 | G19: ='F55'!G19+'F42'!G19+'F60'!G19+'F90'!G19 -> 0 | I19: 复合糖化酶 | K19: ='F55'!K19 -> 32.197431 | L19: =IF($N$3=0,,N19/$N$3) -> 0.16059442 | M19: =K19*L19 -> 5.1707279 | N19: ='F55'!N19+'F42'!N19+'F60'!N19+'F90'!N19 -> 9304 | O19: ='F55'!O19+'F42'!O19+'F60'!O19+'F90'!O19 -> 299564.9
A20: 异构酶 | C20: ='F55'!C20 -> 0 | D20: =IF($F$3=0,,F20/$F$3) -> 0 | E20: =C20*D20 -> 0 | F20: ='F55'!F20+'F42'!F20+'F60'!F20+'F90'!F20 -> 0 | G20: ='F55'!G20+'F42'!G20+'F60'!G20+'F90'!G20 -> 0 | I20: 异构酶 | K20: ='F55'!K20 -> 218.57702 | L20: =IF($N$3=0,,N20/$N$3) -> 0.097368137 | M20: =K20*L20 -> 21.282437 | N20: ='F55'!N20+'F42'!N20+'F60'!N20+'F90'!N20 -> 5641 | O20: ='F55'!O20+'F42'!O20+'F60'!O20+'F90'!O20 -> 1232993
A21: 硫酸镁 | C21: ='F55'!C21 -> 0 | D21: =IF($F$3=0,,F21/$F$3) -> 0 | E21: =C21*D21 -> 0 | F21: ='F55'!F21+'F42'!F21+'F60'!F21+'F90'!F21 -> 0 | G21: ='F55'!G21+'F42'!G21+'F60'!G21+'F90'!G21 -> 0 | I21: 硫酸镁 | K21: ='F55'!K21 -> 0.97947435 | L21: =IF($N$3=0,,N21/$N$3) -> 0.49452174 | M21: =K21*L21 -> 0.48437136 | N21: ='F55'!N21+'F42'!N21+'F60'!N21+'F90'!N21 -> 28650 | O21: ='F55'!O21+'F42'!O21+'F60'!O21+'F90'!O21 -> 28061.94
A22: 焦亚硫酸钠 | C22: ='F55'!C22 -> 0 | D22: =IF($F$3=0,,F22/$F$3) -> 0 | E22: =C22*D22 -> 0 | F22: ='F55'!F22+'F42'!F22+'F60'!F22+'F90'!F22 -> 0 | G22: ='F55'!G22+'F42'!G22+'F60'!G22+'F90'!G22 -> 0 | I22: 焦亚硫酸钠 | K22: ='F55'!K22 -> 1.8560801 | L22: =IF($N$3=0,,N22/$N$3) -> 0.29084437 | M22: =K22*L22 -> 0.53983046 | N22: ='F55'!N22+'F42'!N22+'F60'!N22+'F90'!N22 -> 16850 | O22: ='F55'!O22+'F42'!O22+'F60'!O22+'F90'!O22 -> 31274.95
A23: 树脂 | E23: =IF($F$3=0,0,G23/$F$3) -> 0 | F23: ='F55'!F23+'F42'!F23+'F60'!F23 -> 0 | G23: ='F55'!G23+'F42'!G23+'F60'!G23+'F90'!G23 -> #DIV/0! | I23: 树脂 | M23: =IF($N$3=0,0,O23/$N$3) -> #DIV/0! | N23: ='F55'!N23+'F42'!N23+'F60'!N23+'F90'!N23 -> 0 | O23: ='F55'!O23+'F42'!O23+'F60'!O23+'F90'!O23 -> #DIV/0!
A24: 其他 | E24: =IF($F$3=0,0,G24/$F$3) -> 0 | F24: ='F55'!F24+'F42'!F24+'F60'!F24 -> 0 | G24: ='F55'!G24+'F42'!G24+'F60'!G24+'F90'!G24 -> #DIV/0! | I24: 其他 | M24: =O24/N3 -> #DIV/0! | N24: ='F55'!N24+'F42'!N24+'F60'!N24+'F90'!N24 -> 0 | O24: ='F55'!O24+'F42'!O24+'F60'!O24+'F90'!O24 -> #DIV/0!
A25: (三)包装物 | E25: =IF($F$3=0,,G25/$F$3) -> 0 | G25: ='F55'!G25+'F60'!G25+'F42'!G25+'F90'!G25 -> 0 | I25: (三)包装物 | M25: =IF($N$3=0,,O25/$N$3) -> 0 | O25: ='F55'!O25+'F60'!O25+'F42'!O25+'F90'!O25 -> 0
A26: (四)动力能源 | E26: =SUM(E27:E30) -> 0 | G26: =SUM(G27:G30) -> 0 | I26: (四)动力能源 | M26: =SUM(M27:M30) -> #DIV/0! | O26: =SUM(O27:O30) -> #DIV/0!
A27: 1、蒸汽 | B27: 吨 | C27: ='F55'!C27 -> 0 | D27: =IF($F$3=0,0,F27/$F$3) -> 0 | E27: =C27*D27 -> 0 | F27: ='F55'!F27+'F42'!F27+'F60'!F27+'F90'!F27 -> 0 | G27: ='F55'!G27+'F42'!G27+'F60'!G27+'F90'!G27 -> 0 | I27: 1、蒸汽 | J27: 吨 | K27: ='F55'!K27 -> 374.79903 | L27: =IF($N$3=0,0,N27/$N$3) -> 0.30803612 | M27: =K27*L27 -> 115.45164 | N27: ='F55'!N27+'F42'!N27+'F60'!N27+'F90'!N27 -> 17846 | O27: ='F55'!O27+'F42'!O27+'F60'!O27+'F90'!O27 -> 6688663.4
A28: 2、电 | B28: 度 | C28: ='F55'!C28 -> 0 | D28: =IF($F$3=0,0,F28/$F$3) -> 0 | E28: =C28*D28 -> 0 | F28: ='F55'!F28+'F42'!F28+'F60'!F28+'F90'!F28 -> #DIV/0! | G28: ='F55'!G28+'F42'!G28+'F60'!G28+'F90'!G28 -> 0 | I28: 2、电 | J28: 度 | K28: ='F55'!K28 -> 0.6806368 | L28: =IF($N$3=0,0,N28/$N$3) -> #DIV/0! | M28: =K28*L28 -> #DIV/0! | N28: ='F55'!N28+'F42'!N28+'F60'!N28+'F90'!N28 -> #DIV/0! | O28: ='F55'!O28+'F42'!O28+'F60'!O28+'F90'!O28 -> #DIV/0!
A29: 3、水 | B29: 吨 | C29: ='F55'!C29 -> 0 | D29: =IF($F$3=0,0,F29/$F$3) -> 0 | E29: =C29*D29 -> 0 | F29: ='F55'!F29+'F42'!F29+'F60'!F29+'F90'!F29 -> #DIV/0! | G29: ='F55'!G29+'F42'!G29+'F60'!G29+'F90'!G29 -> 0 | I29: 3、水 | J29: 吨 | K29: ='F55'!K29 -> 5.8950402 | L29: =IF($N$3=0,0,N29/$N$3) -> #DIV/0! | M29: =K29*L29 -> #DIV/0! | N29: ='F55'!N29+'F42'!N29+'F60'!N29+'F90'!N29 -> #DIV/0! | O29: ='F55'!O29+'F42'!O29+'F60'!O29+'F90'!O29 -> #DIV/0!
A30: 4、其他 | B30: 吨 | C30: =IF(G30=0,0,G30/F30) -> 0 | D30: =IF($F$3=0,0,F30/$F$3) -> 0 | E30: =C30*D30 -> 0 | F30: ='F55'!F30+'F42'!F30+'F60'!F30+'F90'!F30 -> 0 | G30: ='F55'!G30+'F42'!G30+'F60'!G30+'F90'!G30 -> 0 | I30: 4、其他 | J30: 吨 | K30: ='F55'!K30 -> 0 | L30: =IF($N$3=0,0,N30/$N$3) -> 0 | M30: =K30*L30 -> 0 | N30: ='F55'!N30+'F42'!N30+'F60'!N30+'F90'!N30 -> 0 | O30: ='F55'!O30+'F42'!O30+'F60'!O30+'F90'!O30 -> 0
A31: (五)排污费 | E31: =IF(F$3=0,0,G31/F$3) -> 0 | F31: ='F55'!F31+'F42'!F31+'F60'!F31+'F90'!F31 -> 0 | G31: ='F55'!G31+'F60'!G31+'F42'!G31+'F90'!G31 -> #DIV/0! | I31: (五)排污费 | M31: =IF(N$3=0,0,O31/N$3) -> #DIV/0! | N31: ='F55'!N31+'F42'!N31+'F60'!N31+'F90'!N31 -> 0 | O31: ='F55'!O31+'F60'!O31+'F42'!O301+'F90'!O31 -> #DIV/0!
A32: 1.污水处理 | E32: =E31 -> 0 | F32: =F31 -> 0 | G32: =G31 -> #DIV/0! | I32: 1.污水处理 | M32: =M31 -> #DIV/0! | N32: =N31 -> 0 | O32: =O31 -> #DIV/0!
A33: 2.污水固定成本 | I33: 2.污水固定成本
A34: (六)增值税 | I34: (六)增值税
A35: 三、边际贡献 | E35: =E5-E10 -> 0 | G35: =G5-G10 -> #DIV/0! | I35: 三、边际贡献 | M35: =M5-M10 -> #DIV/0! | O35: =O5-O10 -> #DIV/0!
A36: 四、固定成本 | E36: =SUM(E37:E43) -> 0 | G36: =SUM(G37:G43) -> #DIV/0! | I36: 四、固定成本 | M36: =IF(N$3=0,0,O36/N$3) -> #DIV/0! | O36: =SUM(O37:O43) -> #DIV/0!
A37: （一）折旧与摊销 | E37: =IF(F$3=0,0,G37/F$3) -> 0 | G37: ='F55'!G37+'F42'!G37+'F60'!G37+'F90'!G37 -> #DIV/0! | I37: （一）折旧与摊销 | M37: =IF(N$3=0,0,O37/N$3) -> #DIV/0! | O37: ='F55'!O37+'F42'!O37+'F60'!O37+'F90'!O37 -> #DIV/0!
A38: （二）工资 | E38: =IF(F$3=0,0,G38/F$3) -> 0 | G38: ='F55'!G38+'F42'!G38+'F60'!G38+'F90'!G38 -> #DIV/0! | I38: （二）工资 | M38: =IF(N$3=0,0,O38/N$3) -> #DIV/0! | O38: ='F55'!O38+'F42'!O38+'F60'!O38+'F90'!O38 -> #DIV/0!
A39: （三）制造费用 | E39: =IF(F$3=0,0,G39/F$3) -> 0 | G39: ='F55'!G39+'F42'!G39+'F60'!G39+'F90'!G39 -> #DIV/0! | I39: （三）制造费用 | M39: =IF(N$3=0,0,O39/N$3) -> #DIV/0! | O39: ='F55'!O39+'F42'!O39+'F60'!O39+'F90'!O39 -> #DIV/0!
A40: （四）销售费用 | E40: =IF(F$3=0,0,G40/F$3) -> 0 | G40: ='F55'!G40+'F42'!G40+'F60'!G40+'F90'!G40 -> #DIV/0! | I40: （四）销售费用 | M40: =IF(N$3=0,0,O40/N$3) -> #DIV/0! | O40: ='F55'!O40+'F42'!O40+'F60'!O40+'F90'!O40 -> #DIV/0!
A41: （五）管理费用 | E41: =IF(F$3=0,0,G41/F$3) -> 0 | G41: ='F55'!G41+'F42'!G41+'F60'!G41+'F90'!G41 -> #DIV/0! | I41: （五）管理费用 | M41: =IF(N$3=0,0,O41/N$3) -> #DIV/0! | O41: ='F55'!O41+'F42'!O41+'F60'!O41+'F90'!O41 -> #DIV/0!
A42: （六）财务费用 | E42: =IF(F$3=0,0,G42/F$3) -> 0 | G42: ='F55'!G42+'F42'!G42+'F60'!G42+'F90'!G42 -> #DIV/0! | I42: （六）财务费用 | M42: =IF(N$3=0,0,O42/N$3) -> #DIV/0! | O42: ='F55'!O42+'F42'!O42+'F60'!O42+'F90'!O42 -> #DIV/0!
A43: （七）其他 | E43: =IF(F$3=0,0,G43/F$3) -> 0 | G43: ='F55'!G43+'F42'!G43+'F60'!G43+'F90'!G43 -> #DIV/0! | I43: （七） 其他 | M43: =IF(N$3=0,0,O43/N$3) -> #DIV/0! | O43: ='F55'!O43+'F42'!O43+'F60'!O43+'F90'!O43 -> #DIV/0!
A44: 其中：税金及附加 | E44: =IF(F$3=0,0,G44/F$3) -> 0 | G44: ='F55'!G44+'F60'!G44+'F42'!G44+'F90'!G44 -> #DIV/0! | I44: 其中：税金及附加 | M44: =IF(N$3=0,0,O44/N$3) -> #DIV/0! | O44: ='F55'!O44+'F60'!O44+'F42'!O44+'F90'!O44 -> #DIV/0!
A45: 其他业务收支 | E45: =IF(F$3=0,0,G45/F$3) -> 0 | G45: ='F55'!G45+'F60'!G45+'F42'!G45+'F90'!G45 -> #DIV/0! | I45: 其他业务收支 | M45: =IF(N$3=0,0,O45/N$3) -> #DIV/0! | O45: ='F55'!O45+'F60'!O45+'F42'!O45+'F90'!O45 -> #DIV/0!
A46: 营业外收支 | E46: =IF(F$3=0,0,G46/F$3) -> 0 | G46: ='F55'!G46+'F60'!G46+'F42'!G46+'F90'!G46 -> #DIV/0! | I46: 营业外收支 | M46: =IF(N$3=0,0,O46/N$3) -> #DIV/0! | O46: ='F55'!O46+'F60'!O46+'F42'!O46+'F90'!O46 -> #DIV/0!
A47: 投资收益+公允价值变动损益 | E47: =IF(F$3=0,0,G47/F$3) -> 0 | G47: ='F55'!G47+'F60'!G47+'F42'!G47+'F90'!G47 -> #DIV/0! | I47: 投资收益+公允价值变动损益 | M47: =IF(N$3=0,0,O47/N$3) -> #DIV/0! | O47: ='F55'!O47+'F60'!O47+'F42'!O47+'F90'!O47 -> #DIV/0!
A48: 其他收益 | E48: =IF(F$3=0,0,G48/F$3) -> 0 | G48: ='F55'!G48+'F60'!G48+'F42'!G48+'F90'!G48 -> #DIV/0! | I48: 其他收益 | M48: =IF(N$3=0,0,O48/N$3) -> #DIV/0! | O48: ='F55'!O48+'F60'!O48+'F42'!O48+'F90'!O48 -> #DIV/0!
A49: 资产减值损失 | E49: =IF(F$3=0,0,G49/F$3) -> 0 | G49: ='F55'!G49+'F60'!G49+'F42'!G49+'F90'!G49 -> #DIV/0! | I49: 资产减值损失 | M49: =IF(N$3=0,0,O49/N$3) -> #DIV/0! | O49: ='F55'!O49+'F60'!O49+'F42'!O49+'F90'!O49 -> #DIV/0!
A50: 其他 | E50: =IF(F$3=0,0,G50/F$3) -> 0 | G50: ='F55'!G50+'F60'!G50+'F42'!G50+'F90'!G50 -> #DIV/0! | I50: 其他 | M50: =IF(N$3=0,0,O50/N$3) -> #DIV/0! | O50: ='F55'!O50+'F60'!O50+'F42'!O50+'F90'!O50 -> #DIV/0!
A51: 五、完全成本 | B51: 元 | E51: =E36+E10 -> 0 | G51: =G36+G10 -> #DIV/0! | I51: 五、完全成本 | J51: 元 | M51: =M36+M10 -> #DIV/0! | O51: =O36+O10 -> #DIV/0!
A52: 六、利润总额 | E52: =E35-E36 -> 0 | G52: =G35-G36 -> #DIV/0! | I52: 六、利润总额 | M52: =M35-M36 -> #DIV/0! | O52: =O35-O36 -> #DIV/0!
A53: 七、现金流 | E53: =E52+E37 -> 0 | G53: =G52+G37 -> #DIV/0! | I53: 七、现金流 | M53: =M52+M37 -> #DIV/0! | O53: =O52+O37 -> #DIV/0!
A54: 加工费 | B54: 元 | E54: =E10-E11+E36-E25 -> 0 | G54: =G10-G11+G36-G25 -> #DIV/0! | I54: 加工费 | J54: 元 | M54: =M10-M11+M36-M25 -> #DIV/0! | O54: =O10-O11+O36-O25 -> #DIV/0!
A55: 其他业务收支-糖渣 | E55: =IF(F$3=0,0,G55/F$3) -> 0 | G55: ='F55'!G55+'F60'!G55+'F42'!G55+'F90'!G55 -> #DIV/0! | I55: 其他业务收支-糖渣 | M55: =IF(N$3=0,0,O55/N$3) -> #DIV/0! | O55: ='F55'!O55+'F60'!O55+'F42'!O55+'F90'!O55 -> #DIV/0!

Sheet 专用糖
A1: =CONCATENATE("糖浆老线综合成本利润表_不含税(2025年"&mth&"月)") -> 糖浆老线综合成本利润表_不含税(2025年8月) | I1: =CONCATENATE("糖浆老线综合成本利润表_不含税(2025年1-"&mth&"月)") -> 糖浆老线综合成本利润表_不含税(2025年1-8月)
A3: 产量 | E3: 本月产量 | F3: =OFFSET(基础表!C13,0,mth-1,1,1) -> 0 | G3: 吨 | M3: 本年产量 | N3: =基础表!O13 -> 38999.431 | O3: 吨
B4: 单位 | C4: 单价 | D4: 单耗 | E4: 单位成本 | F4: 总耗量 | G4: 总成本 | J4: 单位 | K4: 单价 | L4: 单耗 | M4: 单位成本 | N4: 总耗量 | O4: 总成本
A5: 一、收入 | E5: =E6-E7 -> #DIV/0! | G5: =G6-G7 -> #DIV/0! | I5: 一、收入 | M5: =M6-M7 -> 2838.4466 | O5: =O6-O7 -> 1.106978e+08
A6: （一）销售价格 | E6: =OFFSET(销售收入及运费!C78,0,mth-1,1,1) -> 0 | G6: =E6*$F$3 -> 0 | I6: （一）销售价格 | M6: =销售收入及运费!O78 -> 2907.4664 | O6: =M6*$N$3 -> 1.1338954e+08
A7: （二）物流费 | E7: =E8+E9 -> #DIV/0! | G7: =E7*$F$3 -> #DIV/0! | I7: （二）物流费 | M7: =M8+M9 -> 69.019841 | O7: =M7*$N$3 -> 2691734.5
A8: 1、运费 | E8: =OFFSET(销售收入及运费!C135,0,mth-1,1,1)/1.09/OFFSET(销售收入及运费!C18,0,mth-1,1,1) -> #DIV/0! | G8: =E8*$F$3 -> #DIV/0! | I8: 1、运费 | M8: =销售收入及运费!O135/1.09/销售收入及运费!O18 -> 58.974504 | O8: =M8*$N$3 -> 2299972.1
A9: 2、包装费、租赁费等 | E9: =(OFFSET(销售收入及运费!C155,0,mth-1,1,1)/1.13+OFFSET(销售收入及运费!C175,0,mth-1,1,1)/1.13)/(OFFSET(销售收入及运费!C18,0,mth-1,1,1)) -> #DIV/0! | G9: =E9*$F$3 -> #DIV/0! | I9: 2、包装费、租赁费等 | M9: =(销售收入及运费!O155+销售收入及运费!O175)/1.13/销售收入及运费!O18 -> 10.045337 | O9: =M9*$N$3 -> 391762.42
A10: 二、变动成本 | E10: =E11+E13+E28+E33 -> 0 | G10: =G11+G13+G28+G33+G27 -> #DIV/0! | I10: 二、变动成本 | M10: =M11+M13+M28+M33 -> #DIV/0! | O10: =O11+O13+O28+O33+O27 -> #DIV/0! | Q10: =F3*0.84 -> 0
A11: (一)淀粉 | B11: 吨 | C11: =C12 -> 0 | D11: =IF(C11=0,0,E11/C11) -> 0 | E11: =E12 -> 0 | F11: =F12 -> 0 | G11: =G12 -> 0 | I11: (一)淀粉 | J11: 吨 | K11: =IF(N11=0,0,O11/N11) -> 2498.3033 | L11: =IF(K11=0,0,M11/K11) -> 0.84925716 | M11: =M12 -> 2121.702 | N11: =N12 -> 33120.546 | O11: =O12 -> 82745169
A12: 1、淀粉(14%) | B12: 吨 | C12: =OFFSET(分配表!C70,0,mth-1,1,1) -> 0 | D12: =IF(VALUE($F$3)=0,0,F12/$F$3) -> 0 | E12: =C12*D12 -> 0 | F12: =OFFSET(分配表!C84,0,mth-1,1,1) -> 0 | G12: =E12*F3 -> 0 | I12: 1、淀粉(14%) | J12: 吨 | K12: =分配表!O70 -> 2498.3033 | L12: =IF($N$3=0,0,N12/$N$3) -> 0.84925716 | M12: =K12*L12 -> 2121.702 | N12: =分配表!O84 -> 33120.546 | O12: =K12*N12 -> 82745169
A13: (二)辅助材料 | E13: =IF(VALUE($F$3)=0,0,G13/$F$3) -> 0 | G13: =OFFSET(分配表!C281,0,mth-1) -> 0 | I13: (二)辅助材料 | M13: =IF($N$3=0,0,O13/$N$3) -> 45.096402 | O13: =分配表!O281 -> 1758734
A14: 活性炭 | C14: =OFFSET(分配表!C240,0,mth-1,1,1) -> 0 | D14: =IF(VALUE($F$3)=0,0,F14/$F$3) -> 0 | E14: =C14*D14 -> 0 | F14: =OFFSET(分配表!C226,0,mth-1) -> 0 | G14: =E14*$F$3 -> 0 | I14: 活性炭 | K14: =分配表!O240 -> 3.5720579 | L14: =IF($N$3=0,,N14/$N$3) -> 3.7759525 | M14: =K14*L14 -> 13.487921 | N14: =分配表!O226 -> 147260 | O14: =M14*$N$3 -> 526021.24
A15: 食用级盐酸（折百） | C15: =OFFSET(分配表!C241,0,mth-1,1,1) -> 0 | D15: =IF(VALUE($F$3)=0,0,F15/$F$3) -> 0 | E15: =C15*D15 -> 0 | F15: =OFFSET(分配表!C227,0,mth-1) -> 0 | G15: =E15*$F$3 -> 0 | I15: 食用级盐酸（折百） | K15: =分配表!O241 -> 1.0323967 | L15: =IF($N$3=0,,N15/$N$3) -> 3.6441429 | M15: =K15*L15 -> 3.762201 | N15: =分配表!O227 -> 142119.5 | O15: =M15*$N$3 -> 146723.7
A16: 食用级液碱（折百） | C16: =OFFSET(分配表!C242,0,mth-1,1,1) -> 0 | D16: =IF(VALUE($F$3)=0,0,F16/$F$3) -> 0 | E16: =C16*D16 -> 0 | F16: =OFFSET(分配表!C228,0,mth-1) -> 0 | G16: =E16*$F$3 -> 0 | I16: 食用级液碱（折百） | K16: =分配表!O242 -> 3.1537633 | L16: =IF($N$3=0,,N16/$N$3) -> 4.4881065 | M16: =K16*L16 -> 14.154425 | N16: =分配表!O228 -> 175033.6 | O16: =M16*$N$3 -> 552014.54
A17: 纯碱 | C17: =OFFSET(分配表!C243,0,mth-1,1,1) -> 0 | D17: =IF(VALUE($F$3)=0,0,F17/$F$3) -> 0 | E17: =C17*D17 -> 0 | F17: =OFFSET(分配表!C229,0,mth-1) -> 0 | G17: =E17*$F$3 -> 0 | I17: 纯碱 | K17: =分配表!O243 -> 2.1446133 | L17: =IF($N$3=0,,N17/$N$3) -> 0.076924199 | M17: =K17*L17 -> 0.16497266 | N17: =分配表!O229 -> 3000 | O17: =M17*$N$3 -> 6433.84
A18: 真菌酶 | C18: =OFFSET(分配表!C244,0,mth-1,1,1) -> 0 | D18: =IF(VALUE($F$3)=0,0,F18/$F$3) -> 0 | E18: =C18*D18 -> 0 | F18: =OFFSET(分配表!C230,0,mth-1) -> 0 | G18: =E18*$F$3 -> 0 | I18: 真菌酶 | K18: =分配表!O244 -> 35.398243 | L18: =IF($N$3=0,,N18/$N$3) -> 0.035308207 | M18: =K18*L18 -> 1.2498485 | N18: =分配表!O230 -> 1377 | O18: =M18*$N$3 -> 48743.38
A19: 2X型高温酶 | C19: =OFFSET(分配表!C245,0,mth-1,1,1) -> 0 | D19: =IF(VALUE($F$3)=0,0,F19/$F$3) -> 0 | E19: =C19*D19 -> 0 | F19: =OFFSET(分配表!C231,0,mth-1) -> 0 | G19: =E19*$F$3 -> 0 | I19: 2X型高温酶 | K19: =分配表!O245 -> 18.550904 | L19: =IF($N$3=0,,N19/$N$3) -> 0.13864305 | M19: =K19*L19 -> 2.5719539 | N19: =分配表!O231 -> 5407 | O19: =M19*$N$3 -> 100304.74
A20: 普鲁兰酶 | C20: =OFFSET(分配表!C246,0,mth-1,1,1) -> 0 | D20: =IF(VALUE($F$3)=0,0,F20/$F$3) -> 0 | E20: =C20*D20 -> 0 | F20: =OFFSET(分配表!C232,0,mth-1) -> 0 | G20: =E20*$F$3 -> 0 | I20: 普鲁兰酶 | K20: =分配表!O246 -> 35.398211 | L20: =IF($N$3=0,,N20/$N$3) -> 0.016910503 | M20: =K20*L20 -> 0.59860155 | N20: =分配表!O232 -> 659.5 | O20: =M20*$N$3 -> 23345.12
A21: β淀粉酶 | C21: =OFFSET(分配表!C247,0,mth-1,1,1) -> 0 | D21: =IF(VALUE($F$3)=0,0,F21/$F$3) -> 0 | E21: =C21*D21 -> 0 | F21: =OFFSET(分配表!C233,0,mth-1) -> 0 | G21: =E21*$F$3 -> 0 | I21: β淀粉酶 | K21: =分配表!O247 -> 62.022154 | L21: =IF($N$3=0,,N21/$N$3) -> 0.083090956 | M21: =K21*L21 -> 5.1534801 | N21: =分配表!O233 -> 3240.5 | O21: =M21*$N$3 -> 200982.79
A22: DX1.5X强效糖化酶 | C22: =OFFSET(分配表!C248,0,mth-1,1,1) -> 0 | D22: =IF(VALUE($F$3)=0,0,F22/$F$3) -> 0 | E22: =C22*D22 -> 0 | F22: =OFFSET(分配表!C234,0,mth-1) -> 0 | G22: =E22*$F$3 -> 0 | I22: DX1.5X强效糖化酶 | K22: =分配表!O248 -> 25.292485 | L22: =IF($N$3=0,,N22/$N$3) -> 0.033231254 | M22: =K22*L22 -> 0.84050098 | N22: =分配表!O234 -> 1296 | O22: =M22*$N$3 -> 32779.06
A23: 转甘酶 | C23: =OFFSET(分配表!C249,0,mth-1,1,1) -> 0 | D23: =IF(VALUE($F$3)=0,0,F23/$F$3) -> 0 | E23: =C23*D23 -> 0 | F23: =OFFSET(分配表!C235,0,mth-1) -> 0 | G23: =E23*$F$3 -> 0 | I23: 转甘酶 | K23: =分配表!O249 -> 529.20353 | L23: =IF($N$3=0,,N23/$N$3) -> 0.00384621 | M23: =K23*L23 -> 2.0354279 | N23: =分配表!O235 -> 150 | O23: =M23*$N$3 -> 79380.53
A24: 葡糖淀粉酶 | C24: =OFFSET(分配表!C250,0,mth-1,1,1) -> 0 | D24: =IF(VALUE($F$3)=0,0,F24/$F$3) -> 0 | E24: =C24*D24 -> 0 | F24: =OFFSET(分配表!C236,0,mth-1) -> 0 | G24: =E24*$F$3 -> 0 | I24: 葡糖淀粉酶 | K24: =分配表!O250 -> 0 | L24: =IF($N$3=0,,N24/$N$3) -> 0 | M24: =K24*L24 -> 0 | N24: =分配表!O236 -> 0 | O24: =M24*$N$3 -> 0
A25: 麦芽糖淀粉酶 | C25: =OFFSET(分配表!C251,0,mth-1,1,1) -> 0 | D25: =IF(VALUE($F$3)=0,0,F25/$F$3) -> 0 | E25: =C25*D25 -> 0 | F25: =OFFSET(分配表!C237,0,mth-1) -> 0 | G25: =E25*$F$3 -> 0 | I25: 麦芽糖淀粉酶 | K25: =分配表!O251 -> 0 | L25: =IF($N$3=0,,N25/$N$3) -> 0 | M25: =K25*L25 -> 0 | N25: =分配表!O237 -> 0 | O25: =M25*$N$3 -> 0
A26: 其他 | E26: =G26/F3 -> #DIV/0! | G26: =OFFSET(分配表!C280,0,mth-1,1,1) -> 0 | I26: 其他 | M26: =O26/N3 -> 1.0770693 | O26: =分配表!O280 -> 42005.09
A27: (三)包装物 | I27: (三)包装物
A28: (四)动力能源 | E28: =SUM(E29:E32) -> 0 | G28: =SUM(G29:G32) -> 0 | I28: (四)动力能源 | M28: =SUM(M29:M32) -> 215.05444 | O28: =SUM(O29:O32) -> 8387000.8
A29: 1、蒸汽 | B29: 吨 | C29: ='F55'!C27 -> 0 | D29: =IF(VALUE($F$3)=0,0,F29/$F$3) -> 0 | E29: =C29*D29 -> 0 | F29: =OFFSET(分配表!C314,0,mth-1,1,1) -> 0 | G29: =E29*F$3 -> 0 | I29: 1、蒸汽 | J29: 吨 | K29: ='F55'!K27 -> 374.79903 | L29: =IF($N$3=0,0,N29/$N$3) -> 0.43431403 | M29: =K29*L29 -> 162.78047 | N29: =分配表!O314 -> 16938 | O29: =M29*N$3 -> 6348345.9
A30: 2、电 | B30: 度 | C30: ='F55'!C28 -> 0 | D30: =IF(VALUE($F$3)=0,0,F30/$F$3) -> 0 | E30: =C30*D30 -> 0 | F30: =OFFSET(分配表!C333,0,mth-1,1,1) -> 0 | G30: =E30*F$3 -> 0 | I30: 2、电 | J30: 度 | K30: ='F55'!K28 -> 0.6806368 | L30: =IF($N$3=0,0,N30/$N$3) -> 61.258714 | M30: =K30*L30 -> 41.694935 | N30: =分配表!O333 -> 2389055 | O30: =M30*N$3 -> 1626078.7
A31: 3、水 | B31: 吨 | C31: ='F55'!C29 -> 0 | D31: =IF(VALUE($F$3)=0,0,F31/$F$3) -> 0 | E31: =C31*D31 -> 0 | F31: =OFFSET(分配表!C351,0,mth-1,1,1) -> 0 | G31: =E31*F$3 -> 0 | I31: 3、水 | J31: 吨 | K31: ='F55'!K29 -> 5.8950402 | L31: =IF($N$3=0,0,N31/$N$3) -> 1.7945646 | M31: =K31*L31 -> 10.579031 | N31: =分配表!O351 -> 69987 | O31: =M31*N$3 -> 412576.18
A32: 4、天然气 | B32: M3 | C32: ='F55'!C30 -> 0 | D32: =IF(VALUE($F$3)=0,0,F32/$F$3) -> 0 | E32: =C32*D32 -> 0 | F32: =OFFSET(分配表!C367,0,mth-1,1,1) -> 0 | G32: =E32*F$3 -> 0 | I32: 4、天然气 | J32: M3 | K32: ='F55'!K30 -> 0 | L32: =IF($N$3=0,0,N32/$N$3) -> 0 | M32: =K32*L32 -> 0 | N32: =分配表!O367 -> 0 | O32: =M32*N$3 -> 0
A33: (四)污水 | E33: =IF(VALUE($F$3)=0,0,G33/$F$3) -> 0 | G33: =OFFSET(分配表!C379,0,mth-1,1,1) -> #DIV/0! | I33: (四)污水 | M33: =IF($N$3=0,,O33/$N$3) -> #DIV/0! | O33: =分配表!O379 -> #DIV/0!
A34: 1.污水处理 | E34: =E33 -> 0 | G34: =G33 -> #DIV/0! | I34: 1.污水处理 | M34: =M33 -> #DIV/0! | O34: =O33 -> #DIV/0!
A35: 2.污水固定成本 | I35: 2.污水固定成本
A36: (五)增值税 | I36: (五)增值税
A37: 三、边际贡献 | E37: =E5-E10 -> #DIV/0! | G37: =G5-G10 -> #DIV/0! | I37: 三、边际贡献 | M37: =M5-M10 -> #DIV/0! | O37: =O5-O10 -> #DIV/0!
A38: 四、固定成本 | E38: =SUM(E39:E45) -> 0 | G38: =SUM(G39:G45) -> #DIV/0! | I38: 四、固定成本 | M38: =IF(N$3=0,0,O38/N$3) -> #DIV/0! | O38: =SUM(O39:O45) -> #DIV/0!
A39: （一）折旧与摊销 | E39: =IF(VALUE($F$3)=0,0,G39/$F$3) -> 0 | G39: =OFFSET(分配表!C412,0,mth-1,1,1) -> #DIV/0! | I39: （一）折旧与摊销 | M39: =IF($N$3=0,0,O39/$N$3) -> #DIV/0! | O39: =分配表!O412 -> #DIV/0!
A40: （二）工资 | E40: =IF(VALUE($F$3)=0,0,G40/$F$3) -> 0 | G40: =OFFSET(分配表!C432,0,mth-1,1,1) -> #DIV/0! | I40: （二）工资 | M40: =IF($N$3=0,0,O40/$N$3) -> #DIV/0! | O40: =分配表!O432 -> #DIV/0!
A41: （三）制造费用 | E41: =IF(VALUE($F$3)=0,0,G41/$F$3) -> 0 | G41: =OFFSET(分配表!C452,0,mth-1,1,1) -> #DIV/0! | I41: （三）制造费用 | M41: =IF($N$3=0,0,O41/$N$3) -> #DIV/0! | O41: =分配表!O452 -> #DIV/0!
A42: （四）销售费用 | E42: =IF(VALUE($F$3)=0,0,G42/$F$3) -> 0 | G42: =OFFSET(分配表!C472,0,mth-1,1,1) -> #DIV/0! | I42: （四）销售费用 | M42: =IF($N$3=0,0,O42/$N$3) -> #DIV/0! | O42: =分配表!O472 -> #DIV/0!
A43: （五）管理费用 | E43: =IF(VALUE($F$3)=0,0,G43/$F$3) -> 0 | G43: =OFFSET(分配表!C492,0,mth-1,1,1) -> #DIV/0! | I43: （五）管理费用 | M43: =IF($N$3=0,0,O43/$N$3) -> #DIV/0! | O43: =分配表!O492 -> #DIV/0!
A44: （六）财务费用 | E44: =IF(VALUE($F$3)=0,0,G44/$F$3) -> 0 | G44: =OFFSET(分配表!C508,0,mth-1,1,1) -> #DIV/0! | I44: （六）财务费用 | M44: =IF($N$3=0,0,O44/$N$3) -> #DIV/0! | O44: =分配表!O508 -> #DIV/0!
A45: （七）其他 | E45: =IF(VALUE($F$3)=0,0,G45/$F$3) -> 0 | G45: =OFFSET(分配表!C530,0,mth-1,1,1) -> #DIV/0! | I45: （七） 其他 | M45: =IF($N$3=0,0,O45/$N$3) -> #DIV/0! | O45: =分配表!O530 -> #DIV/0!
A46: 其中：税金及附加 | E46: =IF(VALUE($F$3)=0,0,G46/$F$3) -> 0 | G46: =OFFSET(分配表!C542,0,mth-1,1,1) -> #DIV/0! | I46: 其中：税金及附加 | M46: =IF($N$3=0,0,O46/$N$3) -> #DIV/0! | O46: =分配表!O542 -> #DIV/0!
A47: 其他业务收支 | E47: =IF(VALUE($F$3)=0,0,G47/$F$3) -> 0 | G47: =OFFSET(分配表!C554,0,mth-1,1,1) -> #DIV/0! | I47: 其他业务收支 | M47: =IF($N$3=0,0,O47/$N$3) -> #DIV/0! | O47: =分配表!O554 -> #DIV/0!
A48: 营业外收支 | E48: =IF(VALUE($F$3)=0,0,G48/$F$3) -> 0 | G48: =OFFSET(分配表!C602,0,mth-1,1,1) -> #DIV/0! | I48: 营业外收支 | M48: =IF($N$3=0,0,O48/$N$3) -> #DIV/0! | O48: =分配表!O602 -> #DIV/0!
A49: 投资收益+公允价值变动损益 | E49: =IF(VALUE($F$3)=0,0,G49/$F$3) -> 0 | G49: =OFFSET(分配表!C566,0,mth-1,1,1) -> #DIV/0! | I49: 投资收益+公允价值变动损益 | M49: =IF($N$3=0,0,O49/$N$3) -> #DIV/0! | O49: =分配表!O566 -> #DIV/0!
A50: 其他收益 | E50: =IF(VALUE($F$3)=0,0,G50/$F$3) -> 0 | G50: =OFFSET(分配表!C578,0,mth-1,1,1) -> #DIV/0! | I50: 其他收益 | M50: =IF($N$3=0,0,O50/$N$3) -> #DIV/0! | O50: =分配表!O578 -> #DIV/0!
A51: 资产减值损失 | E51: =IF(VALUE($F$3)=0,0,G51/$F$3) -> 0 | G51: =OFFSET(分配表!C590,0,mth-1,1,1) -> #DIV/0! | I51: 资产减值损失 | M51: =IF($N$3=0,0,O51/$N$3) -> #DIV/0! | O51: =分配表!O590 -> #DIV/0!
A52: 其他 | E52: =IF(VALUE($F$3)=0,0,G52/$F$3) -> 0 | G52: =OFFSET(分配表!C614,0,mth-1,1,1) -> #DIV/0! | I52: 其他 | M52: =IF($N$3=0,0,O52/$N$3) -> #DIV/0! | O52: =分配表!O614 -> #DIV/0!
A53: 五、完全成本 | B53: 元 | E53: =E38+E10 -> 0 | G53: =G38+G10 -> #DIV/0! | I53: 五、完全成本 | J53: 元 | M53: =M38+M10 -> #DIV/0! | O53: =O38+O10 -> #DIV/0!
A54: 六、利润总额 | E54: =E37-E38 -> #DIV/0! | G54: =G37-G38 -> #DIV/0! | I54: 六、利润总额 | M54: =M37-M38 -> #DIV/0! | O54: =O37-O38 -> #DIV/0!
A55: 七、现金流 | E55: =E54+E39 -> #DIV/0! | G55: =G54+G39 -> #DIV/0! | I55: 七、现金流 | M55: =M54+M39 -> #DIV/0! | O55: =O54+O39 -> #DIV/0!
A56: 加工费 | B56: 元 | E56: =E10-E11-E27+E38 -> 0 | G56: =G10-G11-G27+G38 -> #DIV/0! | I56: 加工费 | J56: 元 | M56: =M10-M11-M27+M38 -> #DIV/0! | O56: =O10-O11-O27+O38 -> #DIV/0!
A57: 其他业务收支-糖渣 | E57: =IF(VALUE($F$3)=0,0,G57/$F$3) -> 0 | G57: =OFFSET(分配表!C627,0,mth-1,1,1) -> #DIV/0! | I57: 其他业务收支-糖渣 | M57: =IF($N$3=0,0,O57/$N$3) -> #DIV/0! | O57: =分配表!O627 -> #DIV/0!

Sheet F90
A1: =CONCATENATE("果葡糖浆F90综合成本利润表_不含税(2025年"&mth&"月)") -> 果葡糖浆F90综合成本利润表_不含税(2025年8月) | I1: =CONCATENATE("果葡糖浆F90综合成本利润表_不含税(2025年1-"&mth&"月)") -> 果葡糖浆F90综合成本利润表_不含税(2025年1-8月)
A3: 自产部分 | E3: 自产产量 | F3: =OFFSET(基础表!C11,0,mth-1,1,1) -> 0 | M3: 自产产量 | N3: =基础表!O11 -> 36.72 | O3: 吨
B4: 单位 | C4: 单价 | D4: 单耗 | E4: 单位成本 | F4: 总耗量 | G4: 总成本 | J4: 单位 | K4: 单价 | L4: 单耗 | M4: 单位成本 | N4: 总耗量 | O4: 总成本
A5: 一、收入 | E5: =E6-E7 -> 0 | G5: =G6-G7 -> 0 | I5: 一、收入 | M5: =M6-M7 -> 3626.0359 | O5: =O6-O7 -> 133148.04
A6: （一）销售价格 | E6: =OFFSET(销售收入及运费!C77,0,mth-1,1,1) -> 0 | G6: =E6*$F$3 -> 0 | I6: （一）销售价格 | M6: =销售收入及运费!O77 -> 3679.725 | O6: =M6*$N$3 -> 135119.5
A7: （二）物流费 | E7: =SUM(E8:E9) -> 0 | G7: =E7*$F$3 -> 0 | I7: （二）物流费 | M7: =SUM(M8:M9) -> 53.689075 | O7: =M7*$N$3 -> 1971.4628
A8: 1、运费 | E8: =IFERROR(OFFSET(销售收入及运费!C134,0,mth-1,1,1)/1.09/OFFSET(销售收入及运费!C17,0,mth-1,1,1),"0") -> 0 | G8: =E8*$F$3 -> 0 | I8: 1、运费 | M8: =IFERROR(销售收入及运费!O134/1.09/销售收入及运费!O17,"0") -> 53.689075 | O8: =M8*$N$3 -> 1971.4628
A9: 2、包装费、租赁费等 | E9: =IFERROR((OFFSET(销售收入及运费!C154,0,mth-1,1,1)/1.13+OFFSET(销售收入及运费!C174,0,mth-1,1,1)/1.13)/OFFSET(销售收入及运费!C17,0,mth-1,1,1),"0") -> 0 | G9: =E9*$F$3 -> 0 | I9: 2、包装费、租赁费等 | M9: =IFERROR((销售收入及运费!O154+销售收入及运费!O174)/1.13/销售收入及运费!O17,"0") -> 0 | O9: =M9*$N$3 -> 0
A10: 二、变动成本 | E10: =E11+E13+E26+E31+E34+E25 -> 0 | G10: =G11+G13+G26+G31+G25 -> #DIV/0! | I10: 二、变动成本 | M10: =M11+M13+M26+M31+M34+M25 -> #DIV/0! | O10: =O11+O13+O26+O31+O25 -> #DIV/0!
A11: (一)淀粉 | B11: 吨 | C11: =C12 -> 0 | D11: =IF(C11=0,0,E11/C11) -> 0 | E11: =E12 -> 0 | F11: =F12 -> 0 | G11: =G12 -> 0 | I11: (一)淀粉 | J11: 吨 | K11: =IF(N11=0,0,O11/N11) -> 2453.7157 | L11: =IF(K11=0,0,M11/K11) -> 0.81284707 | M11: =M12 -> 1994.4956 | N11: =N12 -> 29.847744 | O11: =O12 -> 73237.879
A12: 1、淀粉(14%) | B12: 吨 | C12: =OFFSET(分配表!C69,0,mth-1,1,1) -> 0 | D12: =IF(VALUE($F$3)=0,0,F12/$F$3) -> 0 | E12: =C12*D12 -> 0 | F12: =OFFSET(分配表!C83,0,mth-1,1,1) -> 0 | G12: =E12*F3 -> 0 | I12: 1、淀粉(14%) | J12: 吨 | K12: =分配表!O69 -> 2453.7157 | L12: =IF($N$3=0,,N12/$N$3) -> 0.81284707 | M12: =K12*L12 -> 1994.4956 | N12: =分配表!O83 -> 29.847744 | O12: =K12*N12 -> 73237.879
A13: (二）辅料 | E13: =SUM(E14:E24) -> 0 | G13: =SUM(G14:G24) -> #DIV/0! | I13: (二）辅料 | M13: =SUM(M14:M24) -> #DIV/0! | O13: =SUM(O14:O24) -> #DIV/0!
A14: 盐酸(折百) | C14: =OFFSET(分配表!C179,0,mth-1,1,1) -> 0 | D14: =IF(VALUE($F$3)=0,0,F14/$F$3) -> 0 | E14: =C14*D14 -> 0 | F14: =OFFSET(分配表!C166,0,mth-1) -> 0 | G14: =E14*$F$3 -> 0 | I14: 盐酸(折百) | K14: =分配表!O179 -> 1.0336348 | L14: =IF($N$3=0,,N14/$N$3) -> 4.3055556 | M14: =K14*L14 -> 4.4503719 | N14: =分配表!O166 -> 158.1 | O14: =M14*$N$3 -> 163.41766
A15: 氢氧化钠(折百) | C15: =OFFSET(分配表!C180,0,mth-1,1,1) -> 0 | D15: =IF(VALUE($F$3)=0,0,F15/$F$3) -> 0 | E15: =C15*D15 -> 0 | F15: =OFFSET(分配表!C167,0,mth-1) -> 0 | G15: =E15*$F$3 -> 0 | I15: 氢氧化钠(折百) | K15: =分配表!O180 -> 3.1653036 | L15: =IF($N$3=0,,N15/$N$3) -> 4.9673203 | M15: =K15*L15 -> 15.723077 | N15: =分配表!O167 -> 182.4 | O15: =M15*$N$3 -> 577.35138
A16: 硅藻土 | C16: =OFFSET(分配表!C181,0,mth-1,1,1) -> 0 | D16: =IF(VALUE($F$3)=0,0,F16/$F$3) -> 0 | E16: =C16*D16 -> 0 | F16: =OFFSET(分配表!C168,0,mth-1) -> 0 | G16: =E16*$F$3 -> 0 | I16: 硅藻土 | K16: =分配表!O181 -> 2.60487 | L16: =IF($N$3=0,,N16/$N$3) -> 0.84422658 | M16: =K16*L16 -> 2.1991005 | N16: =分配表!O168 -> 31 | O16: =M16*$N$3 -> 80.750971
A17: 活性炭 | C17: =OFFSET(分配表!C183,0,mth-1,1,1) -> 0 | D17: =IF(VALUE($F$3)=0,0,F17/$F$3) -> 0 | E17: =C17*D17 -> 0 | F17: =OFFSET(分配表!C170,0,mth-1) -> 0 | G17: =E17*$F$3 -> 0 | I17: 活性炭 | K17: =分配表!O183 -> 7.0797015 | L17: =IF($N$3=0,,N17/$N$3) -> 1.7701525 | M17: =K17*L17 -> 12.532151 | N17: =分配表!O170 -> 65 | O17: =M17*$N$3 -> 460.1806
A18: 淀粉酶 | C18: =OFFSET(分配表!C184,0,mth-1,1,1) -> 0 | D18: =IF(VALUE($F$3)=0,0,F18/$F$3) -> 0 | E18: =C18*D18 -> 0 | F18: =OFFSET(分配表!C171,0,mth-1) -> 0 | G18: =E18*$F$3 -> 0 | I18: 淀粉酶 | K18: =分配表!O184 -> 47.801409 | L18: =IF($N$3=0,,N18/$N$3) -> 0.087145969 | M18: =K18*L18 -> 4.1657002 | N18: =分配表!O171 -> 3.2 | O18: =M18*$N$3 -> 152.96451
A19: 复合糖化酶 | C19: =OFFSET(分配表!C185,0,mth-1,1,1) -> 0 | D19: =IF(VALUE($F$3)=0,0,F19/$F$3) -> 0 | E19: =C19*D19 -> 0 | F19: =OFFSET(分配表!C172,0,mth-1) -> 0 | G19: =E19*$F$3 -> 0 | I19: 复合糖化酶 | K19: =分配表!O185 -> 32.197431 | L19: =IF($N$3=0,,N19/$N$3) -> 0.14978214 | M19: =K19*L19 -> 4.8226 | N19: =分配表!O172 -> 5.5 | O19: =M19*$N$3 -> 177.08587
A20: 异构酶 | C20: =OFFSET(分配表!C186,0,mth-1,1,1) -> 0 | D20: =IF(VALUE($F$3)=0,0,F20/$F$3) -> 0 | E20: =C20*D20 -> 0 | F20: =OFFSET(分配表!C1726,0,mth-1) -> 0 | G20: =E20*$F$3 -> 0 | I20: 异构酶 | K20: =分配表!O186 -> 218.57702 | L20: =IF($N$3=0,,N20/$N$3) -> 0.089869281 | M20: =K20*L20 -> 19.64336 | N20: =分配表!O173 -> 3.3 | O20: =M20*$N$3 -> 721.30417
A21: 硫酸镁 | C21: =OFFSET(分配表!C187,0,mth-1,1,1) -> 0 | D21: =IF(VALUE($F$3)=0,0,F21/$F$3) -> 0 | E21: =C21*D21 -> 0 | F21: =OFFSET(分配表!C174,0,mth-1) -> 0 | G21: =E21*$F$3 -> 0 | I21: 硫酸镁 | K21: =分配表!O187 -> 0.97947435 | L21: =IF($N$3=0,,N21/$N$3) -> 0.43572985 | M21: =K21*L21 -> 0.42678621 | N21: =分配表!O174 -> 16 | O21: =M21*$N$3 -> 15.67159
A22: 焦亚硫酸钠 | C22: =OFFSET(分配表!C188,0,mth-1,1,1) -> 0 | D22: =IF(VALUE($F$3)=0,0,F22/$F$3) -> 0 | E22: =C22*D22 -> 0 | F22: =OFFSET(分配表!C175,0,mth-1) -> 0 | G22: =E22*$F$3 -> 0 | I22: 焦亚硫酸钠 | K22: =分配表!O188 -> 1.8560801 | L22: =IF($N$3=0,,N22/$N$3) -> 0.29956427 | M22: =K22*L22 -> 0.55601529 | N22: =分配表!O175 -> 11 | O22: =M22*$N$3 -> 20.416881
A23: 树脂 | E23: =IF(VALUE($F$3)=0,0,G23/$F$3) -> 0 | G23: =OFFSET(分配表!C205,0,mth-1,1,1) -> #DIV/0! | I23: 树脂 | M23: =IF($N$3=0,0,O23/$N$3) -> #DIV/0! | O23: =分配表!O210 -> #DIV/0!
A24: 其他 | E24: =IF(VALUE($F$3)=0,0,G24/$F$3) -> 0 | G24: =OFFSET(分配表!C216,0,mth-1,1,1) -> #DIV/0! | I24: 其他 | M24: =IF($N$3=0,0,O24/$N$3) -> #DIV/0! | O24: =分配表!O221 -> #DIV/0!
A25: (三)包装物 | I25: (三)包装物
A26: (四)动力能源 | E26: =SUM(E27:E30) -> 0 | G26: =SUM(G27:G30) -> 0 | I26: (四)动力能源 | M26: =SUM(M27:M30) -> #DIV/0! | O26: =SUM(O27:O30) -> #DIV/0!
A27: 1、蒸汽 | B27: 吨 | C27: =OFFSET(分配表!C305,0,mth-1,1,1) -> 0 | D27: =IF(VALUE($F$3)=0,0,F27/$F$3) -> 0 | E27: =C27*D27 -> 0 | F27: =OFFSET(分配表!C313,0,mth-1,1,1) -> 0 | G27: =E27*F$3 -> 0 | I27: 1、蒸汽 | J27: 吨 | K27: =分配表!O305 -> 374.79903 | L27: =IF($N$3=0,0,N27/$N$3) -> 0.81699346 | M27: =K27*L27 -> 306.20835 | N27: =分配表!O313 -> 30 | O27: =M27*N$3 -> 11243.971
A28: 2、电 | B28: 度 | C28: =OFFSET(分配表!C324,0,mth-1,1,1) -> 0 | D28: =IF(VALUE($F$3)=0,0,F28/$F$3) -> 0 | E28: =C28*D28 -> 0 | F28: =OFFSET(分配表!C332,0,mth-1,1,1) -> #DIV/0! | G28: =E28*F$3 -> 0 | I28: 2、电 | J28: 度 | K28: =分配表!O324 -> 0.6806368 | L28: =IF($N$3=0,0,N28/$N$3) -> #DIV/0! | M28: =K28*L28 -> #DIV/0! | N28: =分配表!O332 -> #DIV/0! | O28: =M28*N$3 -> #DIV/0!
A29: 3、水 | B29: 吨 | C29: =OFFSET(分配表!C343,0,mth-1,1,1) -> 0 | D29: =IF(VALUE($F$3)=0,0,F29/$F$3) -> 0 | E29: =C29*D29 -> 0 | F29: =OFFSET(分配表!C350,0,mth-1,1,1) -> #DIV/0! | G29: =E29*F$3 -> 0 | I29: 3、水 | J29: 吨 | K29: =分配表!O343 -> 5.8950402 | L29: =IF($N$3=0,0,N29/$N$3) -> #DIV/0! | M29: =K29*L29 -> #DIV/0! | N29: =分配表!O350 -> #DIV/0! | O29: =M29*N$3 -> #DIV/0!
A30: 4、其他 | B30: 吨 | C30: =OFFSET(分配表!C360,0,mth-1,1,1) -> 0 | D30: =IF(VALUE($F$3)=0,0,F30/$F$3) -> 0 | E30: =C30*D30 -> 0 | F30: =OFFSET(分配表!C366,0,mth-1,1,1) -> 0 | G30: =E30*F$3 -> 0 | I30: 4、其他 | J30: 吨 | K30: =分配表!O360 -> 0 | L30: =IF($N$3=0,0,N30/$N$3) -> 0 | M30: =K30*L30 -> 0 | N30: =分配表!O366 -> 0 | O30: =M30*N$3 -> 0
A31: (五)排污费 | E31: =IF(VALUE($F$3)=0,0,G31/$F$3) -> 0 | G31: =OFFSET(分配表!C378,0,mth-1,1,1) -> #DIV/0! | I31: (五)排污费 | M31: =IF($N$3=0,,O31/$N$3) -> #DIV/0! | O31: =分配表!O378 -> #DIV/0!
A32: 1.污水处理 | E32: =E31 -> 0 | G32: =G31 -> #DIV/0! | I32: 1.污水处理 | M32: =M31 -> #DIV/0! | O32: =O31 -> #DIV/0!
A33: 2.污水固定成本 | I33: 2.污水固定成本
A34: (六)增值税 | I34: (六)增值税
A35: 三、边际贡献 | E35: =E5-E10 -> 0 | G35: =G5-G10 -> #DIV/0! | I35: 三、边际贡献 | M35: =M5-M10 -> #DIV/0! | O35: =O5-O10 -> #DIV/0!
A36: 四、固定成本 | E36: =SUM(E37:E43) -> 0 | G36: =SUM(G37:G43) -> #DIV/0! | I36: 四、固定成本 | M36: =IF(N$3=0,0,O36/N$3) -> #DIV/0! | O36: =SUM(O37:O43) -> #DIV/0!
A37: （一）折旧与摊销 | E37: =IF(VALUE($F$3)=0,0,G37/$F$3) -> 0 | G37: =OFFSET(分配表!C411,0,mth-1,1,1) -> #DIV/0! | I37: （一）折旧与摊销 | M37: =IF($N$3=0,0,O37/$N$3) -> #DIV/0! | O37: =分配表!O411 -> #DIV/0!
A38: （二）工资 | E38: =IF(VALUE($F$3)=0,0,G38/$F$3) -> 0 | G38: =OFFSET(分配表!C431,0,mth-1,1,1) -> #DIV/0! | I38: （二）工资 | M38: =IF($N$3=0,0,O38/$N$3) -> #DIV/0! | O38: =分配表!O431 -> #DIV/0!
A39: （三）制造费用 | E39: =IF(VALUE($F$3)=0,0,G39/$F$3) -> 0 | G39: =OFFSET(分配表!C451,0,mth-1,1,1) -> #DIV/0! | I39: （三）制造费用 | M39: =IF($N$3=0,0,O39/$N$3) -> #DIV/0! | O39: =分配表!O451 -> #DIV/0!
A40: （四）销售费用 | E40: =IF(VALUE($F$3)=0,0,G40/$F$3) -> 0 | G40: =OFFSET(分配表!C471,0,mth-1,1,1) -> #DIV/0! | I40: （四）销售费用 | M40: =IF($N$3=0,0,O40/$N$3) -> #DIV/0! | O40: =分配表!O471 -> #DIV/0!
A41: （五）管理费用 | E41: =IF(VALUE($F$3)=0,0,G41/$F$3) -> 0 | G41: =OFFSET(分配表!C491,0,mth-1,1,1) -> #DIV/0! | I41: （五）管理费用 | M41: =IF($N$3=0,0,O41/$N$3) -> #DIV/0! | O41: =分配表!O491 -> #DIV/0!
A42: （六）财务费用 | E42: =IF(VALUE($F$3)=0,0,G42/$F$3) -> 0 | G42: =OFFSET(分配表!C507,0,mth-1,1,1) -> #DIV/0! | I42: （六）财务费用 | M42: =IF($N$3=0,0,O42/$N$3) -> #DIV/0! | O42: =分配表!O507 -> #DIV/0!
A43: （七）其他 | E43: =IF(VALUE($F$3)=0,0,G43/$F$3) -> 0 | G43: =OFFSET(分配表!C529,0,mth-1,1,1) -> #DIV/0! | I43: （七） 其他 | M43: =IF($N$3=0,0,O43/$N$3) -> #DIV/0! | O43: =分配表!O529 -> #DIV/0!
A44: 其中：税金及附加 | E44: =IF(VALUE($F$3)=0,0,G44/$F$3) -> 0 | G44: =OFFSET(分配表!C541,0,mth-1,1,1) -> #DIV/0! | I44: 其中：税金及附加 | M44: =IF($N$3=0,0,O44/$N$3) -> #DIV/0! | O44: =分配表!O541 -> #DIV/0!
A45: 其他业务收支 | E45: =IF(VALUE($F$3)=0,0,G45/$F$3) -> 0 | G45: =OFFSET(分配表!C553,0,mth-1,1,1) -> #DIV/0! | I45: 其他业务收支 | M45: =IF($N$3=0,0,O45/$N$3) -> #DIV/0! | O45: =分配表!O553 -> #DIV/0!
A46: 营业外收支 | E46: =IF(VALUE($F$3)=0,0,G46/$F$3) -> 0 | G46: =OFFSET(分配表!C601,0,mth-1,1,1) -> #DIV/0! | I46: 营业外收支 | M46: =IF($N$3=0,0,O46/$N$3) -> #DIV/0! | O46: =分配表!O601 -> #DIV/0!
A47: 投资收益+公允价值变动损益 | E47: =IF(VALUE($F$3)=0,0,G47/$F$3) -> 0 | G47: =OFFSET(分配表!C565,0,mth-1,1,1) -> #DIV/0! | I47: 投资收益+公允价值变动损益 | M47: =IF($N$3=0,0,O47/$N$3) -> #DIV/0! | O47: =分配表!O565 -> #DIV/0!
A48: 其他收益 | E48: =IF(VALUE($F$3)=0,0,G48/$F$3) -> 0 | G48: =OFFSET(分配表!C577,0,mth-1,1,1) -> #DIV/0! | I48: 其他收益 | M48: =IF($N$3=0,0,O48/$N$3) -> #DIV/0! | O48: =分配表!O577 -> #DIV/0!
A49: 资产减值损失 | E49: =IF(VALUE($F$3)=0,0,G49/$F$3) -> 0 | G49: =OFFSET(分配表!C589,0,mth-1,1,1) -> #DIV/0! | I49: 资产减值损失 | M49: =IF($N$3=0,0,O49/$N$3) -> #DIV/0! | O49: =分配表!O589 -> #DIV/0!
A50: 其他 | E50: =IF(VALUE($F$3)=0,0,G50/$F$3) -> 0 | G50: =OFFSET(分配表!C613,0,mth-1,1,1) -> #DIV/0! | I50: 其他 | M50: =IF($N$3=0,0,O50/$N$3) -> #DIV/0! | O50: =分配表!O613 -> #DIV/0!
A51: 五、完全成本 | B51: 元 | E51: =E36+E10 -> 0 | G51: =G36+G10 -> #DIV/0! | I51: 五、完全成本 | J51: 元 | M51: =M36+M10 -> #DIV/0! | O51: =O36+O10 -> #DIV/0!
A52: 六、利润总额 | E52: =E35-E36 -> 0 | G52: =G35-G36 -> #DIV/0! | I52: 六、利润总额 | M52: =M35-M36 -> #DIV/0! | O52: =O35-O36 -> #DIV/0!
A53: 七、现金流 | E53: =E52+E37 -> 0 | G53: =G52+G37 -> #DIV/0! | I53: 七、现金流 | M53: =M52+M37 -> #DIV/0! | O53: =O52+O37 -> #DIV/0!
A54: 加工费 | B54: 元 | E54: =E10-E11+E36-E25 -> 0 | G54: =G10-G11+G36-G25 -> #DIV/0! | I54: 加工费 | J54: 元 | M54: =M10-M11+M36-M25 -> #DIV/0! | O54: =O10-O11+O36-O25 -> #DIV/0!
A55: 其他业务收支-糖渣 | E55: =IF(VALUE($F$3)=0,0,G55/$F$3) -> 0 | G55: =OFFSET(分配表!C626,0,mth-1,1,1) -> #DIV/0! | I55: 其他业务收支-糖渣 | M55: =IF($N$3=0,0,O55/$N$3) -> #DIV/0! | O55: =分配表!O626 -> #DIV/0!

Sheet 果糖汇总-含税
A1: =CONCATENATE("果糖装置汇总综合成本利润表_含税(2025年"&mth&"月)") -> 果糖装置汇总综合成本利润表_含税(2025年8月) | I1: =CONCATENATE("果糖装置汇总综合成本利润表_含税(2025年1-"&mth&"月)") -> 果糖装置汇总综合成本利润表_含税(2025年1-8月)
E3: 本月折77固形物产量： | F3: =果糖汇总!F3 -> 0 | G3: 吨 | M3: 本年折77固形物产量： | N3: =果糖汇总!N3 -> 57934.763 | O3: 吨
B4: 单位 | C4: 单价 | D4: 单耗 | E4: 单位成本 | F4: 总耗量 | G4: 总成本 | J4: 单位 | K4: 单价 | L4: 单耗 | M4: 单位成本 | N4: 总耗量 | O4: 总成本
A5: 一、收入 | E5: =E6-E7 -> 0 | G5: =G6-G7 -> 0 | I5: 一、收入 | M5: =M6-M7 -> 3077.2707 | O5: =O6-O7 -> 1.7828095e+08
A6: （一）销售价格 | E6: =IF(F$3=0,0,G6/F$3) -> 0 | G6: ='F60-含税'!G6+'F55-含税'!G6+'F42-含税-pt'!G6+'F90-含税 '!G6 -> 0 | I6: （一）销售价格 | M6: =IF($N$3=0,,O6/$N$3) -> 3228.5571 | O6: ='F55-含税'!O6+'F60-含税'!O6+'F42-含税'!O6+'F90-含税 '!O6 -> 1.8704569e+08
A7: （二）物流费 | E7: =IF($F$3=0,,G7/$F$3) -> 0 | G7: ='F55-含税'!G7+'F60-含税'!G7+'F42-含税'!G7+'F90-含税 '!G7 -> 0 | I7: （二）物流费 | M7: =IF($N$3=0,,O7/$N$3) -> 151.28642 | O7: ='F55-含税'!O7+'F60-含税'!O7+'F42-含税'!O7+'F90-含税 '!O7 -> 8764742.9
A8: 1、运费 | E8: =果糖汇总!E8*1.09 -> 0 | G8: =果糖汇总!G8*1.09 -> #DIV/0! | I8: 1、运费 | M8: =果糖汇总!M8*1.09 -> 70.227779 | O8: =果糖汇总!O8*1.09 -> 4068629.7
A9: 2、包装费、租赁费等 | E9: =果糖汇总!E9*1.13 -> 0 | G9: =果糖汇总!G9*1.13 -> #DIV/0! | I9: 2、包装费、租赁费等 | M9: =果糖汇总!M9*1.13 -> 81.05864 | O9: =果糖汇总!O9*1.13 -> 4696113.1
A10: 二、变动成本 | E10: =E11+E13+E26+E31+E34+E25 -> 0 | G10: =G11+G13+G26+G31+G34+G25 -> #DIV/0! | I10: 二、变动成本 | M10: =M11+M13+M26+M31+M34+M25 -> #DIV/0! | O10: =O11+O13+O26+O31+O34+O25 -> #DIV/0!
A11: (一)淀粉 | B11: 吨 | C11: =C12 -> 0 | D11: =D12 -> 0 | E11: =E12 -> 0 | F11: =F12 -> 0 | G11: =G12 -> 0 | I11: (一)淀粉 | J11: 吨 | K11: =IF(N11=0,0,O11/N11) -> 2824.3347 | L11: =IF(K11=0,0,M11/K11) -> 0.84550165 | M11: =M12 -> 2387.9796 | N11: =N12 -> 48983.938 | O11: =O12 -> 1.3834704e+08
A12: 1、淀粉(14%) | B12: 吨 | C12: =果糖汇总!C12*1.13 -> 0 | D12: =果糖汇总!D12 -> 0 | E12: =果糖汇总!E12*1.13 -> 0 | F12: =果糖汇总!F12 -> 0 | G12: =果糖汇总!G12*1.13 -> 0 | I12: 1、淀粉(14%) | J12: 吨 | K12: =果糖汇总!K12*1.13 -> 2824.3347 | L12: =果糖汇总!L12 -> 0.84550165 | M12: =果糖汇总!M12*1.13 -> 2387.9796 | N12: =果糖汇总!N12 -> 48983.938 | O12: =果糖汇总!O12*1.13 -> 1.3834704e+08
A13: (二)辅助材料 | E13: =果糖汇总!E13*1.13 -> 0 | G13: =果糖汇总!G13*1.13 -> #DIV/0! | I13: (二)辅助材料 | M13: =果糖汇总!M13*1.13 -> #DIV/0! | O13: =果糖汇总!O13*1.13 -> #DIV/0!
A14: 盐酸(折百) | B14: 公斤 | C14: =果糖汇总!C14*1.13 -> 0 | D14: =果糖汇总!D14 -> 0 | E14: =果糖汇总!E14*1.13 -> 0 | F14: =果糖汇总!F14 -> 0 | G14: =果糖汇总!G14*1.13 -> 0 | I14: 盐酸(折百) | J14: 公斤 | K14: =果糖汇总!K14*1.13 -> 1.1680073 | L14: =果糖汇总!L14 -> 4.5394438 | M14: =果糖汇总!M14*1.13 -> 5.3021034 | N14: =果糖汇总!N14 -> 262991.6 | O14: =果糖汇总!O14*1.13 -> 307176.1
A15: 氢氧化钠(折百) | B15: 公斤 | C15: =果糖汇总!C15*1.13 -> 0 | D15: =果糖汇总!D15 -> 0 | E15: =果糖汇总!E15*1.13 -> 0 | F15: =果糖汇总!F15 -> 0 | G15: =果糖汇总!G15*1.13 -> 0 | I15: 氢氧化钠(折百) | J15: 公斤 | K15: =果糖汇总!K15*1.13 -> 3.5767931 | L15: =果糖汇总!L15 -> 5.0423611 | M15: =果糖汇总!M15*1.13 -> 18.035483 | N15: =果糖汇总!N15 -> 292128 | O15: =果糖汇总!O15*1.13 -> 1044881.4
A16: 硅藻土 | B16: 公斤 | C16: =果糖汇总!C16*1.13 -> 0 | D16: =果糖汇总!D16 -> 0 | E16: =果糖汇总!E16*1.13 -> 0 | F16: =果糖汇总!F16 -> 0 | G16: =果糖汇总!G16*1.13 -> 0 | I16: 硅藻土 | J16: 公斤 | K16: =果糖汇总!K16*1.13 -> 2.9435031 | L16: =果糖汇总!L16 -> 0.76499838 | M16: =果糖汇总!M16*1.13 -> 2.2517751 | N16: =果糖汇总!N16 -> 44320 | O16: =果糖汇总!O16*1.13 -> 130456.06
A17: 活性炭 | B17: 公斤 | C17: =果糖汇总!C17*1.13 -> 0 | D17: =果糖汇总!D17 -> 0 | E17: =果糖汇总!E17*1.13 -> 0 | F17: =果糖汇总!F17 -> 0 | G17: =果糖汇总!G17*1.13 -> 0 | I17: 活性炭 | J17: 公斤 | K17: =果糖汇总!K17*1.13 -> 8.0000627 | L17: =果糖汇总!L17 -> 1.5935165 | M17: =果糖汇总!M17*1.13 -> 12.748232 | N17: =果糖汇总!N17 -> 92320 | O17: =果糖汇总!O17*1.13 -> 738565.79
A18: 淀粉酶 | B18: 公斤 | C18: =果糖汇总!C18*1.13 -> 0 | D18: =果糖汇总!D18 -> 0 | E18: =果糖汇总!E18*1.13 -> 0 | F18: =果糖汇总!F18 -> 0 | G18: =果糖汇总!G18*1.13 -> 0 | I18: 淀粉酶 | J18: 公斤 | K18: =果糖汇总!K18*1.13 -> 54.015593 | L18: =果糖汇总!L18 -> 0.08242029 | M18: =果糖汇总!M18*1.13 -> 4.4519808 | N18: =果糖汇总!N18 -> 4775 | O18: =果糖汇总!O18*1.13 -> 257924.45
A19: 复合糖化酶 | B19: 公斤 | C19: =果糖汇总!C19*1.13 -> 0 | D19: =果糖汇总!D19 -> 0 | E19: =果糖汇总!E19*1.13 -> 0 | F19: =果糖汇总!F19 -> 0 | G19: =果糖汇总!G19*1.13 -> 0 | I19: 复合糖化酶 | J19: 公斤 | K19: =果糖汇总!K19*1.13 -> 36.383097 | L19: =果糖汇总!L19 -> 0.16059442 | M19: =果糖汇总!M19*1.13 -> 5.8429226 | N19: =果糖汇总!N19 -> 9304 | O19: =果糖汇总!O19*1.13 -> 338508.34
A20: 异构酶 | B20: 公斤 | C20: =果糖汇总!C20*1.13 -> 0 | D20: =果糖汇总!D20 -> 0 | E20: =果糖汇总!E20*1.13 -> 0 | F20: =果糖汇总!F20 -> 0 | G20: =果糖汇总!G20*1.13 -> 0 | I20: 异构酶 | J20: 公斤 | K20: =果糖汇总!K20*1.13 -> 246.99203 | L20: =果糖汇总!L20 -> 0.097368137 | M20: =果糖汇总!M20*1.13 -> 24.049154 | N20: =果糖汇总!N20 -> 5641 | O20: =果糖汇总!O20*1.13 -> 1393282.1
A21: 硫酸镁 | B21: 公斤 | C21: =果糖汇总!C21*1.13 -> 0 | D21: =果糖汇总!D21 -> 0 | E21: =果糖汇总!E21*1.13 -> 0 | F21: =果糖汇总!F21 -> 0 | G21: =果糖汇总!G21*1.13 -> 0 | I21: 硫酸镁 | J21: 公斤 | K21: =果糖汇总!K21*1.13 -> 1.106806 | L21: =果糖汇总!L21 -> 0.49452174 | M21: =果糖汇总!M21*1.13 -> 0.54733963 | N21: =果糖汇总!N21 -> 28650 | O21: =果糖汇总!O21*1.13 -> 31709.992
A22: 焦亚硫酸钠 | B22: 公斤 | C22: =果糖汇总!C22*1.13 -> 0 | D22: =果糖汇总!D22 -> 0 | E22: =果糖汇总!E22*1.13 -> 0 | F22: =果糖汇总!F22 -> 0 | G22: =果糖汇总!G22*1.13 -> 0 | I22: 焦亚硫酸钠 | J22: 公斤 | K22: =果糖汇总!K22*1.13 -> 2.0973705 | L22: =果糖汇总!L22 -> 0.29084437 | M22: =果糖汇总!M22*1.13 -> 0.61000842 | N22: =果糖汇总!N22 -> 16850 | O22: =果糖汇总!O22*1.13 -> 35340.694
A23: 树脂 | B23: 公斤 | E23: =果糖汇总!E23*1.13 -> 0 | G23: =果糖汇总!G23*1.13 -> #DIV/0! | I23: 树脂 | J23: 公斤 | K23: =果糖汇总!K23*1.13 -> 0 | L23: =果糖汇总!L23 -> 0 | M23: =果糖汇总!M23*1.13 -> #DIV/0! | N23: =果糖汇总!N23 -> 0 | O23: =果糖汇总!O23*1.13 -> #DIV/0!
A24: 其他 | E24: =果糖汇总!E24*1.13 -> 0 | G24: =果糖汇总!G24*1.13 -> #DIV/0! | I24: 其他 | K24: =果糖汇总!K24*1.13 -> 0 | L24: =果糖汇总!L24 -> 0 | M24: =果糖汇总!M24*1.13 -> #DIV/0! | N24: =果糖汇总!N24 -> 0 | O24: =果糖汇总!O24*1.13 -> #DIV/0!
A25: (三)包装物 | E25: =IF($F$3=0,,G25/$F$3) -> 0 | G25: ='F55-含税'!G25+'F60-含税'!G25+'F42-含税'!G25+'F90-含税 '!G25 -> 0 | I25: (三)包装物 | M25: =IF($N$3=0,,O25/$N$3) -> 0 | O25: ='F55-含税'!O25+'F60-含税'!O25+'F42-含税'!O25 -> 0
A26: (四)动力能源 | E26: =SUM(E27:E30) -> 0 | G26: =SUM(G27:G30) -> 0 | I26: (四)动力能源 | M26: =SUM(M27:M30) -> #DIV/0! | O26: =SUM(O27:O30) -> #DIV/0!
A27: 1、蒸汽 | B27: 吨 | C27: ='F55-含税'!C27 -> 0 | D27: =果糖汇总!D27 -> 0 | E27: =C27*D27 -> 0 | F27: =果糖汇总!F27 -> 0 | G27: ='F55-含税'!G27+'F42-含税'!G27+'F60-含税'!G27+'F90-含税 '!G27 -> 0 | I27: 1、蒸汽 | J27: 吨 | K27: ='F55-含税'!K27 -> 408.53094 | L27: =果糖汇总!L27 -> 0.30803612 | M27: =K27*L27 -> 125.84229 | N27: =果糖汇总!N27 -> 17846 | O27: ='F55-含税'!O27+'F42-含税'!O27+'F60-含税'!O27+'F90-含税 '!O27 -> 7290643.1
A28: 2、电 | B28: 度 | C28: =IF(G28=0,0,G28/F28) -> 0 | D28: =果糖汇总!D28 -> 0 | E28: =果糖汇总!E28*1.13 -> 0 | F28: =果糖汇总!F28 -> #DIV/0! | G28: =果糖汇总!G28*1.13 -> 0 | I28: 2、电 | J28: 度 | K28: =IF(O28=0,0,O28/N28) -> #DIV/0! | L28: =果糖汇总!L28 -> #DIV/0! | M28: =果糖汇总!M28*1.13 -> #DIV/0! | N28: =果糖汇总!N28 -> #DIV/0! | O28: =果糖汇总!O28*1.13 -> #DIV/0!
A29: 3、水 | B29: 吨 | C29: =IF(G29=0,0,G29/F29) -> 0 | D29: =果糖汇总!D29 -> 0 | E29: =D29*C29 -> 0 | F29: =果糖汇总!F29 -> #DIV/0! | G29: ='F55-含税'!G29+'F60-含税'!G29+'F42-含税'!G29+'F90-含税 '!G29 -> 0 | I29: 3、水 | J29: 吨 | K29: =IF(O29=0,0,O29/N29) -> #DIV/0! | L29: =果糖汇总!L29 -> #DIV/0! | M29: =L29*K29 -> #DIV/0! | N29: =果糖汇总!N29 -> #DIV/0! | O29: ='F55-含税'!O29+'F60-含税'!O29+'F42-含税'!O29+'F90-含税 '!O29 -> #DIV/0!
A30: 4、其他 | B30: 吨 | I30: 4、其他 | J30: 吨
A31: (五)排污费 | E31: =果糖汇总!$E$31*1.13 -> 0 | G31: =果糖汇总!$G$31*1.13 -> #DIV/0! | I31: (五)排污费 | M31: =果糖汇总!$M$31*1.13 -> #DIV/0! | O31: =果糖汇总!$O$31*1.13 -> #DIV/0!
A32: 1.污水处理 | E32: =果糖汇总!$E$31*1.13 -> 0 | G32: =果糖汇总!$G$31*1.13 -> #DIV/0! | I32: 1.污水处理 | M32: =果糖汇总!$M$31*1.13 -> #DIV/0! | O32: =果糖汇总!$O$31*1.13 -> #DIV/0!
A33: 2.污水固定成本 | I33: 2.污水固定成本
A34: (六)增值税 | E34: =SUM(E5,-E11,-E13,-E26,-E31,-E25)-SUM(果糖汇总!E5,-果糖汇总!E11,-果糖汇总!E13,-果糖汇总!E26,-果糖汇总!E31,-果糖汇总!E25) -> 0 | G34: =SUM(G5,-G11,-G13,-G26,-G31,-G25)-SUM(果糖汇总!G5,-果糖汇总!G11,-果糖汇总!G13,-果糖汇总!G26,-果糖汇总!G31,-果糖汇总!G25) -> #DIV/0! | I34: (六)增值税 | M34: =SUM(M5,-M11,-M13,-M26,-M31,-M25)-SUM(果糖汇总!M5,-果糖汇总!M11,-果糖汇总!M13,-果糖汇总!M26,-果糖汇总!M31,-果糖汇总!M25) -> #DIV/0! | O34: =SUM(O5,-O11,-O13,-O26,-O31,-O25)-SUM(果糖汇总!O5,-果糖汇总!O11,-果糖汇总!O13,-果糖汇总!O26,-果糖汇总!O31,-果糖汇总!O25) -> #DIV/0!
A35: 三、边际贡献 | E35: =E5-E10 -> 0 | G35: =G5-G10 -> #DIV/0! | I35: 三、边际贡献 | M35: =M5-M10 -> #DIV/0! | O35: =O5-O10 -> #DIV/0!
A36: 四、固定成本 | E36: =SUM(E37:E43) -> 0 | G36: =SUM(G37:G43) -> #DIV/0! | I36: 四、固定成本 | M36: =SUM(M37:M43) -> #DIV/0! | O36: =SUM(O37:O43) -> #DIV/0!
A37: （一）折旧与摊销 | E37: =IF(F$3=0,0,G37/F$3) -> 0 | G37: =果糖汇总!G37 -> #DIV/0! | I37: （一）折旧与摊销 | M37: =IF(N$3=0,0,O37/N$3) -> #DIV/0! | O37: =果糖汇总!O37 -> #DIV/0!
A38: （二）工资 | E38: =IF(F$3=0,0,G38/F$3) -> 0 | G38: =果糖汇总!G38 -> #DIV/0! | I38: （二）工资 | M38: =IF(N$3=0,0,O38/N$3) -> #DIV/0! | O38: =果糖汇总!O38 -> #DIV/0!
A39: （三）制造费用 | E39: =IF(F$3=0,0,G39/F$3) -> 0 | G39: =果糖汇总!G39 -> #DIV/0! | I39: （三）制造费用 | M39: =IF(N$3=0,0,O39/N$3) -> #DIV/0! | O39: =果糖汇总!O39 -> #DIV/0!
A40: （四）销售费用 | E40: =IF(F$3=0,0,G40/F$3) -> 0 | G40: =果糖汇总!G40 -> #DIV/0! | I40: （四）销售费用 | M40: =IF(N$3=0,0,O40/N$3) -> #DIV/0! | O40: =果糖汇总!O40 -> #DIV/0!
A41: （五）管理费用 | E41: =IF(F$3=0,0,G41/F$3) -> 0 | G41: =果糖汇总!G41 -> #DIV/0! | I41: （五）管理费用 | M41: =IF(N$3=0,0,O41/N$3) -> #DIV/0! | O41: =果糖汇总!O41 -> #DIV/0!
A42: （六）财务费用 | E42: =IF(F$3=0,0,G42/F$3) -> 0 | G42: =果糖汇总!G42 -> #DIV/0! | I42: （六）财务费用 | M42: =IF(N$3=0,0,O42/N$3) -> #DIV/0! | O42: =果糖汇总!O42 -> #DIV/0!
A43: （七）其他 | E43: =IF(F$3=0,0,G43/F$3) -> 0 | G43: =果糖汇总!G43 -> #DIV/0! | I43: （七） 其他 | M43: =IF(N$3=0,0,O43/N$3) -> #DIV/0! | O43: =果糖汇总!O43 -> #DIV/0!
A44: 其中：税金及附加 | E44: =IF(F$3=0,0,G44/F$3) -> 0 | G44: =果糖汇总!G44 -> #DIV/0! | I44: 其中：税金及附加 | M44: =IF(N$3=0,0,O44/N$3) -> #DIV/0! | O44: =果糖汇总!O44 -> #DIV/0!
A45: 其他业务收支 | E45: =IF(F$3=0,0,G45/F$3) -> 0 | G45: =果糖汇总!G45 -> #DIV/0! | I45: 其他业务收支 | M45: =IF(N$3=0,0,O45/N$3) -> #DIV/0! | O45: =果糖汇总!O45 -> #DIV/0!
A46: 营业外收支 | E46: =IF(F$3=0,0,G46/F$3) -> 0 | G46: =果糖汇总!G46 -> #DIV/0! | I46: 营业外收支 | M46: =IF(N$3=0,0,O46/N$3) -> #DIV/0! | O46: =果糖汇总!O46 -> #DIV/0!
A47: 投资收益+公允价值变动损益 | E47: =IF(F$3=0,0,G47/F$3) -> 0 | G47: =果糖汇总!G47 -> #DIV/0! | I47: 投资收益+公允价值变动损益 | M47: =IF(N$3=0,0,O47/N$3) -> #DIV/0! | O47: =果糖汇总!O47 -> #DIV/0!
A48: 其他收益 | E48: =IF(F$3=0,0,G48/F$3) -> 0 | G48: =果糖汇总!G48 -> #DIV/0! | I48: 其他收益 | M48: =IF(N$3=0,0,O48/N$3) -> #DIV/0! | O48: =果糖汇总!O48 -> #DIV/0!
... A50: 其他 | E50: =IF(F$3=0,0,G50/F$3) -> 0 | G50: =果糖汇总!G50 -> #DIV/0! | I50: 其他 | M50: =IF(N$3=0,0,O50/N$3) -> #DIV/0! | O50: =果糖汇总!O50 -> #DIV/0!
A51: 五、完全成本 | B51: 元 | E51: =E36+E10 -> 0 | G51: =G36+G10 -> #DIV/0! | I51: 五、完全成本 | J51: 元 | M51: =M36+M10 -> #DIV/0! | O51: =O36+O10 -> #DIV/0!
A52: 六、利润总额 | B52: 元 | E52: =E35-E36 -> 0 | G52: =G35-G36 -> #DIV/0! | I52: 六、利润总额 | J52: 元 | M52: =M35-M36 -> #DIV/0! | O52: =O35-O36 -> #DIV/0!
A53: 七、现金流 | B53: 元 | E53: =E52+E37 -> 0 | G53: =G52+G37 -> #DIV/0! | I53: 七、现金流 | J53: 元 | M53: =M52+M37 -> #DIV/0! | O53: =O52+O37 -> #DIV/0!
A54: 加工费 | B54: 元 | E54: =E10-E11+E36-E25 -> 0 | G54: =G10-G11+G36-G25 -> #DIV/0! | I54: 加工费 | J54: 元 | M54: =M10-M11+M36-M25 -> #DIV/0! | O54: =O10-O11+O36-O25 -> #DIV/0!
A55: 其他业务收支-糖渣 | E55: =IF(F$3=0,0,G55/F$3) -> 0 | G55: =果糖汇总!G55 -> #DIV/0! | I55: 其他业务收支-糖渣 | M55: =IF(N$3=0,0,O55/N$3) -> #DIV/0! | O55: =果糖汇总!O55 -> #DIV/0!
A58: 含税与不含税校验 | E58: =E35-果糖汇总!E35 -> 0 | G58: =G35-果糖汇总!G35 -> #DIV/0! | L58: check | M58: =M35-果糖汇总!M35 -> #DIV/0! | O58: =O35-果糖汇总!O35 -> #DIV/0!
O59: =O36-果糖汇总!O36 -> #DIV/0!

Sheet 专用糖-含税
A1: =CONCATENATE("专用糖综合成本利润表_含税(2025年"&mth&"月)") -> 专用糖综合成本利润表_含税(2025年8月) | I1: =CONCATENATE("专用糖综合成本利润表_含税(2025年1-"&mth&"月)") -> 专用糖综合成本利润表_含税(2025年1-8月)
A3: 产量 | E3: 本月产量 | F3: =专用糖!F3 -> 0 | G3: 吨 | M3: 本年产量 | N3: =专用糖!N3 -> 38999.431 | O3: 吨
B4: 单位 | C4: 单价 | D4: 单耗 | E4: 单位成本 | F4: 总耗量 | G4: 总成本 | J4: 单位 | K4: 单价 | L4: 单耗 | M4: 单位成本 | N4: 总耗量 | O4: 总成本
A5: 一、收入 | E5: =E6-E7 -> 0 | G5: =G6-G7 -> 0 | I5: 一、收入 | M5: =M6-M7 -> 3182.0163 | O5: =O6-O7 -> 1.2409682e+08
A6: （一）销售价格 | E6: =OFFSET(销售收入及运费!C97,0,mth-1,1,1) -> 0 | G6: =F3*E6 -> 0 | I6: （一）销售价格 | M6: =销售收入及运费!O97 -> 3257.6497 | O6: =M6*$N$3 -> 1.2704649e+08
A7: （二）物流费 | E7: =OFFSET(销售收入及运费!C195,0,mth-1,1,1) -> 0 | G7: =E7*$F$3 -> 0 | I7: （二）物流费 | M7: =销售收入及运费!O195 -> 75.63344 | O7: =M7*$N$3 -> 2949661.1
A8: 1、运费 | E8: =专用糖!E8*1.09 -> #DIV/0! | G8: =专用糖!G8*1.09 -> #DIV/0! | I8: 1、运费 | M8: =专用糖!M8*1.09 -> 64.282209 | O8: =专用糖!O8*1.09 -> 2506969.6
A9: 2、包装费、租赁费等 | E9: =专用糖!E9*1.13 -> #DIV/0! | G9: =专用糖!G9*1.13 -> #DIV/0! | I9: 2、包装费、租赁费等 | M9: =专用糖!M9*1.13 -> 11.351231 | O9: =专用糖!O9*1.13 -> 442691.53
A10: 二、变动成本 | E10: =E11+E13+E28+E33+E36+E27 -> 0 | G10: =G11+G13+G28+G33+G36+G27 -> #DIV/0! | I10: 二、变动成本 | M10: =M11+M13+M28+M33+M36+M27 -> #DIV/0! | O10: =O11+O13+O28+O33+O36+O27 -> #DIV/0!
A11: (一)淀粉 | B11: 吨 | C11: =C12 -> 0 | D11: =IF(C11=0,0,E11/C11) -> 0 | E11: =E12 -> 0 | F11: =F12 -> 0 | G11: =G12 -> 0 | I11: (一)淀粉 | J11: 吨 | K11: =IF(N11=0,0,O11/N11) -> 2823.0827 | L11: =IF(K11=0,0,M11/K11) -> 0.84925716 | M11: =M12 -> 2397.5232 | N11: =N12 -> 33120.546 | O11: =O12 -> 93502041
A12: 1、淀粉(14%) | B12: 吨 | C12: =专用糖!C12*1.13 -> 0 | D12: =专用糖!D12 -> 0 | E12: =专用糖!E12*1.13 -> 0 | F12: =专用糖!F12 -> 0 | G12: =专用糖!G12*1.13 -> 0 | I12: 1、淀粉(14%) | J12: 吨 | K12: =专用糖!K12*1.13 -> 2823.0827 | L12: =专用糖!L12 -> 0.84925716 | M12: =专用糖!M12*1.13 -> 2397.5232 | N12: =专用糖!N12 -> 33120.546 | O12: =专用糖!O12*1.13 -> 93502041
A13: (二)辅助材料 | E13: =专用糖!E13*1.13 -> 0 | G13: =专用糖!G13*1.13 -> 0 | I13: (二)辅助材料 | M13: =专用糖!M13*1.13 -> 50.958935 | O13: =专用糖!O13*1.13 -> 1987369.5
A14: 活性炭 | B14: 公斤 | C14: =专用糖!C14*1.13 -> 0 | D14: =专用糖!D14 -> 0 | E14: =专用糖!E14*1.13 -> 0 | F14: =专用糖!F14 -> 0 | G14: =专用糖!G14*1.13 -> 0 | I14: 活性炭 | J14: 公斤 | K14: =分配表!O254 -> 4.0364254 | L14: =专用糖!L14 -> 3.7759525 | M14: =专用糖!M14*1.13 -> 15.241351 | N14: =专用糖!N14 -> 147260 | O14: =专用糖!O14*1.13 -> 594404
A15: 食用级盐酸（折百） | B15: 公斤 | C15: =专用糖!C15*1.13 -> 0 | D15: =专用糖!D15 -> 0 | E15: =专用糖!E15*1.13 -> 0 | F15: =专用糖!F15 -> 0 | G15: =专用糖!G15*1.13 -> 0 | I15: 食用级盐酸（折百） | J15: 公斤 | K15: =分配表!O255 -> 1.1666082 | L15: =专用糖!L15 -> 3.6441429 | M15: =专用糖!M15*1.13 -> 4.2512872 | N15: =专用糖!N15 -> 142119.5 | O15: =专用糖!O15*1.13 -> 165797.78
A16: 食用级液碱（折百） | B16: 公斤 | C16: =专用糖!C16*1.13 -> 0 | D16: =专用糖!D16 -> 0 | E16: =专用糖!E16*1.13 -> 0 | F16: =专用糖!F16 -> 0 | G16: =专用糖!G16*1.13 -> 0 | I16: 食用级液碱（折百） | J16: 公斤 | K16: =分配表!O256 -> 3.5637525 | L16: =专用糖!L16 -> 4.4881065 | M16: =专用糖!M16*1.13 -> 15.994501 | N16: =专用糖!N16 -> 175033.6 | O16: =专用糖!O16*1.13 -> 623776.43
A17: 纯碱 | B17: 公斤 | C17: =专用糖!C17*1.13 -> 0 | D17: =专用糖!D17 -> 0 | E17: =专用糖!E17*1.13 -> 0 | F17: =专用糖!F17 -> 0 | G17: =专用糖!G17*1.13 -> 0 | I17: 纯碱 | J17: 公斤 | K17: =分配表!O257 -> 2.4234131 | L17: =专用糖!L17 -> 0.076924199 | M17: =专用糖!M17*1.13 -> 0.18641911 | N17: =专用糖!N17 -> 3000 | O17: =专用糖!O17*1.13 -> 7270.2392
A18: 真菌酶 | B18: 公斤 | C18: =专用糖!C18*1.13 -> 0 | D18: =专用糖!D18 -> 0 | E18: =专用糖!E18*1.13 -> 0 | F18: =专用糖!F18 -> 0 | G18: =专用糖!G18*1.13 -> 0 | I18: 真菌酶 | J18: 公斤 | K18: =分配表!O258 -> 40.000014 | L18: =专用糖!L18 -> 0.035308207 | M18: =专用糖!M18*1.13 -> 1.4123288 | N18: =专用糖!N18 -> 1377 | O18: =专用糖!O18*1.13 -> 55080.019
A19: 2X型高温酶 | B19: 公斤 | C19: =专用糖!C19*1.13 -> 0 | D19: =专用糖!D19 -> 0 | E19: =专用糖!E19*1.13 -> 0 | F19: =专用糖!F19 -> 0 | G19: =专用糖!G19*1.13 -> 0 | I19: 2X型高温酶 | J19: 公斤 | K19: =分配表!O259 -> 20.962522 | L19: =专用糖!L19 -> 0.13864305 | M19: =专用糖!M19*1.13 -> 2.9063079 | N19: =专用糖!N19 -> 5407 | O19: =专用糖!O19*1.13 -> 113344.36
A20: 普鲁兰酶 | B20: 公斤 | C20: =专用糖!C20*1.13 -> 0 | D20: =专用糖!D20 -> 0 | E20: =专用糖!E20*1.13 -> 0 | F20: =专用糖!F20 -> 0 | G20: =专用糖!G20*1.13 -> 0 | I20: 普鲁兰酶 | J20: 公斤 | K20: =分配表!O260 -> 39.999978 | L20: =专用糖!L20 -> 0.016910503 | M20: =专用糖!M20*1.13 -> 0.67641976 | N20: =专用糖!N20 -> 659.5 | O20: =专用糖!O20*1.13 -> 26379.986
A21: β淀粉酶 | B21: 公斤 | C21: =专用糖!C21*1.13 -> 0 | D21: =专用糖!D21 -> 0 | E21: =专用糖!E21*1.13 -> 0 | F21: =专用糖!F21 -> 0 | G21: =专用糖!G21*1.13 -> 0 | I21: β淀粉酶 | J21: 公斤 | K21: =分配表!O261 -> 70.085034 | L21: =专用糖!L21 -> 0.083090956 | M21: =专用糖!M21*1.13 -> 5.8234325 | N21: =专用糖!N21 -> 3240.5 | O21: =专用糖!O21*1.13 -> 227110.55
A22: DX1.5X强效糖化酶 | B22: 公斤 | C22: =专用糖!C22*1.13 -> 0 | D22: =专用糖!D22 -> 0 | E22: =专用糖!E22*1.13 -> 0 | F22: =专用糖!F22 -> 0 | G22: =专用糖!G22*1.13 -> 0 | I22: DX1.5X强效糖化酶 | J22: 公斤 | K22: =分配表!O262 -> 28.580508 | L22: =专用糖!L22 -> 0.033231254 | M22: =专用糖!M22*1.13 -> 0.94976611 | N22: =专用糖!N22 -> 1296 | O22: =专用糖!O22*1.13 -> 37040.338
A23: 转甘酶 | B23: L | C23: =专用糖!C23*1.13 -> 0 | D23: =专用糖!D23 -> 0 | E23: =专用糖!E23*1.13 -> 0 | F23: =专用糖!F23 -> 0 | G23: =专用糖!G23*1.13 -> 0 | I23: 转甘酶 | J23: L | K23: =分配表!O263 -> 597.99999 | L23: =专用糖!L23 -> 0.00384621 | M23: =专用糖!M23*1.13 -> 2.3000335 | N23: =专用糖!N23 -> 150 | O23: =专用糖!O23*1.13 -> 89699.999
A24: 葡糖淀粉酶 | B24: 公斤 | C24: =专用糖!C24*1.13 -> 0 | D24: =专用糖!D24 -> 0 | E24: =专用糖!E24*1.13 -> 0 | F24: =专用糖!F24 -> 0 | G24: =专用糖!G24*1.13 -> 0 | I24: 葡糖淀粉酶 | J24: 公斤 | K24: =分配表!O264 -> 0 | L24: =专用糖!L24 -> 0 | M24: =专用糖!M24*1.13 -> 0 | N24: =专用糖!N24 -> 0 | O24: =专用糖!O24*1.13 -> 0
A25: 麦芽糖淀粉酶 | B25: 公斤 | C25: =专用糖!C25*1.13 -> 0 | D25: =专用糖!D25 -> 0 | E25: =专用糖!E25*1.13 -> 0 | F25: =专用糖!F25 -> 0 | G25: =专用糖!G25*1.13 -> 0 | I25: 麦芽糖淀粉酶 | J25: 公斤 | K25: =分配表!O265 -> 0 | L25: =专用糖!L25 -> 0 | M25: =专用糖!M25*1.13 -> 0 | N25: =专用糖!N25 -> 0 | O25: =专用糖!O25*1.13 -> 0
A26: 其他 | E26: =专用糖!E26*1.13 -> #DIV/0! | G26: =专用糖!G26*1.13 -> 0 | I26: 其他 | M26: =专用糖!M26*1.13 -> 1.2170883 | O26: =专用糖!O26*1.13 -> 47465.752
A27: (三)包装物 | I27: (三)包装物
A28: (四)动力能源 | E28: =SUM(E29:E32) -> 0 | G28: =SUM(G29:G32) -> 0 | I28: (四)动力能源 | M28: =SUM(M29:M32) -> 235.30082 | O28: =SUM(O29:O32) -> 9176598.1
A29: 1、蒸汽 | B29: 吨 | C29: =OFFSET(分配表!C306,0,mth-1,1,1) -> 0 | D29: =专用糖!D29 -> 0 | E29: =C29*D29 -> 0 | F29: =专用糖!F29 -> 0 | G29: =E29*F$3 -> 0 | I29: 1、蒸汽 | J29: 吨 | K29: =分配表!O306 -> 408.53094 | L29: =专用糖!L29 -> 0.43431403 | M29: =K29*L29 -> 177.43072 | N29: =专用糖!N29 -> 16938 | O29: =M29*N$3 -> 6919697
A30: 2、电 | B30: 度 | C30: =专用糖!C30*1.13 -> 0 | D30: =专用糖!D30 -> 0 | E30: =专用糖!E30*1.13 -> 0 | F30: =专用糖!F30 -> 0 | G30: =专用糖!G30*1.13 -> 0 | I30: 2、电 | J30: 度 | K30: =专用糖!K30*1.13 -> 0.76911958 | L30: =专用糖!L30 -> 61.258714 | M30: =专用糖!M30*1.13 -> 47.115277 | N30: =专用糖!N30 -> 2389055 | O30: =专用糖!O30*1.13 -> 1837469
A31: 3、水 | B31: 吨 | C31: =3.32+0.9*2.97 -> 5.993 | D31: =专用糖!D31 -> 0 | E31: =D31*C31 -> 0 | F31: =专用糖!F31 -> 0 | G31: =E31*F3 -> 0 | I31: 3、水 | J31: 吨 | K31: =3.32+0.9*2.97 -> 5.993 | L31: =专用糖!L31 -> 1.7945646 | M31: =L31*K31 -> 10.754826 | N31: =专用糖!N31 -> 69987 | O31: =M31*N3 -> 419432.09
A32: 4、其他 | B32: M3 | I32: 4、其他 | J32: M3
A33: (五)排污费 | E33: =专用糖!E33*1.13 -> 0 | G33: =专用糖!G33*1.13 -> #DIV/0! | I33: (五)排污费 | M33: =专用糖!M33*1.13 -> #DIV/0! | O33: =专用糖!O33*1.13 -> #DIV/0!
A34: 1.污水处理 | E34: =E33 -> 0 | G34: =G33 -> #DIV/0! | I34: 1.污水处理 | M34: =M33 -> #DIV/0! | O34: =O33 -> #DIV/0!
A35: 2.污水固定成本 | I35: 2.污水固定成本
A36: (五)增值税 | E36: =IF(VALUE(F$3)=0,0,G36/F$3) -> 0 | G36: =SUM(G5,-G11,-G13,-G28,-G33,-G27)-SUM(专用糖!G5,-专用糖!G11,-专用糖!G13,-专用糖!G28,-专用糖!G33,-专用糖!G27) -> #DIV/0! | I36: (五)增值税 | M36: =IF(N$3=0,0,O36/N$3) -> #DIV/0! | O36: =SUM(O5,-O11,-O13,-O28,-O33,-O27)-SUM(专用糖!O5,-专用糖!O11,-专用糖!O13,-专用糖!O28,-专用糖!O33,-专用糖!O27) -> #DIV/0!
A37: 三、边际贡献 | E37: =E5-E10 -> 0 | G37: =G5-G10 -> #DIV/0! | I37: 三、边际贡献 | M37: =M5-M10 -> #DIV/0! | O37: =O5-O10 -> #DIV/0!
A38: 四、固定成本 | E38: =SUM(E39:E45) -> 0 | G38: =SUM(G39:G45) -> #DIV/0! | I38: 四、固定成本 | M38: =IF(N$3=0,0,O38/N$3) -> #DIV/0! | O38: =SUM(O39:O45) -> #DIV/0!
A39: （一）折旧与摊销 | E39: =专用糖!E39 -> 0 | G39: =专用糖!G39 -> #DIV/0! | I39: （一）折旧与摊销 | M39: =专用糖!M39 -> #DIV/0! | O39: =专用糖!O39 -> #DIV/0!
A40: （二）工资 | E40: =专用糖!E40 -> 0 | G40: =专用糖!G40 -> #DIV/0! | I40: （二）工资 | M40: =专用糖!M40 -> #DIV/0! | O40: =专用糖!O40 -> #DIV/0!
A41: （三）制造费用 | E41: =专用糖!E41 -> 0 | G41: =专用糖!G41 -> #DIV/0! | I41: （三）制造费用 | M41: =专用糖!M41 -> #DIV/0! | O41: =专用糖!O41 -> #DIV/0!
A42: （四）销售费用 | E42: =专用糖!E42 -> 0 | G42: =专用糖!G42 -> #DIV/0! | I42: （四）销售费用 | M42: =专用糖!M42 -> #DIV/0! | O42: =专用糖!O42 -> #DIV/0!
A43: （五）管理费用 | E43: =专用糖!E43 -> 0 | G43: =专用糖!G43 -> #DIV/0! | I43: （五）管理费用 | M43: =专用糖!M43 -> #DIV/0! | O43: =专用糖!O43 -> #DIV/0!
A44: （六）财务费用 | E44: =专用糖!E44 -> 0 | G44: =专用糖!G44 -> #DIV/0! | I44: （六）财务费用 | M44: =专用糖!M44 -> #DIV/0! | O44: =专用糖!O44 -> #DIV/0!
A45: （七）其他 | E45: =专用糖!E45 -> 0 | G45: =专用糖!G45 -> #DIV/0! | I45: （七） 其他 | M45: =专用糖!M45 -> #DIV/0! | O45: =专用糖!O45 -> #DIV/0!
A46: 其中：税金及附加 | E46: =专用糖!E46 -> 0 | G46: =专用糖!G46 -> #DIV/0! | I46: 其中：税金及附加 | M46: =专用糖!M46 -> #DIV/0! | O46: =专用糖!O46 -> #DIV/0!
A47: 其他业务收支 | E47: =专用糖!E47 -> 0 | G47: =专用糖!G47 -> #DIV/0! | I47: 其他业务收支 | M47: =专用糖!M47 -> #DIV/0! | O47: =专用糖!O47 -> #DIV/0!
A48: 营业外收支 | E48: =专用糖!E48 -> 0 | G48: =专用糖!G48 -> #DIV/0! | I48: 营业外收支 | M48: =专用糖!M48 -> #DIV/0! | O48: =专用糖!O48 -> #DIV/0!
A49: 投资收益+公允价值变动损益 | E49: =专用糖!E49 -> 0 | G49: =专用糖!G49 -> #DIV/0! | I49: 投资收益+公允价值变动损益 | M49: =专用糖!M49 -> #DIV/0! | O49: =专用糖!O49 -> #DIV/0!
A50: 其他收益 | E50: =专用糖!E50 -> 0 | G50: =专用糖!G50 -> #DIV/0! | I50: 其他收益 | M50: =专用糖!M50 -> #DIV/0! | O50: =专用糖!O50 -> #DIV/0!
... A52: 其他 | E52: =专用糖!E52 -> 0 | G52: =专用糖!G52 -> #DIV/0! | I52: 其他 | M52: =专用糖!M52 -> #DIV/0! | O52: =专用糖!O52 -> #DIV/0!
A53: 五、完全成本 | B53: 元 | E53: =E38+E10 -> 0 | G53: =G38+G10 -> #DIV/0! | I53: 五、完全成本 | J53: 元 | M53: =M38+M10 -> #DIV/0! | O53: =O38+O10 -> #DIV/0!
A54: 六、利润总额 | B54: 元 | E54: =E37-E38 -> 0 | G54: =G37-G38 -> #DIV/0! | I54: 六、利润总额 | J54: 元 | M54: =M37-M38 -> #DIV/0! | O54: =O37-O38 -> #DIV/0!
A55: 七、现金流 | B55: 元 | E55: =E54+E39 -> 0 | G55: =G54+G39 -> #DIV/0! | I55: 七、现金流 | J55: 元 | M55: =M54+M39 -> #DIV/0! | O55: =O54+O39 -> #DIV/0!
A56: 加工费 | B56: 元 | E56: =E10-E11-E27+E38 -> 0 | G56: =G10-G11-G27+G38 -> #DIV/0! | I56: 加工费 | J56: 元 | M56: =M10-M11-M27+M38 -> #DIV/0! | O56: =O10-O11-O27+O38 -> #DIV/0!
A57: 其他业务收支-糖渣 | E57: =专用糖!E57 -> 0 | G57: =专用糖!G57 -> #DIV/0! | I57: 其他业务收支-糖渣 | M57: =专用糖!M57 -> #DIV/0! | O57: =专用糖!O57 -> #DIV/0!
A62: 含税与不含税校验 | E62: =E37-专用糖!E37 -> #DIV/0! | G62: =G37-专用糖!G37 -> #DIV/0! | L62: check | M62: =M37-专用糖!M37 -> #DIV/0! | O62: =O37-专用糖!O37 -> #DIV/0!

Sheet 风味糖-含税
A1: =CONCATENATE("风味糖综合成本利润表_含税(2025年"&mth&"月)") -> 风味糖综合成本利润表_含税(2025年8月) | I1: =CONCATENATE("风味糖综合成本利润表_含税(2025年1-"&mth&"月)") -> 风味糖综合成本利润表_含税(2025年1-8月)
A3: 产量 | E3: 本月产量 | F3: =风味糖!F3 -> 0 | G3: 吨 | M3: 本年产量 | N3: =风味糖!N3 -> 415.89678 | O3: 吨
B4: 单位 | C4: 单价 | D4: 单耗 | E4: 单位成本 | F4: 总耗量 | G4: 总成本 | J4: 单位 | K4: 单价 | L4: 单耗 | M4: 单位成本 | N4: 总耗量 | O4: 总成本
A5: 一、收入 | E5: =E6-E7 -> 0 | G5: =G6-G7 -> 0 | I5: 一、收入 | M5: =M6-M7 -> 16042.264 | O5: =O6-O7 -> 6671926
A6: （一）销售价格 | E6: =OFFSET(销售收入及运费!C101,0,mth-1,1,1) -> 0 | G6: =风味糖!G6*1.13 -> 0 | I6: （一）销售价格 | M6: =销售收入及运费!O101 -> 18772.952 | O6: =M6*$N$3 -> 7807610.1
A7: （二）物流费 | E7: =OFFSET(销售收入及运费!C199,0,mth-1,1,1) -> 0 | G7: =E7*F3 -> 0 | I7: （二）物流费 | M7: =销售收入及运费!O199 -> 2730.6874 | O7: =M7*$N$3 -> 1135684.1
A8: 1、运费 | E8: =风味糖!E8*1.09 -> #DIV/0! | G8: =风味糖!G8*1.09 -> #DIV/0! | I8: 1、运费 | M8: =风味糖!M8*1.09 -> 395.50103 | O8: =风味糖!O8*1.09 -> 164487.6
A9: 2、包装费、租赁费等 | E9: =风味糖!E9*1.13 -> #DIV/0! | G9: =风味糖!G9*1.13 -> #DIV/0! | I9: 2、包装费、租赁费等 | M9: =风味糖!M9*1.13 -> 2335.1863 | O9: =风味糖!O9*1.13 -> 971196.48
A10: 二、变动成本 | E10: =E11+E20+E58+E63+E66+E57 -> #DIV/0! | G10: =G11+G20+G58+G63+G66+G57 -> #DIV/0! | I10: 二、变动成本 | M10: =M11+M20+M58+M63+M66+M57 -> #DIV/0! | O10: =O11+O20+O58+O63+O66+O57 -> #DIV/0!
A11: (一)直接材料 | B11: 吨 | C11: =IFERROR(风味糖!C11*1.13,0) -> 0 | D11: =IFERROR(IF(C11=0,0,E11/C11),0) -> 0 | E11: =SUM(E12:E19) -> #DIV/0! | F11: =SUM(F12:F19) -> 0 | G11: =SUM(G12:G19) -> 0 | I11: (一)直接材料 | J11: 吨 | K11: =IF(N11=0,0,O11/N11) -> 5325.8938 | L11: =IF(K11=0,0,M11/K11) -> 0.021447629 | M11: =SUM(M12:M19) -> 114.2278 | N11: =SUM(N12:N19) -> 8.92 | O11: =SUM(O12:O19) -> 47506.972
A12: F42果葡糖浆_半成品_71% | B12: 吨 | C12: =风味糖!C12*1.13 -> 0 | D12: =风味糖!D12 -> 0 | E12: =风味糖!E12*1.13 -> 0 | F12: =风味糖!F12 -> 0 | G12: =风味糖!G12*1.13 -> 0 | I12: F42果葡糖浆_半成品_71% | J12: 吨 | K12: =风味糖!K12*1.13 -> 0 | L12: =风味糖!L12 -> 0 | M12: =风味糖!M12*1.13 -> 0 | N12: =风味糖!N12 -> 0 | O12: =风味糖!O12*1.13 -> 0
A13: F55果葡糖浆_半成品_77.0% | B13: 吨 | C13: =风味糖!C13*1.13 -> 0 | D13: =风味糖!D13 -> 0 | E13: =风味糖!E13*1.13 -> 0 | F13: =风味糖!F13 -> 0 | G13: =风味糖!G13*1.13 -> 0 | I13: F55果葡糖浆_半成品_77.0% | J13: 吨 | K13: =风味糖!K13*1.13 -> 0 | L13: =风味糖!L13 -> 0 | M13: =风味糖!M13*1.13 -> 0 | N13: =风味糖!N13 -> 0 | O13: =风味糖!O13*1.13 -> 0
A14: F60果葡糖浆_半成品_77% | B14: 吨 | C14: =风味糖!C14*1.13 -> 0 | D14: =风味糖!D14 -> 0 | E14: =风味糖!E14*1.13 -> 0 | F14: =风味糖!F14 -> 0 | G14: =风味糖!G14*1.13 -> 0 | I14: F60果葡糖浆_半成品_77% | J14: 吨 | K14: =风味糖!K14*1.13 -> 0 | L14: =风味糖!L14 -> 0 | M14: =风味糖!M14*1.13 -> 0 | N14: =风味糖!N14 -> 0 | O14: =风味糖!O14*1.13 -> 0
A15: 麦芽糖M-70_半成品_75.5% | B15: 吨 | C15: =风味糖!C15*1.13 -> 0 | D15: =风味糖!D15 -> 0 | E15: =风味糖!E15*1.13 -> 0 | F15: =风味糖!F15 -> 0 | G15: =风味糖!G15*1.13 -> 0 | I15: 麦芽糖M-70_半成品_75.5% | J15: 吨 | K15: =风味糖!K15*1.13 -> 0 | L15: =风味糖!L15 -> 0 | M15: =风味糖!M15*1.13 -> 0 | N15: =风味糖!N15 -> 0 | O15: =风味糖!O15*1.13 -> 0
A16: 麦芽糖浆42DE_半成品_80.3% | B16: 吨 | C16: =风味糖!C16*1.13 -> 0 | D16: =风味糖!D16 -> 0 | E16: =风味糖!E16*1.13 -> 0 | F16: =风味糖!F16 -> 0 | G16: =风味糖!G16*1.13 -> 0 | I16: 麦芽糖浆42DE_半成品_80.3% | J16: 吨 | K16: =风味糖!K16*1.13 -> 0 | L16: =风味糖!L16 -> 0 | M16: =风味糖!M16*1.13 -> 0 | N16: =风味糖!N16 -> 0 | O16: =风味糖!O16*1.13 -> 0
A17: 麦芽糖浆（M40)_半成品_73.5% | B17: 吨 | C17: =风味糖!C17*1.13 -> 0 | D17: =风味糖!D17 -> 0 | E17: =风味糖!E17*1.13 -> 0 | F17: =风味糖!F17 -> 0 | G17: =风味糖!G17*1.13 -> 0 | I17: 麦芽糖浆（M40)_半成品_73.5% | J17: 吨 | K17: =风味糖!K17*1.13 -> 2755.9876 | L17: =风味糖!L17 -> 0.018562298 | M17: =风味糖!M17*1.13 -> 51.157463 | N17: =风味糖!N17 -> 7.72 | O17: =风味糖!O17*1.13 -> 21276.224
A18: 产成品及其他 | B18: 吨 | C18: =风味糖!C18*1.13 -> 0 | D18: =风味糖!D18 -> 0 | E18: =风味糖!E18*1.13 -> 0 | F18: =风味糖!F18 -> 0 | G18: =风味糖!G18*1.13 -> 0 | I18: 产成品及其他 | J18: 吨 | K18: =风味糖!K18*1.13 -> 6817.6064 | L18: =风味糖!L18 -> 0.0028853313 | M18: =风味糖!M18*1.13 -> 19.671053 | N18: =风味糖!N18 -> 1.2 | O18: =风味糖!O18*1.13 -> 8181.1277
A19: 灌装损耗 | B19: 吨 | C19: =风味糖!C19*1.13 -> 0 | D19: =风味糖!D19 -> 0 | E19: =风味糖!E19 -> #DIV/0! | F19: =风味糖!F19 -> 0 | G19: =风味糖!G19 -> 0 | I19: 灌装损耗 | J19: 吨 | K19: =风味糖!K19*1.13 -> 0 | L19: =风味糖!L19 -> 0 | M19: =风味糖!M19 -> 43.399279 | N19: =风味糖!N19 -> 0 | O19: =风味糖!O19 -> 18049.62
A20: (二）辅料 | E20: =风味糖!E20*1.13 -> 0 | G20: =风味糖!G20*1.13 -> 0 | I20: (二）辅料 | M20: =风味糖!M20*1.13 -> 5385.1715 | O20: =风味糖!O20*1.13 -> 2239675.5
A21: 无碘盐|通用|通用|食品级 | B21: 公斤 | C21: =风味糖!C21*1.13 -> 0 | D21: =风味糖!D21 -> 0 | E21: =风味糖!E21*1.13 -> 0 | F21: =风味糖!F21 -> 0 | G21: =风味糖!G21*1.13 -> 0 | I21: 无碘盐|通用|通用|食品级 | J21: 公斤 | K21: =分配表!O887 -> 0 | L21: =风味糖!L21 -> 0 | M21: =风味糖!M21*1.13 -> 0 | N21: =风味糖!N21 -> 0 | O21: =风味糖!O21*1.13 -> 0
A22: 柠檬酸钠_细目_优质 | B22: 公斤 | C22: =风味糖!C22*1.13 -> 0 | D22: =风味糖!D22 -> 0 | E22: =风味糖!E22*1.13 -> 0 | F22: =风味糖!F22 -> 0 | G22: =风味糖!G22*1.13 -> 0 | I22: 柠檬酸钠_细目_优质 | J22: 公斤 | K22: =分配表!O888 -> 0 | L22: =风味糖!L22 -> 0 | M22: =风味糖!M22*1.13 -> 0 | N22: =风味糖!N22 -> 0 | O22: =风味糖!O22*1.13 -> 0
A23: 白砂糖|50㎏|一级 | B23: 公斤 | C23: =风味糖!C23*1.13 -> 0 | D23: =风味糖!D23 -> 0 | E23: =风味糖!E23*1.13 -> 0 | F23: =风味糖!F23 -> 0 | G23: =风味糖!G23*1.13 -> 0 | I23: 白砂糖|50㎏|一级 | J23: 公斤 | K23: =分配表!O889 -> 0 | L23: =风味糖!L23 -> 0 | M23: =风味糖!M23*1.13 -> 0 | N23: =风味糖!N23 -> 0 | O23: =风味糖!O23*1.13 -> 0
A24: 红糖|25㎏ | B24: 公斤 | C24: =风味糖!C24*1.13 -> 0 | D24: =风味糖!D24 -> 0 | E24: =风味糖!E24*1.13 -> 0 | F24: =风味糖!F24 -> 0 | G24: =风味糖!G24*1.13 -> 0 | I24: 红糖|25㎏ | J24: 公斤 | K24: =分配表!O890 -> 0 | L24: =风味糖!L24 -> 0 | M24: =风味糖!M24*1.13 -> 0 | N24: =风味糖!N24 -> 0 | O24: =风味糖!O24*1.13 -> 0
A25: 白砂糖|50㎏|精制 | B25: 公斤 | C25: =风味糖!C25*1.13 -> 0 | D25: =风味糖!D25 -> 0 | E25: =风味糖!E25*1.13 -> 0 | F25: =风味糖!F25 -> 0 | G25: =风味糖!G25*1.13 -> 0 | I25: 白砂糖|50㎏|精制 | J25: 公斤 | K25: =分配表!O891 -> 6.8505889 | L25: =风味糖!L25 -> 430.26709 | M25: =风味糖!M25*1.13 -> 2947.583 | N25: =风味糖!N25 -> 178946.7 | O25: =风味糖!O25*1.13 -> 1225890.3
A26: 黑糖|25㎏|一级 | B26: 公斤 | C26: =风味糖!C26*1.13 -> 0 | D26: =风味糖!D26 -> 0 | E26: =风味糖!E26*1.13 -> 0 | F26: =风味糖!F26 -> 0 | G26: =风味糖!G26*1.13 -> 0 | I26: 黑糖|25㎏|一级 | J26: 公斤 | K26: =分配表!O892 -> 0 | L26: =风味糖!L26 -> 0 | M26: =风味糖!M26*1.13 -> 0 | N26: =风味糖!N26 -> 0 | O26: =风味糖!O26*1.13 -> 0
A27: 焦糖糖浆_罗盖特_SRC-8S7301_通用 | B27: 公斤 | C27: =风味糖!C27*1.13 -> 0 | D27: =风味糖!D27 -> 0 | E27: =风味糖!E27*1.13 -> 0 | F27: =风味糖!F27 -> 0 | G27: =风味糖!G27*1.13 -> 0 | I27: 焦糖糖浆_罗盖特_SRC-8S7301_通用 | J27: 公斤 | K27: =分配表!O893 -> 0 | L27: =风味糖!L27 -> 0 | M27: =风味糖!M27*1.13 -> 0 | N27: =风味糖!N27 -> 0 | O27: =风味糖!O27*1.13 -> 0
A28: 焦糖糖浆_罗盖特_SRC-3380_通用 | B28: 公斤 | C28: =风味糖!C28*1.13 -> 0 | D28: =风味糖!D28 -> 0 | E28: =风味糖!E28*1.13 -> 0 | F28: =风味糖!F28 -> 0 | G28: =风味糖!G28*1.13 -> 0 | I28: 焦糖糖浆_罗盖特_SRC-3380_通用 | J28: 公斤 | K28: =分配表!O894 -> 8.9992369 | L28: =风味糖!L28 -> 0.0069320085 | M28: =风味糖!M28*1.13 -> 0.062382787 | N28: =风味糖!N28 -> 2.883 | O28: =风味糖!O28*1.13 -> 25.9448
A29: 山梨酸钾_通用_食品级_通用 | B29: 公斤 | C29: =风味糖!C29*1.13 -> 0 | D29: =风味糖!D29 -> 0 | E29: =风味糖!E29*1.13 -> 0 | F29: =风味糖!F29 -> 0 | G29: =风味糖!G29*1.13 -> 0 | I29: 山梨酸钾_通用_食品级_通用 | J29: 公斤 | K29: =分配表!O895 -> 21.500051 | L29: =风味糖!L29 -> 0.4534178 | M29: =风味糖!M29*1.13 -> 9.7485059 | N29: =风味糖!N29 -> 188.575 | O29: =风味糖!O29*1.13 -> 4054.3722
A30: 玫瑰粉_通用_速溶_通用 | B30: 公斤 | C30: =风味糖!C30*1.13 -> 0 | D30: =风味糖!D30 -> 0 | E30: =风味糖!E30*1.13 -> 0 | F30: =风味糖!F30 -> 0 | G30: =风味糖!G30*1.13 -> 0 | I30: 玫瑰粉_通用_速溶_通用 | J30: 公斤 | K30: =分配表!O896 -> 350.00076 | L30: =风味糖!L30 -> 0.025967982 | M30: =风味糖!M30*1.13 -> 9.0888134 | N30: =风味糖!N30 -> 10.8 | O30: =风味糖!O30*1.13 -> 3780.0082
A31: 麦芽提取物_通用_固体黑麦精_通用 | B31: 吨 | C31: =风味糖!C31*1.13 -> 0 | D31: =风味糖!D31 -> 0 | E31: =风味糖!E31*1.13 -> 0 | F31: =风味糖!F31 -> 0 | G31: =风味糖!G31*1.13 -> 0 | I31: 麦芽提取物_通用_固体黑麦精_通用 | J31: 吨 | K31: =分配表!O897 -> 0 | L31: =风味糖!L31 -> 0 | M31: =风味糖!M31*1.13 -> 0 | N31: =风味糖!N31 -> 0 | O31: =风味糖!O31*1.13 -> 0
A32: 甜蜜素_通用_干燥减量≤0.5%_食品级 | B32: 公斤 | C32: =风味糖!C32*1.13 -> 0 | D32: =风味糖!D32 -> 0 | E32: =风味糖!E32*1.13 -> 0 | F32: =风味糖!F32 -> 0 | G32: =风味糖!G32*1.13 -> 0 | I32: 甜蜜素_通用_干燥减量≤0.5%_食品级 | J32: 公斤 | K32: =分配表!O898 -> 0 | L32: =风味糖!L32 -> 0 | M32: =风味糖!M32*1.13 -> 0 | N32: =风味糖!N32 -> 0 | O32: =风味糖!O32*1.13 -> 0
... A43: 藏青盐 | B43: 公斤 | C43: =风味糖!C43*1.13 -> 0 | D43: =风味糖!D43 -> 0 | E43: =风味糖!E43*1.13 -> 0 | F43: =风味糖!F43 -> 0 | G43: =风味糖!G43*1.13 -> 0 | I43: 藏青盐 | J43: 公斤 | K43: =分配表!O909 -> 10.978549 | L43: =风味糖!L43 -> 29.776619 | M43: =风味糖!M43*1.13 -> 326.90406 | N43: =风味糖!N43 -> 12384 | O43: =风味糖!O43*1.13 -> 135958.35
A44: 食用香精_通用_液体香精_GB30616-2020 | C44: =风味糖!C44*1.13 -> 0 | D44: =风味糖!D44 -> 0 | E44: =风味糖!E44*1.13 -> 0 | F44: =风味糖!F44 -> 0 | G44: =风味糖!G44*1.13 -> 0 | I44: 食用香精_通用_液体香精_GB30616-2020 | K44: =分配表!O910 -> 0 | L44: =风味糖!L44 -> 0 | M44: =风味糖!M44*1.13 -> 0 | N44: =风味糖!N44 -> 0 | O44: =风味糖!O44*1.13 -> 0
A45: 其它香精_通用_液体香精_SHRS0140 | C45: =风味糖!C45*1.13 -> 0 | D45: =风味糖!D45 -> 0 | E45: =风味糖!E45*1.13 -> 0 | F45: =风味糖!F45 -> 0 | G45: =风味糖!G45*1.13 -> 0 | I45: 其它香精_通用_液体香精_SHRS0140 | K45: =分配表!O911 -> 140.00079 | L45: =风味糖!L45 -> 0.048088855 | M45: =风味糖!M45*1.13 -> 6.7324775 | N45: =风味糖!N45 -> 20 | O45: =风味糖!O45*1.13 -> 2800.0157
A46: 苯甲酸钠_通用_通用_通用 | C46: =风味糖!C46*1.13 -> 0 | D46: =风味糖!D46 -> 0 | E46: =风味糖!E46*1.13 -> 0 | F46: =风味糖!F46 -> 0 | G46: =风味糖!G46*1.13 -> 0 | I46: 苯甲酸钠_通用_通用_通用 | K46: =分配表!O912 -> 0 | L46: =风味糖!L46 -> 0 | M46: =风味糖!M46*1.13 -> 0 | N46: =风味糖!N46 -> 0 | O46: =风味糖!O46*1.13 -> 0
A47: 其它香精_通用_液体香精_SHRS0100 | C47: =风味糖!C47*1.13 -> 0 | D47: =风味糖!D47 -> 0 | E47: =风味糖!E47*1.13 -> 0 | F47: =风味糖!F47 -> 0 | G47: =风味糖!G47*1.13 -> 0 | I47: 其它香精_通用_液体香精_SHRS0100 | K47: =分配表!O913 -> 117.4195 | L47: =风味糖!L47 -> 0.03952423 | M47: =风味糖!M47*1.13 -> 4.6409153 | N47: =风味糖!N47 -> 16.438 | O47: =风味糖!O47*1.13 -> 1930.1417
A48: =风味糖!A48 -> 其它香精_通用_液体香精_SHRS0120 | C48: =风味糖!C48*1.13 -> 0 | D48: =风味糖!D48 -> 0 | E48: =风味糖!E48*1.13 -> 0 | F48: =风味糖!F48 -> 0 | G48: =风味糖!G48*1.13 -> 0 | I48: =A48 -> 其它香精_通用_液体香精_SHRS0120 | K48: =分配表!O914 -> 123.00002 | L48: =风味糖!L48 -> 0.7153626 | M48: =风味糖!M48*1.13 -> 87.989617 | N48: =风味糖!N48 -> 297.517 | O48: =风味糖!O48*1.13 -> 36594.598
A49: =风味糖!A49 -> 甘蔗香精_通用_通用 | C49: =风味糖!C49*1.13 -> 0 | D49: =风味糖!D49 -> 0 | E49: =风味糖!E49*1.13 -> 0 | F49: =风味糖!F49 -> 0 | G49: =风味糖!G49*1.13 -> 0 | I49: =A49 -> 甘蔗香精_通用_通用 | K49: =分配表!O915 -> 0 | L49: =风味糖!L49 -> 0 | M49: =风味糖!M49*1.13 -> 0 | N49: =风味糖!N49 -> 0 | O49: =风味糖!O49*1.13 -> 0
A50: =风味糖!A50 -> 炒板栗香精_通用_通用 | C50: =风味糖!C50*1.13 -> 0 | D50: =风味糖!D50 -> 0 | E50: =风味糖!E50*1.13 -> 0 | F50: =风味糖!F50 -> 0 | G50: =风味糖!G50*1.13 -> 0 | I50: =A50 -> 炒板栗香精_通用_通用 | K50: =分配表!O916 -> 0 | L50: =风味糖!L50 -> 0 | M50: =风味糖!M50*1.13 -> 0 | N50: =风味糖!N50 -> 0 | O50: =风味糖!O50*1.13 -> 0
A51: =风味糖!A51 -> 其它香精_通用_液体香精_SHRS0160 | C51: =风味糖!C51*1.13 -> 0 | D51: =风味糖!D51 -> 0 | E51: =风味糖!E51*1.13 -> 0 | F51: =风味糖!F51 -> 0 | G51: =风味糖!G51*1.13 -> 0 | I51: =A51 -> 其它香精_通用_液体香精_SHRS0160 | K51: =分配表!O917 -> 179.28001 | L51: =风味糖!L51 -> 0.026097822 | M51: =风味糖!M51*1.13 -> 4.6788177 | N51: =风味糖!N51 -> 10.854 | O51: =风味糖!O51*1.13 -> 1945.9052
A52: =风味糖!A52 -> 其它香精_通用_液体香精_SHRS0240 | C52: =风味糖!C52*1.13 -> 0 | D52: =风味糖!D52 -> 0 | E52: =风味糖!E52*1.13 -> 0 | F52: =风味糖!F52 -> 0 | G52: =风味糖!G52*1.13 -> 0 | I52: =A52 -> 其它香精_通用_液体香精_SHRS0240 | K52: =分配表!O918 -> 258.00469 | L52: =风味糖!L52 -> 0.0079418745 | M52: =风味糖!M52*1.13 -> 2.0490409 | N52: =风味糖!N52 -> 3.303 | O52: =风味糖!O52*1.13 -> 852.1895
A53: =风味糖!A53 -> 其它香精_通用_液体香精_SHRS0220 | C53: =风味糖!C53*1.13 -> 0 | D53: =风味糖!D53 -> 0 | E53: =风味糖!E53*1.13 -> 0 | F53: =风味糖!F53 -> 0 | G53: =风味糖!G53*1.13 -> 0 | I53: =A53 -> 其它香精_通用_液体香精_SHRS0220 | K53: =分配表!O919 -> 227.2648 | L53: =风味糖!L53 -> 0.031685747 | M53: =风味糖!M53*1.13 -> 7.2010548 | N53: =风味糖!N53 -> 13.178 | O53: =风味糖!O53*1.13 -> 2994.8955
A54: =风味糖!A54 -> 甘蔗多酚_通用 | C54: =风味糖!C54*1.13 -> 0 | D54: =风味糖!D54 -> 0 | E54: =风味糖!E54*1.13 -> 0 | F54: =风味糖!F54 -> 0 | G54: =风味糖!G54*1.13 -> 0 | I54: =A54 -> 甘蔗多酚_通用 | K54: =分配表!O920 -> 0 | L54: =风味糖!L54 -> 0 | M54: =风味糖!M54*1.13 -> 0 | N54: =风味糖!N54 -> 0 | O54: =风味糖!O54*1.13 -> 0
A55: =风味糖!A55 -> 其它香精_通用_液体香精_SHRS0200 | C55: =风味糖!C55*1.13 -> 0 | D55: =风味糖!D55 -> 0 | E55: =风味糖!E55*1.13 -> 0 | F55: =风味糖!F55 -> 0 | G55: =风味糖!G55*1.13 -> 0 | I55: =A55 -> 其它香精_通用_液体香精_SHRS0200 | K55: =分配表!O921 -> 217.00024 | L55: =风味糖!L55 -> 0.011882756 | M55: =风味糖!M55*1.13 -> 2.578561 | N55: =风味糖!N55 -> 4.942 | O55: =风味糖!O55*1.13 -> 1072.4152
A56: =风味糖!A56 -> 无水柠檬酸_细目 | C56: =风味糖!C56*1.13 -> 0 | D56: =风味糖!D56 -> 0 | E56: =风味糖!E56*1.13 -> 0 | F56: =风味糖!F56 -> 0 | G56: =风味糖!G56*1.13 -> 0 | I56: =A56 -> 无水柠檬酸_细目 | K56: =分配表!O922 -> 6149.9815 | L56: =风味糖!L56 -> 0.00093773268 | M56: =风味糖!M56*1.13 -> 5.7670387 | N56: =风味糖!N56 -> 0.39 | O56: =风味糖!O56*1.13 -> 2398.4928
A57: (三)包装物 | I57: (三)包装物
A58: (四)动力能源 | E58: =SUM(E59:E62) -> 0 | G58: =SUM(G59:G62) -> 0 | I58: (四)动力能源 | M58: =SUM(M59:M62) -> #DIV/0! | O58: =SUM(O59:O62) -> #DIV/0!
A59: 1、蒸汽 | B59: 吨 | C59: =OFFSET(分配表!C306,0,mth-1,1,1) -> 0 | D59: =风味糖!D59 -> 0 | E59: =C59*D59 -> 0 | F59: =风味糖!F59 -> #DIV/0! | G59: =E59*F$3 -> 0 | I59: 1、蒸汽 | J59: 吨 | K59: =分配表!O306 -> 408.53094 | L59: =风味糖!L59 -> #DIV/0! | M59: =K59*L59 -> #DIV/0! | N59: =风味糖!N59 -> #DIV/0! | O59: =M59*N$3 -> #DIV/0!
A60: 2、电 | B60: 度 | C60: =风味糖!C60*1.13 -> 0 | D60: =风味糖!D60 -> 0 | E60: =风味糖!E60*1.13 -> 0 | F60: =风味糖!F60 -> #DIV/0! | G60: =风味糖!G60*1.13 -> 0 | I60: 2、电 | J60: 度 | K60: =风味糖!K60*1.13 -> 0.76911958 | L60: =风味糖!L60 -> #DIV/0! | M60: =风味糖!M60*1.13 -> #DIV/0! | N60: =风味糖!N60 -> #DIV/0! | O60: =风味糖!O60*1.13 -> #DIV/0!
A61: 3、水 | B61: 吨 | C61: =3.32+0.9*2.97 -> 5.993 | D61: =风味糖!D61 -> 0 | E61: =D61*C61 -> 0 | F61: =风味糖!F61 -> #DIV/0! | G61: =E61*F3 -> 0 | I61: 3、水 | J61: 吨 | K61: 5.993 | L61: =风味糖!L61 -> #DIV/0! | M61: =L61*K61 -> #DIV/0! | N61: =风味糖!N61 -> #DIV/0! | O61: =M61*N3 -> #DIV/0!
A62: 4、其他 | B62: M3 | I62: 4、其他 | J62: M3
A63: (五)排污费 | E63: =风味糖!E63*1.13 -> 0 | G63: =风味糖!G63*1.13 -> #DIV/0! | I63: (五)排污费 | M63: =风味糖!M63*1.13 -> #DIV/0! | O63: =风味糖!O63*1.13 -> #DIV/0!
A64: 1.污水处理 | E64: =E63 -> 0 | G64: =G63 -> #DIV/0! | I64: 1.污水处理 | M64: =M63 -> #DIV/0! | O64: =O63 -> #DIV/0!
A65: 2.污水固定成本 | I65: 2.污水固定成本
A66: (六)增值税 | E66: =IF(VALUE(F$3)=0,0,G66/F$3) -> 0 | G66: =SUM(G5,-G11,-G20,-G58,-G63,-G57)-SUM(风味糖!G5,-风味糖!G11,-风味糖!G20,-风味糖!G58,-风味糖!G63,-风味糖!G57) -> #DIV/0! | I66: (五)增值税 | M66: =IF(N$3=0,0,O66/N$3) -> #DIV/0! | O66: =SUM(O5,-O11,-O20,-O58,-O63,-O57)-SUM(风味糖!O5,-风味糖!O11,-风味糖!O20,-风味糖!O58,-风味糖!O63,-风味糖!O57) -> #DIV/0!
A67: 三、边际贡献 | E67: =E5-E10 -> #DIV/0! | G67: =G5-G10 -> #DIV/0! | I67: 三、边际贡献 | M67: =M5-M10 -> #DIV/0! | O67: =O5-O10 -> #DIV/0!
A68: 四、固定成本 | E68: =SUM(E69:E75) -> 0 | G68: =SUM(G69:G75) -> #DIV/0! | I68: 四、固定成本 | M68: =IF(N$3=0,0,O68/N$3) -> #DIV/0! | O68: =SUM(O69:O75) -> #DIV/0!
A69: （一）折旧与摊销 | E69: =风味糖!E69 -> 0 | G69: =风味糖!G69 -> #DIV/0! | I69: （一）折旧与摊销 | M69: =风味糖!M69 -> #DIV/0! | O69: =风味糖!O69 -> #DIV/0!
A70: （二）工资 | E70: =风味糖!E70 -> 0 | G70: =风味糖!G70 -> #DIV/0! | I70: （二）工资 | M70: =风味糖!M70 -> #DIV/0! | O70: =风味糖!O70 -> #DIV/0!
A71: （三）制造费用 | E71: =风味糖!E71 -> 0 | G71: =风味糖!G71 -> #DIV/0! | I71: （三）制造费用 | M71: =风味糖!M71 -> #DIV/0! | O71: =风味糖!O71 -> #DIV/0!
A72: （四）销售费用 | E72: =风味糖!E72 -> 0 | G72: =风味糖!G72 -> #DIV/0! | I72: （四）销售费用 | M72: =风味糖!M72 -> #DIV/0! | O72: =风味糖!O72 -> #DIV/0!
A73: （五）管理费用 | E73: =风味糖!E73 -> 0 | G73: =风味糖!G73 -> #DIV/0! | I73: （五）管理费用 | M73: =风味糖!M73 -> #DIV/0! | O73: =风味糖!O73 -> #DIV/0!
A74: （六）财务费用 | E74: =风味糖!E74 -> 0 | G74: =风味糖!G74 -> #DIV/0! | I74: （六）财务费用 | M74: =风味糖!M74 -> #DIV/0! | O74: =风味糖!O74 -> #DIV/0!
A75: （七）其他 | E75: =风味糖!E75 -> 0 | G75: =风味糖!G75 -> #DIV/0! | I75: （七） 其他 | M75: =风味糖!M75 -> #DIV/0! | O75: =风味糖!O75 -> #DIV/0!
A76: 其中：税金及附加 | E76: =风味糖!E76 -> 0 | G76: =风味糖!G76 -> #DIV/0! | I76: 其中：税金及附加 | M76: =风味糖!M76 -> #DIV/0! | O76: =风味糖!O76 -> #DIV/0!
A77: 其他业务收支 | E77: =风味糖!E77 -> 0 | G77: =风味糖!G77 -> #DIV/0! | I77: 其他业务收支 | M77: =风味糖!M77 -> #DIV/0! | O77: =风味糖!O77 -> #DIV/0!
A78: 营业外收支 | E78: =风味糖!E78 -> 0 | G78: =风味糖!G78 -> #DIV/0! | I78: 营业外收支 | M78: =风味糖!M78 -> #DIV/0! | O78: =风味糖!O78 -> #DIV/0!
A79: 投资收益+公允价值变动损益 | E79: =风味糖!E79 -> 0 | G79: =风味糖!G79 -> #DIV/0! | I79: 投资收益+公允价值变动损益 | M79: =风味糖!M79 -> #DIV/0! | O79: =风味糖!O79 -> #DIV/0!
A80: 其他收益 | E80: =风味糖!E80 -> 0 | G80: =风味糖!G80 -> #DIV/0! | I80: 其他收益 | M80: =风味糖!M80 -> #DIV/0! | O80: =风味糖!O80 -> #DIV/0!
... A82: 其他 | E82: =风味糖!E82 -> 0 | G82: =风味糖!G82 -> #DIV/0! | I82: 其他 | M82: =风味糖!M82 -> #DIV/0! | O82: =风味糖!O82 -> #DIV/0!
A83: 五、完全成本 | B83: 元 | E83: =E68+E10 -> #DIV/0! | G83: =G68+G10 -> #DIV/0! | I83: 五、完全成本 | J83: 元 | M83: =M68+M10 -> #DIV/0! | O83: =O68+O10 -> #DIV/0!
A84: 六、利润总额 | B84: 元 | E84: =E67-E68 -> #DIV/0! | G84: =G67-G68 -> #DIV/0! | I84: 六、利润总额 | J84: 元 | M84: =M67-M68 -> #DIV/0! | O84: =O67-O68 -> #DIV/0!
A85: 七、现金流 | B85: 元 | E85: =E84+E69 -> #DIV/0! | G85: =G84+G69 -> #DIV/0! | I85: 七、现金流 | J85: 元 | M85: =M84+M69 -> #DIV/0! | O85: =O84+O69 -> #DIV/0!
A86: 加工费 | B86: 元 | E86: =E10-E11+E68-E57 -> #DIV/0! | G86: =G10-G11+G68-G57 -> #DIV/0! | I86: 加工费 | J86: 元 | M86: =M10-M11+M68-M57 -> #DIV/0! | O86: =O10-O11+O68-O57 -> #DIV/0!
A87: 其他业务收支-糖渣 | E87: =风味糖!E87 -> 0 | G87: =风味糖!G87 -> #DIV/0! | I87: 其他业务收支-糖渣 | M87: =风味糖!M87 -> #DIV/0! | O87: =风味糖!O87 -> #DIV/0!
A92: 含税与不含税校验 | E92: =E67-风味糖!E67 -> #DIV/0! | G92: =G67-风味糖!G67 -> #DIV/0! | L92: check | M92: =M67-风味糖!M67 -> #DIV/0! | O92: =O67-风味糖!O67 -> #DIV/0!

Sheet 调味糖-含税
A1: =CONCATENATE("调味糖综合成本利润表_含税(2025年"&mth&"月)") -> 调味糖综合成本利润表_含税(2025年8月) | I1: =CONCATENATE("调味糖综合成本利润表_含税(2025年1-"&mth&"月)") -> 调味糖综合成本利润表_含税(2025年1-8月)
A3: 产量 | E3: 本月产量 | F3: =调味糖!F3 -> 0 | G3: 吨 | M3: 本年产量 | N3: =调味糖!N3 -> 773.71106 | O3: 吨
B4: 单位 | C4: 单价 | D4: 单耗 | E4: 单位成本 | F4: 总耗量 | G4: 总成本 | J4: 单位 | K4: 单价 | L4: 单耗 | M4: 单位成本 | N4: 总耗量 | O4: 总成本
A5: 一、收入 | E5: =E6-E7 -> 0 | G5: =G6-G7 -> 0 | I5: 一、收入 | M5: =M6-M7 -> 6486.952 | O5: =O6-O7 -> 5019026.5
A6: （一）销售价格 | E6: =OFFSET(销售收入及运费!C102,0,mth-1,1,1) -> 0 | G6: =调味糖!G6*1.13 -> 0 | I6: （一）销售价格 | M6: =销售收入及运费!O102 -> 7966.1591 | O6: =M6*$N$3 -> 6163505.4
A7: （二）物流费 | E7: =OFFSET(销售收入及运费!C200,0,mth-1,1,1) -> 0 | G7: =E7*F3 -> 0 | I7: （二）物流费 | M7: =销售收入及运费!O200 -> 1479.2071 | O7: =M7*$N$3 -> 1144478.9
A8: 1、运费 | E8: =调味糖!E8*1.09 -> #DIV/0! | G8: =调味糖!G8*1.09 -> #DIV/0! | I8: 1、运费 | M8: =调味糖!M8*1.09 -> 258.62759 | O8: =调味糖!O8*1.09 -> 200103.03
A9: 2、包装费、租赁费等 | E9: =调味糖!E9*1.13 -> #DIV/0! | G9: =调味糖!G9*1.13 -> #DIV/0! | I9: 2、包装费、租赁费等 | M9: =调味糖!M9*1.13 -> 1220.5795 | O9: =调味糖!O9*1.13 -> 944375.82
A10: 二、变动成本 | E10: =E11+E20+E50+E55+E58+E49 -> #DIV/0! | G10: =G11+G20+G50+G55+G58+G49 -> #DIV/0! | I10: 二、变动成本 | M10: =M11+M20+M50+M55+M58+M49 -> #DIV/0! | O10: =O11+O20+O50+O55+O58+O49 -> #DIV/0!
A11: (一)直接材料 | B11: 吨 | C11: =IFERROR(调味糖!C11*1.13,0) -> 0 | D11: =IFERROR(IF(C11=0,0,E11/C11),0) -> 0 | E11: =SUM(E12:E19) -> #DIV/0! | F11: =SUM(F12:F19) -> 0 | G11: =SUM(G12:G19) -> 0 | I11: (一)直接材料 | J11: 吨 | K11: =IF(N11=0,0,O11/N11) -> 2872.3401 | L11: =IF(K11=0,0,M11/K11) -> 0.52464547 | M11: =SUM(M12:M19) -> 1506.9602 | N11: =SUM(N12:N19) -> 405.924 | O11: =SUM(O12:O19) -> 1165951.8
A12: F42果葡糖浆_半成品_71% | B12: 吨 | C12: =调味糖!C12*1.13 -> 0 | D12: =调味糖!D12 -> 0 | E12: =调味糖!E12*1.13 -> 0 | F12: =调味糖!F12 -> 0 | G12: =调味糖!G12*1.13 -> 0 | I12: F42果葡糖浆_半成品_71% | J12: 吨 | K12: =调味糖!K12*1.13 -> 2428.0951 | L12: =调味糖!L12 -> 0.0789442 | M12: =调味糖!M12*1.13 -> 191.68402 | N12: =调味糖!N12 -> 61.08 | O12: =调味糖!O12*1.13 -> 148308.05
A13: F55果葡糖浆_半成品_77.0% | B13: 吨 | C13: =调味糖!C13*1.13 -> 0 | D13: =调味糖!D13 -> 0 | E13: =调味糖!E13*1.13 -> 0 | F13: =调味糖!F13 -> 0 | G13: =调味糖!G13*1.13 -> 0 | I13: F55果葡糖浆_半成品_77.0% | J13: 吨 | K13: =调味糖!K13*1.13 -> 2641.9558 | L13: =调味糖!L13 -> 0.33607766 | M13: =调味糖!M13*1.13 -> 887.90231 | N13: =调味糖!N13 -> 260.027 | O13: =调味糖!O13*1.13 -> 686979.83
A14: F60果葡糖浆_半成品_77% | B14: 吨 | C14: =调味糖!C14*1.13 -> 0 | D14: =调味糖!D14 -> 0 | E14: =调味糖!E14*1.13 -> 0 | F14: =调味糖!F14 -> 0 | G14: =调味糖!G14*1.13 -> 0 | I14: F60果葡糖浆_半成品_77% | J14: 吨 | K14: =调味糖!K14*1.13 -> 2901.1829 | L14: =调味糖!L14 -> 0.0092334211 | M14: =调味糖!M14*1.13 -> 26.787844 | N14: =调味糖!N14 -> 7.144 | O14: =调味糖!O14*1.13 -> 20726.051
A15: 麦芽糖M-70_半成品_75.5% | B15: 吨 | C15: =调味糖!C15*1.13 -> 0 | D15: =调味糖!D15 -> 0 | E15: =调味糖!E15*1.13 -> 0 | F15: =调味糖!F15 -> 0 | G15: =调味糖!G15*1.13 -> 0 | I15: 麦芽糖M-70_半成品_75.5% | J15: 吨 | K15: =调味糖!K15*1.13 -> 2969.6593 | L15: =调味糖!L15 -> 0.0015923257 | M15: =调味糖!M15*1.13 -> 4.7286648 | N15: =调味糖!N15 -> 1.232 | O15: =调味糖!O15*1.13 -> 3658.6202
A16: 麦芽糖浆42DE_半成品_80.3% | B16: 吨 | C16: =调味糖!C16*1.13 -> 0 | D16: =调味糖!D16 -> 0 | E16: =调味糖!E16*1.13 -> 0 | F16: =调味糖!F16 -> 0 | G16: =调味糖!G16*1.13 -> 0 | I16: 麦芽糖浆42DE_半成品_80.3% | J16: 吨 | K16: =调味糖!K16*1.13 -> 3151.3052 | L16: =调味糖!L16 -> 0.097873747 | M16: =调味糖!M16*1.13 -> 308.43005 | N16: =调味糖!N16 -> 75.726 | O16: =调味糖!O16*1.13 -> 238635.74
A17: 麦芽糖浆（M40)_半成品_73.5% | B17: 吨 | C17: =调味糖!C17*1.13 -> 0 | D17: =调味糖!D17 -> 0 | E17: =调味糖!E17*1.13 -> 0 | F17: =调味糖!F17 -> 0 | G17: =调味糖!G17*1.13 -> 0 | I17: 麦芽糖浆（M40)_半成品_73.5% | J17: 吨 | K17: =调味糖!K17*1.13 -> 0 | L17: =调味糖!L17 -> 0 | M17: =调味糖!M17*1.13 -> 0 | N17: =调味糖!N17 -> 0 | O17: =调味糖!O17*1.13 -> 0
A18: 产成品及其他 | B18: 吨 | C18: =调味糖!C18*1.13 -> 0 | D18: =调味糖!D18 -> 0 | E18: =调味糖!E18*1.13 -> 0 | F18: =调味糖!F18 -> 0 | G18: =调味糖!G18*1.13 -> 0 | I18: 产成品及其他 | J18: 吨 | K18: =调味糖!K18*1.13 -> 4664.5957 | L18: =调味糖!L18 -> 0.0009241176 | M18: =调味糖!M18*1.13 -> 4.310635 | N18: =调味糖!N18 -> 0.715 | O18: =调味糖!O18*1.13 -> 3335.186
A19: 灌装损耗 | B19: 吨 | C19: =调味糖!C19*1.13 -> 0 | D19: =调味糖!D19 -> 0 | E19: =调味糖!E19 -> #DIV/0! | F19: =调味糖!F19 -> 0 | G19: =调味糖!G19 -> 0 | I19: 灌装损耗 | J19: 吨 | K19: =调味糖!K19*1.13 -> 0 | L19: =调味糖!L19 -> 0 | M19: =调味糖!M19 -> 83.116708 | N19: =调味糖!N19 -> 0 | O19: =调味糖!O19 -> 64308.316
A20: (二）辅料 | E20: =调味糖!E20*1.13 -> 0 | G20: =调味糖!G20*1.13 -> 0 | I20: (二）辅料 | M20: =调味糖!M20*1.13 -> 2233.1278 | O20: =调味糖!O20*1.13 -> 1727795.7
A21: 无碘盐|通用|通用|食品级 | B21: 公斤 | C21: =调味糖!C21*1.13 -> 0 | D21: =调味糖!D21 -> 0 | E21: =调味糖!E21*1.13 -> 0 | F21: =调味糖!F21 -> 0 | G21: =调味糖!G21*1.13 -> 0 | I21: 无碘盐|通用|通用|食品级 | J21: 公斤 | K21: =分配表!O926 -> 0 | L21: =调味糖!L21 -> 0 | M21: =调味糖!M21*1.13 -> 0 | N21: =调味糖!N21 -> 0 | O21: =调味糖!O21*1.13 -> 0
A22: 柠檬酸钠_细目_优质 | B22: 公斤 | C22: =调味糖!C22*1.13 -> 0 | D22: =调味糖!D22 -> 0 | E22: =调味糖!E22*1.13 -> 0 | F22: =调味糖!F22 -> 0 | G22: =调味糖!G22*1.13 -> 0 | I22: 柠檬酸钠_细目_优质 | J22: 公斤 | K22: =分配表!O927 -> 5.9561412 | L22: =调味糖!L22 -> 1.008516 | M22: =调味糖!M22*1.13 -> 6.0068639 | N22: =调味糖!N22 -> 780.3 | O22: =调味糖!O22*1.13 -> 4647.577
A23: 白砂糖|50㎏|一级 | B23: 公斤 | C23: =调味糖!C23*1.13 -> 0 | D23: =调味糖!D23 -> 0 | E23: =调味糖!E23*1.13 -> 0 | F23: =调味糖!F23 -> 0 | G23: =调味糖!G23*1.13 -> 0 | I23: 白砂糖|50㎏|一级 | J23: 公斤 | K23: =分配表!O928 -> 0 | L23: =调味糖!L23 -> 0 | M23: =调味糖!M23*1.13 -> 0 | N23: =调味糖!N23 -> 0 | O23: =调味糖!O23*1.13 -> 0
A24: 红糖|25㎏ | B24: 公斤 | C24: =调味糖!C24*1.13 -> 0 | D24: =调味糖!D24 -> 0 | E24: =调味糖!E24*1.13 -> 0 | F24: =调味糖!F24 -> 0 | G24: =调味糖!G24*1.13 -> 0 | I24: 红糖|25㎏ | J24: 公斤 | K24: =分配表!O929 -> 6.4469616 | L24: =调味糖!L24 -> 26.340583 | M24: =调味糖!M24*1.13 -> 169.81673 | N24: =调味糖!N24 -> 20380 | O24: =调味糖!O24*1.13 -> 131389.08
A25: 白砂糖|50㎏|精制 | B25: 公斤 | C25: =调味糖!C25*1.13 -> 0 | D25: =调味糖!D25 -> 0 | E25: =调味糖!E25*1.13 -> 0 | F25: =调味糖!F25 -> 0 | G25: =调味糖!G25*1.13 -> 0 | I25: 白砂糖|50㎏|精制 | J25: 公斤 | K25: =分配表!O930 -> 6.8459601 | L25: =调味糖!L25 -> 67.765691 | M25: =调味糖!M25*1.13 -> 463.92122 | N25: =调味糖!N25 -> 52431.064 | O25: =调味糖!O25*1.13 -> 358940.97
A26: 黑糖|25㎏|一级 | B26: 公斤 | C26: =调味糖!C26*1.13 -> 0 | D26: =调味糖!D26 -> 0 | E26: =调味糖!E26*1.13 -> 0 | F26: =调味糖!F26 -> 0 | G26: =调味糖!G26*1.13 -> 0 | I26: 黑糖|25㎏|一级 | J26: 公斤 | K26: =分配表!O931 -> 6.705329 | L26: =调味糖!L26 -> 33.061438 | M26: =调味糖!M26*1.13 -> 221.68782 | N26: =调味糖!N26 -> 25580 | O26: =调味糖!O26*1.13 -> 171522.32
A27: 焦糖糖浆_罗盖特_SRC-8S7301_通用 | B27: 公斤 | C27: =调味糖!C27*1.13 -> 0 | D27: =调味糖!D27 -> 0 | E27: =调味糖!E27*1.13 -> 0 | F27: =调味糖!F27 -> 0 | G27: =调味糖!G27*1.13 -> 0 | I27: 焦糖糖浆_罗盖特_SRC-8S7301_通用 | J27: 公斤 | K27: =分配表!O932 -> 17.503518 | L27: =调味糖!L27 -> 1.3267227 | M27: =调味糖!M27*1.13 -> 23.222315 | N27: =调味糖!N27 -> 1026.5 | O27: =调味糖!O27*1.13 -> 17967.362
A28: 焦糖糖浆_罗盖特_SRC-3380_通用 | B28: 公斤 | C28: =调味糖!C28*1.13 -> 0 | D28: =调味糖!D28 -> 0 | E28: =调味糖!E28*1.13 -> 0 | F28: =调味糖!F28 -> 0 | G28: =调味糖!G28*1.13 -> 0 | I28: 焦糖糖浆_罗盖特_SRC-3380_通用 | J28: 公斤 | K28: =分配表!O933 -> 8.9999587 | L28: =调味糖!L28 -> 0.38466169 | M28: =调味糖!M28*1.13 -> 3.4619393 | N28: =调味糖!N28 -> 297.617 | O28: =调味糖!O28*1.13 -> 2678.5407
A29: 山梨酸钾_通用_食品级_通用 | B29: 公斤 | C29: =调味糖!C29*1.13 -> 0 | D29: =调味糖!D29 -> 0 | E29: =调味糖!E29*1.13 -> 0 | F29: =调味糖!F29 -> 0 | G29: =调味糖!G29*1.13 -> 0 | I29: 山梨酸钾_通用_食品级_通用 | J29: 公斤 | K29: =分配表!O934 -> 21.499922 | L29: =调味糖!L29 -> 0.37994029 | M29: =调味糖!M29*1.13 -> 8.1686864 | N29: =调味糖!N29 -> 293.964 | O29: =调味糖!O29*1.13 -> 6320.203
A30: 玫瑰粉_通用_速溶_通用 | B30: 公斤 | C30: =调味糖!C30*1.13 -> 0 | D30: =调味糖!D30 -> 0 | E30: =调味糖!E30*1.13 -> 0 | F30: =调味糖!F30 -> 0 | G30: =调味糖!G30*1.13 -> 0 | I30: 玫瑰粉_通用_速溶_通用 | J30: 公斤 | K30: =分配表!O935 -> 0 | L30: =调味糖!L30 -> 0 | M30: =调味糖!M30*1.13 -> 0 | N30: =调味糖!N30 -> 0 | O30: =调味糖!O30*1.13 -> 0
A31: 麦芽提取物_通用_固体黑麦精_通用 | B31: 吨 | C31: =调味糖!C31*1.13 -> 0 | D31: =调味糖!D31 -> 0 | E31: =调味糖!E31*1.13 -> 0 | F31: =调味糖!F31 -> 0 | G31: =调味糖!G31*1.13 -> 0 | I31: 麦芽提取物_通用_固体黑麦精_通用 | J31: 吨 | K31: =分配表!O936 -> 15.500003 | L31: =调味糖!L31 -> 0.88922085 | M31: =调味糖!M31*1.13 -> 13.782926 | N31: =调味糖!N31 -> 688 | O31: =调味糖!O31*1.13 -> 10664.002
A32: 甜蜜素_通用_干燥减量≤0.5%_食品级 | B32: 公斤 | C32: =调味糖!C32*1.13 -> 0 | D32: =调味糖!D32 -> 0 | E32: =调味糖!E32*1.13 -> 0 | F32: =调味糖!F32 -> 0 | G32: =调味糖!G32*1.13 -> 0 | I32: 甜蜜素_通用_干燥减量≤0.5%_食品级 | J32: 公斤 | K32: =分配表!O937 -> 20.999794 | L32: =调味糖!L32 -> 0.093057996 | M32: =调味糖!M32*1.13 -> 1.9541988 | N32: =调味糖!N32 -> 72 | O32: =调味糖!O32*1.13 -> 1511.9852
A33: 三氯蔗糖_通用_通用_食品级 | B33: 公斤 | C33: =调味糖!C33*1.13 -> 0 | D33: =调味糖!D33 -> 0 | E33: =调味糖!E33*1.13 -> 0 | F33: =调味糖!F33 -> 0 | G33: =调味糖!G33*1.13 -> 0 | I33: 三氯蔗糖_通用_通用_食品级 | J33: 公斤 | K33: =分配表!O938 -> 270.00003 | L33: =调味糖!L33 -> 0.033604276 | M33: =调味糖!M33*1.13 -> 9.0731555 | N33: =调味糖!N33 -> 26 | O33: =调味糖!O33*1.13 -> 7020.0007
A34: 单晶体冰糖_99% | C34: =调味糖!C34*1.13 -> 0 | D34: =调味糖!D34 -> 0 | E34: =调味糖!E34*1.13 -> 0 | F34: =调味糖!F34 -> 0 | G34: =调味糖!G34*1.13 -> 0 | I34: 单晶体冰糖_99% | K34: =分配表!O939 -> 7364.1676 | L34: =调味糖!L34 -> 0.13225351 | M34: =调味糖!M34*1.13 -> 973.93698 | N34: =调味糖!N34 -> 102.326 | O34: =调味糖!O34*1.13 -> 753545.81
A35: 金砂糖_通用_通用_通用 | B35: 公斤 | C35: =调味糖!C35*1.13 -> 0 | D35: =调味糖!D35 -> 0 | E35: =调味糖!E35*1.13 -> 0 | F35: =调味糖!F35 -> 0 | G35: =调味糖!G35*1.13 -> 0 | I35: 金砂糖_通用_通用_通用 | J35: 公斤 | K35: =分配表!O940 -> 8.4454658 | L35: =调味糖!L35 -> 6.8177906 | M35: =调味糖!M35*1.13 -> 57.579418 | N35: =调味糖!N35 -> 5275 | O35: =调味糖!O35*1.13 -> 44549.832
A36: 无水柠檬酸_细目_含量≥99.5% | B36: 公斤 | C36: =调味糖!C36*1.13 -> 0 | D36: =调味糖!D36 -> 0 | E36: =调味糖!E36*1.13 -> 0 | F36: =调味糖!F36 -> 0 | G36: =调味糖!G36*1.13 -> 0 | I36: 无水柠檬酸_细目_含量≥99.5% | J36: 公斤 | K36: =分配表!O941 -> 0 | L36: =调味糖!L36 -> 0 | M36: =调味糖!M36*1.13 -> 0 | N36: =调味糖!N36 -> 0 | O36: =调味糖!O36*1.13 -> 0
A37: L-阿拉伯糖_通用_通用_通用 | B37: 公斤 | C37: =调味糖!C37*1.13 -> 0 | D37: =调味糖!D37 -> 0 | E37: =调味糖!E37*1.13 -> 0 | F37: =调味糖!F37 -> 0 | G37: =调味糖!G37*1.13 -> 0 | I37: L-阿拉伯糖_通用_通用_通用 | J37: 公斤 | K37: =分配表!O942 -> 50.682879 | L37: =调味糖!L37 -> 0.073670913 | M37: =调味糖!M37*1.13 -> 3.733854 | N37: =调味糖!N37 -> 57 | O37: =调味糖!O37*1.13 -> 2888.9241
A38: 安赛蜜_通用_食品级_通用 | B38: 公斤 | C38: =调味糖!C38*1.13 -> 0 | D38: =调味糖!D38 -> 0 | E38: =调味糖!E38*1.13 -> 0 | F38: =调味糖!F38 -> 0 | G38: =调味糖!G38*1.13 -> 0 | I38: 安赛蜜_通用_食品级_通用 | J38: 公斤 | K38: =分配表!O943 -> 43.999846 | L38: =调味糖!L38 -> 0.062038664 | M38: =调味糖!M38*1.13 -> 2.7296916 | N38: =调味糖!N38 -> 48 | O38: =调味糖!O38*1.13 -> 2111.9926
A39: 天然玫瑰味香精_通用_通用_食品级 | B39: 公斤 | C39: =调味糖!C39*1.13 -> 0 | D39: =调味糖!D39 -> 0 | E39: =调味糖!E39*1.13 -> 0 | F39: =调味糖!F39 -> 0 | G39: =调味糖!G39*1.13 -> 0 | I39: 天然玫瑰味香精_通用_通用_食品级 | J39: 公斤 | K39: =分配表!O944 -> 0 | L39: =调味糖!L39 -> 0 | M39: =调味糖!M39*1.13 -> 0 | N39: =调味糖!N39 -> 0 | O39: =调味糖!O39*1.13 -> 0
A40: 薄荷香精_通用_通用 | B40: 公斤 | C40: =调味糖!C40*1.13 -> 0 | D40: =调味糖!D40 -> 0 | E40: =调味糖!E40*1.13 -> 0 | F40: =调味糖!F40 -> 0 | G40: =调味糖!G40*1.13 -> 0 | I40: 薄荷香精_通用_通用 | J40: 公斤 | K40: =分配表!O945 -> 0 | L40: =调味糖!L40 -> 0 | M40: =调味糖!M40*1.13 -> 0 | N40: =调味糖!N40 -> 0 | O40: =调味糖!O40*1.13 -> 0
A41: 柠檬浓缩汁_通用 | B41: 公斤 | C41: =调味糖!C41*1.13 -> 0 | D41: =调味糖!D41 -> 0 | E41: =调味糖!E41*1.13 -> 0 | F41: =调味糖!F41 -> 0 | G41: =调味糖!G41*1.13 -> 0 | I41: 柠檬浓缩汁_通用 | J41: 公斤 | K41: =分配表!O946 -> 25.59887 | L41: =调味糖!L41 -> 1.6616113 | M41: =调味糖!M41*1.13 -> 42.53537 | N41: =调味糖!N41 -> 1285.607 | O41: =调味糖!O41*1.13 -> 32910.086
A42: 甘草酸铵_通用 | B42: 公斤 | C42: =调味糖!C42*1.13 -> 0 | D42: =调味糖!D42 -> 0 | E42: =调味糖!E42*1.13 -> 0 | F42: =调味糖!F42 -> 0 | G42: =调味糖!G42*1.13 -> 0 | I42: 甘草酸铵_通用 | J42: 公斤 | K42: =分配表!O947 -> 0 | L42: =调味糖!L42 -> 0 | M42: =调味糖!M42*1.13 -> 0 | N42: =调味糖!N42 -> 0 | O42: =调味糖!O42*1.13 -> 0
A43: 藏青盐 | B43: 公斤 | C43: =调味糖!C43*1.13 -> 0 | D43: =调味糖!D43 -> 0 | E43: =调味糖!E43*1.13 -> 0 | F43: =调味糖!F43 -> 0 | G43: =调味糖!G43*1.13 -> 0 | I43: 藏青盐 | J43: 公斤 | K43: =分配表!O948 -> 0 | L43: =调味糖!L43 -> 0 | M43: =调味糖!M43*1.13 -> 0 | N43: =调味糖!N43 -> 0 | O43: =调味糖!O43*1.13 -> 0
A44: 焦糖色_通用_GB1886.64-2015_通用 | C44: =调味糖!C44*1.13 -> 0 | D44: =调味糖!D44 -> 0 | E44: =调味糖!E44*1.13 -> 0 | F44: =调味糖!F44 -> 0 | G44: =调味糖!G44*1.13 -> 0 | I44: 焦糖色_通用_GB1886.64-2015_通用 | K44: =分配表!O949 -> 0 | L44: =调味糖!L44 -> 0 | M44: =调味糖!M44*1.13 -> 0 | N44: =调味糖!N44 -> 0 | O44: =调味糖!O44*1.13 -> 0
A45: 苯甲酸钠_通用_通用_通用 | C45: =调味糖!C45*1.13 -> 0 | D45: =调味糖!D45 -> 0 | E45: =调味糖!E45*1.13 -> 0 | F45: =调味糖!F45 -> 0 | G45: =调味糖!G45*1.13 -> 0 | I45: 苯甲酸钠_通用_通用_通用 | K45: =分配表!O950 -> #DIV/0! | L45: =调味糖!L45 -> 0 | M45: =调味糖!M45*1.13 -> 0 | N45: =调味糖!N45 -> 0 | O45: =调味糖!O45*1.13 -> 0
A46: 甘蔗多酚_通用 | C46: =调味糖!C46*1.13 -> 0 | D46: =调味糖!D46 -> 0 | E46: =调味糖!E46*1.13 -> 0 | F46: =调味糖!F46 -> 0 | G46: =调味糖!G46*1.13 -> 0 | I46: 甘蔗多酚_通用 | K46: =分配表!O951 -> 557.93541 | L46: =调味糖!L46 -> 0.34896748 | M46: =调味糖!M46*1.13 -> 194.70132 | N46: =调味糖!N46 -> 270 | O46: =调味糖!O46*1.13 -> 150642.56
A47: =调味糖!A47 -> 食品级六偏磷酸钠_通用_含量≥67%_通用 | C47: =调味糖!C47*1.13 -> 0 | D47: =调味糖!D47 -> 0 | E47: =调味糖!E47*1.13 -> 0 | F47: =调味糖!F47 -> 0 | G47: =调味糖!G47*1.13 -> 0 | I47: =A47 -> 食品级六偏磷酸钠_通用_含量≥67%_通用 | K47: =分配表!O952 -> 12.170665 | L47: =调味糖!L47 -> 0.025849443 | M47: =调味糖!M47*1.13 -> 0.31460491 | N47: =调味糖!N47 -> 20 | O47: =调味糖!O47*1.13 -> 243.4133
A48: =调味糖!A48 -> 无水柠檬酸_细目 | C48: =调味糖!C48*1.13 -> 0 | D48: =调味糖!D48 -> 0 | E48: =调味糖!E48*1.13 -> 0 | F48: =调味糖!F48 -> 0 | G48: =调味糖!G48*1.13 -> 0 | I48: =A48 -> 无水柠檬酸_细目 | K48: =分配表!O953 -> 6150.0016 | L48: =调味糖!L48 -> 0.004524945 | M48: =调味糖!M48*1.13 -> 27.828419 | N48: =调味糖!N48 -> 3.501 | O48: =调味糖!O48*1.13 -> 21531.156
A49: (三)包装物 | I49: (三)包装物
A50: (四)动力能源 | E50: =SUM(E51:E54) -> 0 | G50: =SUM(G51:G54) -> 0 | I50: (四)动力能源 | M50: =SUM(M51:M54) -> #DIV/0! | O50: =SUM(O51:O54) -> #DIV/0!
A51: 1、蒸汽 | B51: 吨 | C51: =OFFSET(分配表!C306,0,mth-1,1,1) -> 0 | D51: =调味糖!D52 -> 0 | E51: =C51*D51 -> 0 | F51: =调味糖!F52 -> #DIV/0! | G51: =E51*F$3 -> 0 | I51: 1、蒸汽 | J51: 吨 | K51: =分配表!O306 -> 408.53094 | L51: =调味糖!L52 -> #DIV/0! | M51: =K51*L51 -> #DIV/0! | N51: =调味糖!N52 -> #DIV/0! | O51: =M51*N$3 -> #DIV/0!
A52: 2、电 | B52: 度 | C52: =调味糖!C53*1.13 -> 0 | D52: =调味糖!D53 -> 0 | E52: =调味糖!E53*1.13 -> 0 | F52: =调味糖!F53 -> #DIV/0! | G52: =调味糖!G53*1.13 -> 0 | I52: 2、电 | J52: 度 | K52: =调味糖!K53*1.13 -> 0.76911958 | L52: =调味糖!L53 -> #DIV/0! | M52: =调味糖!M53*1.13 -> #DIV/0! | N52: =调味糖!N53 -> #DIV/0! | O52: =调味糖!O53*1.13 -> #DIV/0!
A53: 3、水 | B53: 吨 | C53: =3.32+0.9*2.97 -> 5.993 | D53: =调味糖!D54 -> 0 | E53: =D53*C53 -> 0 | F53: =调味糖!F54 -> #DIV/0! | G53: =E53*F3 -> 0 | I53: 3、水 | J53: 吨 | K53: 5.993 | L53: =调味糖!L54 -> #DIV/0! | M53: =L53*K53 -> #DIV/0! | N53: =调味糖!N54 -> #DIV/0! | O53: =M53*N3 -> #DIV/0!
A54: 4、其他 | B54: M3 | I54: 4、其他 | J54: M3
A55: (五)排污费 | E55: =调味糖!E56*1.13 -> 0 | G55: =调味糖!G56*1.13 -> #DIV/0! | I55: (五)排污费 | M55: =调味糖!M56*1.13 -> #DIV/0! | O55: =调味糖!O56*1.13 -> #DIV/0!
A56: 1.污水处理 | E56: =E55 -> 0 | G56: =G55 -> #DIV/0! | I56: 1.污水处理 | M56: =M55 -> #DIV/0! | O56: =O55 -> #DIV/0!
A57: 2.污水固定成本 | I57: 2.污水固定成本
A58: (五)增值税 | E58: =IF(VALUE(F$3)=0,0,G58/F$3) -> 0 | G58: =SUM(G5,-G11,-G20,-G50,-G55,-G49)-SUM(调味糖!G5,-调味糖!G11,-调味糖!G20,-调味糖!G51,-调味糖!G56,-调味糖!G50) -> #DIV/0! | I58: (五)增值税 | M58: =IF(N$3=0,0,O58/N$3) -> #DIV/0! | O58: =SUM(O5,-O11,-O20,-O50,-O55,-O49)-SUM(调味糖!O5,-调味糖!O11,-调味糖!O20,-调味糖!O51,-调味糖!O56,-调味糖!O50) -> #DIV/0!
A59: 三、边际贡献 | E59: =E5-E10 -> #DIV/0! | G59: =G5-G10 -> #DIV/0! | I59: 三、边际贡献 | M59: =M5-M10 -> #DIV/0! | O59: =O5-O10 -> #DIV/0!
A60: 四、固定成本 | E60: =SUM(E61:E67) -> 0 | G60: =SUM(G61:G67) -> #DIV/0! | I60: 四、固定成本 | M60: =IF(N$3=0,0,O60/N$3) -> #DIV/0! | O60: =SUM(O61:O67) -> #DIV/0!
A61: （一）折旧与摊销 | E61: =调味糖!E62 -> 0 | G61: =调味糖!G62 -> #DIV/0! | I61: （一）折旧与摊销 | M61: =调味糖!M62 -> #DIV/0! | O61: =调味糖!O62 -> #DIV/0!
A62: （二）工资 | E62: =调味糖!E63 -> 0 | G62: =调味糖!G63 -> #DIV/0! | I62: （二）工资 | M62: =调味糖!M63 -> #DIV/0! | O62: =调味糖!O63 -> #DIV/0!
A63: （三）制造费用 | E63: =调味糖!E64 -> 0 | G63: =调味糖!G64 -> #DIV/0! | I63: （三）制造费用 | M63: =调味糖!M64 -> #DIV/0! | O63: =调味糖!O64 -> #DIV/0!
A64: （四）销售费用 | E64: =调味糖!E65 -> 0 | G64: =调味糖!G65 -> #DIV/0! | I64: （四）销售费用 | M64: =调味糖!M65 -> #DIV/0! | O64: =调味糖!O65 -> #DIV/0!
A65: （五）管理费用 | E65: =调味糖!E66 -> 0 | G65: =调味糖!G66 -> #DIV/0! | I65: （五）管理费用 | M65: =调味糖!M66 -> #DIV/0! | O65: =调味糖!O66 -> #DIV/0!
A66: （六）财务费用 | E66: =调味糖!E67 -> 0 | G66: =调味糖!G67 -> #DIV/0! | I66: （六）财务费用 | M66: =调味糖!M67 -> #DIV/0! | O66: =调味糖!O67 -> #DIV/0!
A67: （七）其他 | E67: =调味糖!E68 -> 0 | G67: =调味糖!G68 -> #DIV/0! | I67: （七） 其他 | M67: =调味糖!M68 -> #DIV/0! | O67: =调味糖!O68 -> #DIV/0!
A68: 其中：税金及附加 | E68: =调味糖!E69 -> 0 | G68: =调味糖!G69 -> #DIV/0! | I68: 其中：税金及附加 | M68: =调味糖!M69 -> #DIV/0! | O68: =调味糖!O69 -> #DIV/0!
A69: 其他业务收支 | E69: =调味糖!E70 -> 0 | G69: =调味糖!G70 -> #DIV/0! | I69: 其他业务收支 | M69: =调味糖!M70 -> #DIV/0! | O69: =调味糖!O70 -> #DIV/0!
A70: 营业外收支 | E70: =调味糖!E71 -> 0 | G70: =调味糖!G71 -> #DIV/0! | I70: 营业外收支 | M70: =调味糖!M71 -> #DIV/0! | O70: =调味糖!O71 -> #DIV/0!
A71: 投资收益+公允价值变动损益 | E71: =调味糖!E72 -> 0 | G71: =调味糖!G72 -> #DIV/0! | I71: 投资收益+公允价值变动损益 | M71: =调味糖!M72 -> #DIV/0! | O71: =调味糖!O72 -> #DIV/0!
A72: 其他收益 | E72: =调味糖!E73 -> 0 | G72: =调味糖!G73 -> #DIV/0! | I72: 其他收益 | M72: =调味糖!M73 -> #DIV/0! | O72: =调味糖!O73 -> #DIV/0!
... A74: 其他 | E74: =调味糖!E75 -> 0 | G74: =调味糖!G75 -> #DIV/0! | I74: 其他 | M74: =调味糖!M75 -> #DIV/0! | O74: =调味糖!O75 -> #DIV/0!
A75: 五、完全成本 | B75: 元 | E75: =E60+E10 -> #DIV/0! | G75: =G60+G10 -> #DIV/0! | I75: 五、完全成本 | J75: 元 | M75: =M60+M10 -> #DIV/0! | O75: =O60+O10 -> #DIV/0!
A76: 六、利润总额 | B76: 元 | E76: =E59-E60 -> #DIV/0! | G76: =G59-G60 -> #DIV/0! | I76: 六、利润总额 | J76: 元 | M76: =M59-M60 -> #DIV/0! | O76: =O59-O60 -> #DIV/0!
A77: 七、现金流 | B77: 元 | E77: =E76+E61 -> #DIV/0! | G77: =G76+G61 -> #DIV/0! | I77: 七、现金流 | J77: 元 | M77: =M76+M61 -> #DIV/0! | O77: =O76+O61 -> #DIV/0!
A78: 加工费 | B78: 元 | E78: =E10-E11+E60-E49 -> #DIV/0! | G78: =G10-G11+G60-G49 -> #DIV/0! | I78: 加工费 | J78: 元 | M78: =M10-M11+M60-M49 -> #DIV/0! | O78: =O10-O11+O60-O49 -> #DIV/0!
A79: 其他业务收支-糖渣 | E79: =调味糖!E80 -> 0 | G79: =调味糖!G80 -> #DIV/0! | I79: 其他业务收支-糖渣 | M79: =调味糖!M80 -> #DIV/0! | O79: =调味糖!O80 -> #DIV/0!
A84: 含税与不含税校验 | E84: =E59-调味糖!E60 -> #DIV/0! | G84: =G59-调味糖!G60 -> #DIV/0! | L84: check | M84: =M59-调味糖!M60 -> #DIV/0! | O84: =O59-调味糖!O60 -> #DIV/0!

Sheet F42-含税
A1: =CONCATENATE("果葡糖浆F42综合成本利润表_含税(2025年"&mth&"月)") -> 果葡糖浆F42综合成本利润表_含税(2025年8月) | I1: =CONCATENATE("果葡糖浆F42综合成本利润表_含税(2025年1-"&mth&"月)") -> 果葡糖浆F42综合成本利润表_含税(2025年1-8月)
A3: 产量 | E3: 本月产量 | F3: ='F42'!F3 -> 0 | G3: 吨 | M3: 本年产量 | N3: ='F42'!N3 -> 1923.675 | O3: 吨
B4: 单位 | C4: 单价 | D4: 单耗 | E4: 单位成本 | F4: 总耗量 | G4: 总成本 | J4: 单位 | K4: 单价 | L4: 单耗 | M4: 单位成本 | N4: 总耗量 | O4: 总成本
A5: 一、收入 | E5: =E6-E7 -> 0 | G5: =G6-G7 -> 0 | I5: 一、收入 | M5: =M6-M7 -> 3103.3811 | O5: =O6-O7 -> 5969896.7
A6: （一）销售价格 | E6: =OFFSET(销售收入及运费!C93,0,mth-1,1,1) -> 0 | G6: =F3*E6 -> 0 | I6: （一）销售价格 | M6: =销售收入及运费!O93 -> 3171.8809 | O6: =M6*$N$3 -> 6101668
A7: （二）物流费 | E7: =OFFSET(销售收入及运费!C191,0,mth-1,1,1) -> 0 | G7: =E7*F3 -> 0 | I7: （二）物流费 | M7: =销售收入及运费!O191 -> 68.499817 | O7: =M7*$N$3 -> 131771.39
A8: 1、运费 | E8: ='F42'!E8*1.09 -> #DIV/0! | G8: ='F42'!G8*1.09 -> #DIV/0! | I8: 1、运费 | M8: ='F42'!M8*1.09 -> 42.300163 | O8: ='F42'!O8*1.09 -> 81371.765
A9: 2、包装费、租赁费等 | E9: ='F42'!E9*1.13 -> #DIV/0! | G9: ='F42'!G9*1.13 -> #DIV/0! | I9: 2、包装费、租赁费等 | M9: ='F42'!M9*1.13 -> 26.199654 | O9: ='F42'!O9*1.13 -> 50399.62
A10: 二、变动成本 | E10: =E11+E13+E26+E31+E34+E25 -> 0 | G10: =G11+G13+G26+G31+G34+G25 -> #DIV/0! | I10: 二、变动成本 | M10: =M11+M13+M26+M31+M34+M25 -> #DIV/0! | O10: =O11+O13+O26+O31+O34+O25 -> #DIV/0!
A11: (一)淀粉 | B11: 吨 | C11: =C12 -> 0 | D11: =IF(C11=0,0,E11/C11) -> 0 | E11: =E12 -> 0 | F11: =F12 -> 0 | G11: =G12 -> 0 | I11: (一)淀粉 | J11: 吨 | K11: =IF(N11=0,0,O11/N11) -> 2810.937 | L11: =IF(K11=0,0,M11/K11) -> 0.76798883 | M11: =M12 -> 2158.7682 | N11: =N12 -> 1477.3609 | O11: =O12 -> 4152768.5
A12: 1、淀粉(14%) | B12: 吨 | C12: ='F42'!C12*1.13 -> 0 | D12: ='F42'!D12 -> 0 | E12: ='F42'!E12*1.13 -> 0 | F12: ='F42'!F12 -> 0 | G12: ='F42'!G12*1.13 -> 0 | I12: 1、淀粉(14%) | J12: 吨 | K12: ='F42'!K12*1.13 -> 2810.937 | L12: ='F42'!L12 -> 0.76798883 | M12: ='F42'!M12*1.13 -> 2158.7682 | N12: =L12*N3 -> 1477.3609 | O12: ='F42'!O12*1.13 -> 4152768.5
A13: (二)辅助材料 | E13: =SUM(E14:E24) -> 0 | G13: =SUM(G14:G24) -> #DIV/0! | I13: (二)辅助材料 | M13: =SUM(M14:M24) -> #DIV/0! | O13: =SUM(O14:O24) -> #DIV/0!
A14: 盐酸(折百) | B14: 公斤 | C14: ='F42'!C14*1.13 -> 0 | D14: ='F42'!D14 -> 0 | E14: ='F42'!E14*1.13 -> 0 | F14: ='F42'!F14 -> 0 | G14: ='F42'!G14*1.13 -> 0 | I14: 盐酸(折百) | J14: 公斤 | K14: =分配表!O191 -> 1.1680073 | L14: ='F42'!L14 -> 4.0391283 | M14: ='F42'!M14*1.13 -> 4.7177312 | N14: ='F42'!N14 -> 7769.9701 | O14: ='F42'!O14*1.13 -> 9075.3816
A15: 氢氧化钠(折百) | B15: 公斤 | C15: ='F42'!C15*1.13 -> 0 | D15: ='F42'!D15 -> 0 | E15: ='F42'!E15*1.13 -> 0 | F15: ='F42'!F15 -> 0 | G15: ='F42'!G15*1.13 -> 0 | I15: 氢氧化钠(折百) | J15: 公斤 | K15: =分配表!O192 -> 3.5767931 | L15: ='F42'!L15 -> 4.4995275 | M15: ='F42'!M15*1.13 -> 16.093879 | N15: ='F42'!N15 -> 8655.6285 | O15: ='F42'!O15*1.13 -> 30959.392
A16: 硅藻土 | B16: 公斤 | C16: ='F42'!C16*1.13 -> 0 | D16: ='F42'!D16 -> 0 | E16: ='F42'!E16*1.13 -> 0 | F16: ='F42'!F16 -> 0 | G16: ='F42'!G16*1.13 -> 0 | I16: 硅藻土 | J16: 公斤 | K16: =分配表!O193 -> 2.9435031 | L16: ='F42'!L16 -> 0.72586553 | M16: ='F42'!M16*1.13 -> 2.1365875 | N16: ='F42'!N16 -> 1396.3294 | O16: ='F42'!O16*1.13 -> 4110.0999
A17: 活性炭 | B17: 公斤 | C17: ='F42'!C17*1.13 -> 0 | D17: ='F42'!D17 -> 0 | E17: ='F42'!E17*1.13 -> 0 | F17: ='F42'!F17 -> 0 | G17: ='F42'!G17*1.13 -> 0 | I17: 活性炭 | J17: 公斤 | K17: =分配表!O195 -> 8.0000627 | L17: ='F42'!L17 -> 1.4472479 | M17: ='F42'!M17*1.13 -> 11.578074 | N17: ='F42'!N17 -> 2784.0346 | O17: ='F42'!O17*1.13 -> 22272.452
A18: 淀粉酶 | B18: 公斤 | C18: ='F42'!C18*1.13 -> 0 | D18: ='F42'!D18 -> 0 | E18: ='F42'!E18*1.13 -> 0 | F18: ='F42'!F18 -> 0 | G18: ='F42'!G18*1.13 -> 0 | I18: 淀粉酶 | J18: 公斤 | K18: =分配表!O196 -> 54.015593 | L18: ='F42'!L18 -> 0.07966358 | M18: ='F42'!M18*1.13 -> 4.3030755 | N18: ='F42'!N18 -> 153.24684 | O18: ='F42'!O18*1.13 -> 8277.7187
A19: 复合糖化酶 | B19: 公斤 | C19: ='F42'!C19*1.13 -> 0 | D19: ='F42'!D19 -> 0 | E19: ='F42'!E19*1.13 -> 0 | F19: ='F42'!F19 -> 0 | G19: ='F42'!G19*1.13 -> 0 | I19: 复合糖化酶 | J19: 公斤 | K19: =分配表!O197 -> 36.383097 | L19: ='F42'!L19 -> 0.14667412 | M19: ='F42'!M19*1.13 -> 5.3364588 | N19: ='F42'!N19 -> 282.15334 | O19: ='F42'!O19*1.13 -> 10265.612
A20: 异构酶 | B20: 公斤 | C20: ='F42'!C20*1.13 -> 0 | D20: ='F42'!D20 -> 0 | E20: ='F42'!E20*1.13 -> 0 | F20: ='F42'!F20 -> 0 | G20: ='F42'!G20*1.13 -> 0 | I20: 异构酶 | J20: 公斤 | K20: =分配表!O198 -> 246.99203 | L20: ='F42'!L20 -> 0.088021744 | M20: ='F42'!M20*1.13 -> 21.740669 | N20: ='F42'!N20 -> 169.32523 | O20: ='F42'!O20*1.13 -> 41821.982
A21: 硫酸镁(食品级) | B21: 公斤 | C21: ='F42'!C21*1.13 -> 0 | D21: ='F42'!D21 -> 0 | E21: ='F42'!E21*1.13 -> 0 | F21: ='F42'!F21 -> 0 | G21: ='F42'!G21*1.13 -> 0 | I21: 硫酸镁(食品级) | J21: 公斤 | K21: =分配表!O199 -> 1.106806 | L21: ='F42'!L21 -> 0.45647545 | M21: ='F42'!M21*1.13 -> 0.50522977 | N21: ='F42'!N21 -> 878.11041 | O21: ='F42'!O21*1.13 -> 971.89788
A22: 焦亚硫酸钠(食品级) | B22: 公斤 | C22: ='F42'!C22*1.13 -> 0 | D22: ='F42'!D22 -> 0 | E22: ='F42'!E22*1.13 -> 0 | F22: ='F42'!F22 -> 0 | G22: ='F42'!G22*1.13 -> 0 | I22: 焦亚硫酸钠(食品级) | J22: 公斤 | K22: =分配表!O200 -> 2.0973705 | L22: ='F42'!L22 -> 0.26629431 | M22: ='F42'!M22*1.13 -> 0.55851785 | N22: ='F42'!N22 -> 512.26372 | O22: ='F42'!O22*1.13 -> 1074.4068
A23: 树脂 | B23: 公斤 | C23: ='F42'!C23*1.13 -> 0 | D23: ='F42'!D23 -> 0 | E23: ='F42'!E23*1.13 -> 0 | F23: ='F42'!F23 -> 0 | G23: ='F42'!G23*1.13 -> #DIV/0! | I23: 树脂 | J23: 公斤 | K23: =分配表!O201 -> 0 | L23: ='F42'!L23 -> 0 | M23: ='F42'!M23*1.13 -> #DIV/0! | N23: ='F42'!N23 -> 0 | O23: ='F42'!O23*1.13 -> #DIV/0!
A24: 其他 | E24: ='F42'!E24*1.13 -> 0 | G24: ='F42'!G24*1.13 -> #DIV/0! | I24: 其他 | M24: ='F42'!M24*1.13 -> #DIV/0! | O24: ='F42'!O24*1.13 -> #DIV/0!
A25: (三)包装物 | I25: (三)包装物
A26: (四)动力能源 | E26: =SUM(E27:E30) -> 0 | G26: =SUM(G27:G30) -> 0 | I26: (四)动力能源 | M26: =SUM(M27:M30) -> #DIV/0! | O26: =SUM(O27:O30) -> #DIV/0!
A27: 1、蒸汽 | B27: 吨 | C27: =OFFSET(分配表!C306,0,mth-1,1,1) -> 0 | D27: ='F42'!D27 -> 0 | E27: =C27*D27 -> 0 | F27: ='F42'!F27 -> 0 | G27: =E27*F$3 -> 0 | I27: 1、蒸汽 | J27: 吨 | K27: =分配表!O306 -> 408.53094 | L27: ='F42'!L27 -> 0.27794258 | M27: =K27*L27 -> 113.54814 | N27: ='F42'!N27 -> 534.67118 | O27: =M27*N$3 -> 218429.72
A28: 2、电 | B28: 度 | C28: ='F42'!C28*1.13 -> 0 | D28: ='F42'!D28 -> 0 | E28: ='F42'!E28*1.13 -> 0 | F28: ='F42'!F28 -> #DIV/0! | G28: ='F42'!G28*1.13 -> 0 | I28: 2、电 | J28: 度 | K28: ='F42'!K28*1.13 -> 0.76911958 | L28: ='F42'!L28 -> #DIV/0! | M28: ='F42'!M28*1.13 -> #DIV/0! | N28: ='F42'!N28 -> #DIV/0! | O28: ='F42'!O28*1.13 -> #DIV/0!
A29: 3、水 | B29: 吨 | C29: =3.32+0.9*2.97 -> 5.993 | D29: ='F42'!D29 -> 0 | E29: =D29*C29 -> 0 | F29: ='F42'!F29 -> #DIV/0! | G29: =E29*F3 -> 0 | I29: 3、水 | J29: 吨 | K29: =3.32+0.9*2.97 -> 5.993 | L29: ='F42'!L29 -> #DIV/0! | M29: =L29*K29 -> #DIV/0! | N29: ='F42'!N29 -> #DIV/0! | O29: =M29*N3 -> #DIV/0!
A30: 4、其他 | B30: 吨 | C30: ='F42'!C30*1.13 -> 0 | D30: ='F42'!D30 -> 0 | E30: ='F42'!E30*1.13 -> 0 | F30: ='F42'!F30 -> 0 | G30: ='F42'!G30*1.13 -> 0 | I30: 4、其他 | J30: 吨 | K30: ='F42'!K30*1.13 -> 0 | L30: ='F42'!L30 -> 0 | M30: ='F42'!M30*1.13 -> 0 | N30: ='F42'!N30 -> 0 | O30: ='F42'!O30*1.13 -> 0
A31: (五)排污费 | E31: =IF(F$3=0,0,G31/F$3) -> 0 | G31: ='F42'!G31*1.13 -> #DIV/0! | I31: (五)排污费 | M31: =IF(N$3=0,0,O31/N$3) -> #DIV/0! | O31: ='F42'!O31*1.13 -> #DIV/0!
A32: 1.污水处理 | E32: =E31 -> 0 | G32: =G31 -> #DIV/0! | I32: 1.污水处理 | M32: =M31 -> #DIV/0! | O32: =O31 -> #DIV/0!
A33: 2.污水固定成本 | I33: 2.污水固定成本
A34: (六)增值税 | E34: =IF(VALUE(F$3)=0,0,G34/F$3) -> 0 | G34: =SUM(G5,-G11,-G13,-G26,-G31,-G25)-SUM('F42'!G5,-'F42'!G11-'F42'!G13-'F42'!G26-'F42'!G31,-'F42'!G25) -> #DIV/0! | I34: (六)增值税 | M34: =IF(N$3=0,0,O34/N$3) -> #DIV/0! | O34: =SUM(O5,-O11,-O13,-O26,-O31,-O25)-SUM('F42'!O5,-'F42'!O11-'F42'!O13-'F42'!O26-'F42'!O31,-'F42'!O25) -> #DIV/0!
A35: 三、边际贡献 | E35: =E5-E10 -> 0 | G35: =G5-G10 -> #DIV/0! | I35: 三、边际贡献 | M35: =M5-M10 -> #DIV/0! | O35: =O5-O10 -> #DIV/0!
A36: 四、固定成本 | E36: =SUM(E37:E43) -> 0 | G36: =SUM(G37:G43) -> #DIV/0! | I36: 四、固定成本 | M36: =IF(N$3=0,0,O36/N$3) -> #DIV/0! | O36: =SUM(O37:O43) -> #DIV/0!
A37: （一）折旧与摊销 | E37: ='F42'!E37 -> 0 | G37: ='F42'!G37 -> #DIV/0! | I37: （一）折旧与摊销 | M37: ='F42'!M37 -> #DIV/0! | O37: ='F42'!O37 -> #DIV/0!
A38: （二）工资 | E38: ='F42'!E38 -> 0 | G38: ='F42'!G38 -> #DIV/0! | I38: （二）工资 | M38: ='F42'!M38 -> #DIV/0! | O38: ='F42'!O38 -> #DIV/0!
A39: （三）制造费用 | E39: ='F42'!E39 -> 0 | G39: ='F42'!G39 -> #DIV/0! | I39: （三）制造费用 | M39: ='F42'!M39 -> #DIV/0! | O39: ='F42'!O39 -> #DIV/0!
A40: （四）销售费用 | E40: ='F42'!E40 -> 0 | G40: ='F42'!G40 -> #DIV/0! | I40: （四）销售费用 | M40: ='F42'!M40 -> #DIV/0! | O40: ='F42'!O40 -> #DIV/0!
A41: （五）管理费用 | E41: ='F42'!E41 -> 0 | G41: ='F42'!G41 -> #DIV/0! | I41: （五）管理费用 | M41: ='F42'!M41 -> #DIV/0! | O41: ='F42'!O41 -> #DIV/0!
A42: （六）财务费用 | E42: ='F42'!E42 -> 0 | G42: ='F42'!G42 -> #DIV/0! | I42: （六）财务费用 | M42: ='F42'!M42 -> #DIV/0! | O42: ='F42'!O42 -> #DIV/0!
A43: （七）其他 | E43: ='F42'!E43 -> 0 | G43: ='F42'!G43 -> #DIV/0! | I43: （七） 其他 | M43: ='F42'!M43 -> #DIV/0! | O43: ='F42'!O43 -> #DIV/0!
A44: 其中：税金及附加 | E44: ='F42'!E44 -> 0 | G44: ='F42'!G44 -> #DIV/0! | I44: 其中：税金及附加 | M44: ='F42'!M44 -> #DIV/0! | O44: ='F42'!O44 -> #DIV/0!
A45: 其他业务收支 | E45: ='F42'!E45 -> 0 | G45: ='F42'!G45 -> #DIV/0! | I45: 其他业务收支 | M45: ='F42'!M45 -> #DIV/0! | O45: ='F42'!O45 -> #DIV/0!
A46: 营业外收支 | E46: ='F42'!E46 -> 0 | G46: ='F42'!G46 -> #DIV/0! | I46: 营业外收支 | M46: ='F42'!M46 -> #DIV/0! | O46: ='F42'!O46 -> #DIV/0!
A47: 投资收益+公允价值变动损益 | E47: ='F42'!E47 -> 0 | G47: ='F42'!G47 -> #DIV/0! | I47: 投资收益+公允价值变动损益 | M47: ='F42'!M47 -> #DIV/0! | O47: ='F42'!O47 -> #DIV/0!
A48: 其他收益 | E48: ='F42'!E48 -> 0 | G48: ='F42'!G48 -> #DIV/0! | I48: 其他收益 | M48: ='F42'!M48 -> #DIV/0! | O48: ='F42'!O48 -> #DIV/0!
... A50: 其他 | E50: ='F42'!E50 -> 0 | G50: ='F42'!G50 -> #DIV/0! | I50: 其他 | M50: ='F42'!M50 -> #DIV/0! | O50: ='F42'!O50 -> #DIV/0!
A51: 五、完全成本 | B51: 元 | E51: =E36+E10 -> 0 | G51: =G36+G10 -> #DIV/0! | I51: 五、完全成本 | J51: 元 | M51: =M36+M10 -> #DIV/0! | O51: =O36+O10 -> #DIV/0!
A52: 六、利润总额 | B52: 元 | E52: =E35-E36 -> 0 | G52: =G35-G36 -> #DIV/0! | I52: 六、利润总额 | J52: 元 | M52: =M35-M36 -> #DIV/0! | O52: =O35-O36 -> #DIV/0!
A53: 七、现金流 | B53: 元 | E53: =E52+E37 -> 0 | G53: =G52+G37 -> #DIV/0! | I53: 七、现金流 | J53: 元 | M53: =M52+M37 -> #DIV/0! | O53: =O52+O37 -> #DIV/0!
A54: 加工费 | B54: 元 | E54: =E10-E11+E36-E25 -> 0 | G54: =G10-G11+G36-G25 -> #DIV/0! | I54: 加工费 | J54: 元 | M54: =M10-M11+M36-M25 -> #DIV/0! | O54: =O10-O11+O36-O25 -> #DIV/0!
A55: 其他业务收支-糖渣 | E55: ='F42'!E55 -> 0 | G55: ='F42'!G55 -> #DIV/0! | I55: 其他业务收支-糖渣 | M55: ='F42'!M55 -> #DIV/0! | O55: ='F42'!O55 -> #DIV/0!
A60: 含税与不含税校验 | E60: =E35-'F42'!E35 -> #DIV/0! | G60: =G35-'F42'!G35 -> #DIV/0! | L60: check | M60: =M35-'F42'!M35 -> #DIV/0! | O60: =O35-'F42'!O35 -> #DIV/0!

Sheet F55-含税
A1: =CONCATENATE("果葡糖浆F55综合成本利润表_含税(2025年"&mth&"月)") -> 果葡糖浆F55综合成本利润表_含税(2025年8月) | I1: =CONCATENATE("果葡糖浆F55综合成本利润表_含税(2025年1-"&mth&"月)") -> 果葡糖浆F55综合成本利润表_含税(2025年1-8月)
E3: 本月产量 | F3: ='F55'!F3 -> 0 | G3: 吨 | M3: 本年产量： | N3: ='F55'!N3 -> 49280.176 | O3: 吨
B4: 单位 | C4: 单价 | D4: 单耗 | E4: 单位成本 | F4: 总耗量 | G4: 总成本 | J4: 单位 | K4: 单价 | L4: 单耗 | M4: 单位成本 | N4: 总耗量 | O4: 总成本
A5: 一、收入 | E5: =E6-E7 -> 0 | G5: =G6-G7 -> 0 | I5: 一、收入 | M5: =M6-M7 -> 3000.7471 | O5: =O6-O7 -> 1.4787735e+08
A6: （一）销售价格 | E6: =OFFSET(销售收入及运费!C85,0,mth-1,1,1) -> 0 | G6: =E6*$F$3 -> 0 | I6: （一）销售价格 | M6: =销售收入及运费!O85 -> 3063.9311 | O6: =M6*$N$3 -> 1.5099106e+08
A7: （二）物流费 | E7: =OFFSET(销售收入及运费!C183,0,mth-1,1,1) -> 0 | G7: =E7*$F$3 -> 0 | I7: （二）物流费 | M7: =销售收入及运费!O183 -> 63.183963 | O7: =M7*$N$3 -> 3113716.8
A8: 1、运费 | E8: ='F55'!E8*1.09 -> #DIV/0! | G8: ='F55'!G8*1.09 -> #DIV/0! | I8: 1、运费 | M8: ='F55'!M8*1.09 -> 48.883769 | O8: ='F55'!O8*1.09 -> 2409000.7
A9: 2、包装费、租赁费等 | E9: ='F55'!E9*1.13 -> #DIV/0! | G9: ='F55'!G9*1.13 -> #DIV/0! | I9: 2、包装费、租赁费等 | M9: ='F55'!M9*1.13 -> 14.300195 | O9: ='F55'!O9*1.13 -> 704716.11
A10: 二、变动成本 | E10: =E11+E13+E26+E31+E34+E25 -> 0 | G10: =G11+G13+G26+G31+G34+G25 -> #DIV/0! | I10: 二、变动成本 | M10: =M11+M13+M26+M31+M34+M25 -> #DIV/0! | O10: =O11+O13+O26+O31+O34+O25 -> #DIV/0!
A11: (一)淀粉 | B11: 吨 | C11: =C12 -> 0 | D11: =IF(C11=0,0,E11/C11) -> 0 | E11: =E12 -> 0 | F11: =F12 -> 0 | G11: =G12 -> 0 | I11: (一)淀粉 | J11: 吨 | K11: =IF(N11=0,0,O11/N11) -> 2824.3684 | L11: =IF(K11=0,0,M11/K11) -> 0.84877003 | M11: =M12 -> 2397.2392 | N11: =N12 -> 41827.536 | O11: =O12 -> 1.1813637e+08
A12: 1、淀粉(14%) | B12: 吨 | C12: ='F55'!C12*1.13 -> 0 | D12: ='F55'!D12 -> 0 | E12: ='F55'!E12*1.13 -> 0 | F12: ='F55'!F12 -> 0 | G12: ='F55'!G12*1.13 -> 0 | I12: 1、淀粉(14%) | J12: 吨 | K12: =分配表!O71 -> 2824.3684 | L12: ='F55'!L12 -> 0.84877003 | M12: =K12*L12 -> 2397.2392 | N12: =L12*N3 -> 41827.536 | O12: =K12*N12 -> 1.1813637e+08
A13: (二)辅助材料 | E13: =SUM(E14:E24) -> 0 | G13: =SUM(G14:G24) -> #DIV/0! | I13: (二)辅助材料 | M13: =SUM(M14:M24) -> #DIV/0! | O13: =SUM(O14:O24) -> #DIV/0!
A14: 盐酸(折百) | B14: 公斤 | C14: ='F55'!C14*1.13 -> 0 | D14: ='F55'!D14 -> 0 | E14: ='F55'!E14*1.13 -> 0 | F14: ='F55'!F14 -> 0 | G14: ='F55'!G14*1.13 -> 0 | I14: 盐酸(折百) | J14: 公斤 | K14: =分配表!O191 -> 1.1680073 | L14: ='F55'!L14 -> 4.5578743 | M14: =K14*L14 -> 5.3236304 | N14: ='F55'!N14 -> 224612.85 | O14: =M14*$N$3 -> 262349.44
A15: 氢氧化钠(折百) | B15: 公斤 | C15: ='F55'!C15*1.13 -> 0 | D15: ='F55'!D15 -> 0 | E15: ='F55'!E15*1.13 -> 0 | F15: ='F55'!F15 -> 0 | G15: ='F55'!G15*1.13 -> 0 | I15: 氢氧化钠(折百) | J15: 公斤 | K15: =分配表!O192 -> 3.5767931 | L15: ='F55'!L15 -> 5.0625869 | M15: =K15*L15 -> 18.107826 | N15: ='F55'!N15 -> 249485.17 | O15: =M15*$N$3 -> 892356.84
A16: 硅藻土 | B16: 公斤 | C16: ='F55'!C16*1.13 -> 0 | D16: ='F55'!D16 -> 0 | E16: ='F55'!E16*1.13 -> 0 | F16: ='F55'!F16 -> 0 | G16: ='F55'!G16*1.13 -> 0 | I16: 硅藻土 | J16: 公斤 | K16: =分配表!O193 -> 2.9435031 | L16: ='F55'!L16 -> 0.76650844 | M16: =K16*L16 -> 2.25622 | N16: ='F55'!N16 -> 37773.671 | O16: =M16*$N$3 -> 111186.92
A17: 活性炭 | B17: 公斤 | C17: ='F55'!C17*1.13 -> 0 | D17: ='F55'!D17 -> 0 | E17: ='F55'!E17*1.13 -> 0 | F17: ='F55'!F17 -> 0 | G17: ='F55'!G17*1.13 -> 0 | I17: 活性炭 | J17: 公斤 | K17: =分配表!O195 -> 8.0000627 | L17: ='F55'!L17 -> 1.5998718 | M17: =K17*L17 -> 12.799075 | N17: ='F55'!N17 -> 78841.965 | O17: =M17*$N$3 -> 630740.66
A18: 淀粉酶 | B18: 公斤 | C18: ='F55'!C18*1.13 -> 0 | D18: ='F55'!D18 -> 0 | E18: ='F55'!E18*1.13 -> 0 | F18: ='F55'!F18 -> 0 | G18: ='F55'!G18*1.13 -> 0 | I18: 淀粉酶 | J18: 公斤 | K18: =分配表!O196 -> 54.015593 | L18: ='F55'!L18 -> 0.082519047 | M18: =K18*L18 -> 4.4573152 | N18: ='F55'!N18 -> 4066.5532 | O18: =M18*$N$3 -> 219657.28
A19: 复合糖化酶 | B19: 公斤 | C19: ='F55'!C19*1.13 -> 0 | D19: ='F55'!D19 -> 0 | E19: ='F55'!E19*1.13 -> 0 | F19: ='F55'!F19 -> 0 | G19: ='F55'!G19*1.13 -> 0 | I19: 复合糖化酶 | J19: 公斤 | K19: =分配表!O197 -> 36.383097 | L19: ='F55'!L19 -> 0.16120776 | M19: =K19*L19 -> 5.8652375 | N19: ='F55'!N19 -> 7944.3467 | O19: =M19*$N$3 -> 289039.94
A20: 异构酶 | B20: 公斤 | C20: ='F55'!C20*1.13 -> 0 | D20: ='F55'!D20 -> 0 | E20: ='F55'!E20*1.13 -> 0 | F20: ='F55'!F20 -> 0 | G20: ='F55'!G20*1.13 -> 0 | I20: 异构酶 | J20: 公斤 | K20: =分配表!O198 -> 246.99203 | L20: ='F55'!L20 -> 0.097700032 | M20: =K20*L20 -> 24.131129 | N20: ='F55'!N20 -> 4814.6748 | O20: =M20*$N$3 -> 1189186.3
A21: 硫酸镁 | B21: 公斤 | C21: ='F55'!C21*1.13 -> 0 | D21: ='F55'!D21 -> 0 | E21: ='F55'!E21*1.13 -> 0 | F21: ='F55'!F21 -> 0 | G21: ='F55'!G21*1.13 -> 0 | I21: 硫酸镁 | J21: 公斤 | K21: =分配表!O199 -> 1.106806 | L21: ='F55'!L21 -> 0.49607959 | M21: =K21*L21 -> 0.54906387 | N21: ='F55'!N21 -> 24446.89 | O21: =M21*$N$3 -> 27057.964
A22: 焦亚硫酸钠 | B22: 公斤 | C22: ='F55'!C22*1.13 -> 0 | D22: ='F55'!D22 -> 0 | E22: ='F55'!E22*1.13 -> 0 | F22: ='F55'!F22 -> 0 | G22: ='F55'!G22*1.13 -> 0 | I22: 焦亚硫酸钠 | J22: 公斤 | K22: =分配表!O200 -> 2.0973705 | L22: ='F55'!L22 -> 0.29181585 | M22: =K22*L22 -> 0.61204596 | N22: ='F55'!N22 -> 14380.736 | O22: =M22*$N$3 -> 30161.733
A23: 树脂 | B23: 公斤 | C23: ='F55'!C23*1.13 -> 0 | D23: ='F55'!D23 -> 0 | E23: ='F55'!E23*1.13 -> 0 | F23: ='F55'!F23 -> 0 | G23: ='F55'!G23*1.13 -> #DIV/0! | I23: 树脂 | J23: 公斤 | K23: =分配表!O201 -> 0 | L23: ='F55'!L23 -> 0 | M23: =IF($N$3=0,0,O23/$N$3) -> 0 | N23: ='F55'!N23 -> 0 | O23: =基础表!O241 -> 0
A24: 其他 | E24: ='F55'!E24*1.13 -> 0 | G24: ='F55'!G24*1.13 -> #DIV/0! | I24: 其他 | M24: =IF($N$3=0,0,O24/$N$3) -> #DIV/0! | O24: ='F55'!O24*1.13 -> #DIV/0!
A25: (三)包装物 | I25: (三)包装物
A26: (四)动力能源 | E26: =SUM(E27:E30) -> 0 | G26: =SUM(G27:G30) -> 0 | I26: (四)动力能源 | M26: =SUM(M27:M30) -> #DIV/0! | O26: =SUM(O27:O30) -> #DIV/0!
A27: 1、蒸汽 | B27: 吨 | C27: =OFFSET(分配表!C306,0,mth-1,1,1) -> 0 | D27: ='F55'!D27 -> 0 | E27: =C27*D27 -> 0 | F27: ='F55'!F27 -> 0 | G27: =E27*F$3 -> 0 | I27: 1、蒸汽 | J27: 吨 | K27: =分配表!O306 -> 408.53094 | L27: =IF($N$3=0,0,N27/$N$3) -> 0.30859932 | M27: =K27*L27 -> 126.07237 | N27: ='F55'!N27 -> 15207.829 | O27: =M27*N$3 -> 6212868.6
A28: 2、电 | B28: 度 | C28: ='F55'!C28*1.13 -> 0 | D28: ='F55'!D28 -> 0 | E28: ='F55'!E28*1.13 -> 0 | F28: ='F55'!F28 -> #DIV/0! | G28: ='F55'!G28*1.13 -> 0 | I28: 2、电 | J28: 度 | K28: =分配表!O325 -> 0.76911958 | L28: =IF($N$3=0,0,N28/$N$3) -> #DIV/0! | M28: =K28*L28 -> #DIV/0! | N28: ='F55'!N28 -> #DIV/0! | O28: =M28*N$3 -> #DIV/0!
A29: 3、水 | B29: 吨 | C29: =3.32+0.9*2.97 -> 5.993 | D29: ='F55'!D29 -> 0 | E29: =D29*C29 -> 0 | F29: ='F55'!F29 -> #DIV/0! | G29: =E29*F3 -> 0 | I29: 3、水 | J29: 吨 | K29: =3.32+0.9*2.97 -> 5.993 | L29: =IF($N$3=0,0,N29/$N$3) -> #DIV/0! | M29: =L29*K29 -> #DIV/0! | N29: ='F55'!N29 -> #DIV/0! | O29: =M29*N3 -> #DIV/0!
A30: 4、其他 | B30: 吨 | C30: ='F55'!C30*1.13 -> 0 | D30: ='F55'!D30 -> 0 | E30: ='F55'!E30*1.13 -> 0 | F30: ='F55'!F30 -> 0 | G30: ='F55'!G30*1.13 -> 0 | I30: 4、其他 | J30: 吨 | K30: ='F55'!K30*1.13 -> 0 | L30: =IF($N$3=0,0,N30/$N$3) -> 0 | M30: ='F55'!M30*1.13 -> 0 | N30: ='F55'!N30 -> 0 | O30: ='F55'!O30*1.13 -> 0
A31: (五)排污费 | E31: =IF(VALUE(F$3)=0,0,G31/F$3) -> 0 | G31: ='F55'!G31*1.13 -> #DIV/0! | I31: (五)排污费 | K31: =IF(N31=0,0,O31/N31) -> 0 | L31: =IF(K31=0,0,M31/K31) -> 0 | M31: =IF($N$3=0,,O31/$N$3) -> #DIV/0! | O31: =分配表!O385 -> #DIV/0!
A32: 1.污水处理 | E32: =E31 -> 0 | G32: =G31 -> #DIV/0! | I32: 1.污水处理 | M32: =M31 -> #DIV/0! | O32: =O31 -> #DIV/0!
A33: 2.污水固定成本 | I33: 2.污水固定成本
A34: (六)增值税 | E34: =IF(VALUE(F$3)=0,0,G34/F$3) -> 0 | G34: =SUM(G5,-G11,-G13,-G26,-G31,-G25)-SUM('F55'!G5,-'F55'!G11-'F55'!G13-'F55'!G26-'F55'!G31,-'F55'!G25) -> #DIV/0! | I34: (六)增值税 | M34: =IF(N$3=0,0,O34/N$3) -> #DIV/0! | O34: =SUM(O5,-O11,-O13,-O26,-O31,-O25)-SUM('F55'!O5,-'F55'!O11-'F55'!O13-'F55'!O26-'F55'!O31,-'F55'!O25) -> #DIV/0!
A35: 三、边际贡献 | E35: =E5-E10 -> 0 | G35: =G5-G10 -> #DIV/0! | I35: 三、边际贡献 | M35: =M5-M10 -> #DIV/0! | O35: =O5-O10 -> #DIV/0!
A36: 四、固定成本 | E36: =SUM(E37:E43) -> 0 | G36: =SUM(G37:G43) -> #DIV/0! | I36: 四、固定成本 | M36: =IF(N$3=0,0,O36/N$3) -> #DIV/0! | O36: =SUM(O37:O43) -> #DIV/0!
A37: （一）折旧与摊销 | E37: ='F55'!E37 -> 0 | G37: ='F55'!G37 -> #DIV/0! | I37: （一）折旧与摊销 | M37: ='F55'!M37 -> #DIV/0! | O37: ='F55'!O37 -> #DIV/0!
A38: （二）工资 | E38: ='F55'!E38 -> 0 | G38: ='F55'!G38 -> #DIV/0! | I38: （二）工资 | M38: ='F55'!M38 -> #DIV/0! | O38: ='F55'!O38 -> #DIV/0!
A39: （三）制造费用 | E39: ='F55'!E39 -> 0 | G39: ='F55'!G39 -> #DIV/0! | I39: （三）制造费用 | M39: ='F55'!M39 -> #DIV/0! | O39: ='F55'!O39 -> #DIV/0!
A40: （四）销售费用 | E40: ='F55'!E40 -> 0 | G40: ='F55'!G40 -> #DIV/0! | I40: （四）销售费用 | M40: ='F55'!M40 -> #DIV/0! | O40: ='F55'!O40 -> #DIV/0!
A41: （五）管理费用 | E41: ='F55'!E41 -> 0 | G41: ='F55'!G41 -> #DIV/0! | I41: （五）管理费用 | M41: ='F55'!M41 -> #DIV/0! | O41: ='F55'!O41 -> #DIV/0!
A42: （六）财务费用 | E42: ='F55'!E42 -> 0 | G42: ='F55'!G42 -> #DIV/0! | I42: （六）财务费用 | M42: ='F55'!M42 -> #DIV/0! | O42: ='F55'!O42 -> #DIV/0!
A43: （七）其他 | E43: ='F55'!E43 -> 0 | G43: ='F55'!G43 -> #DIV/0! | I43: （七） 其他 | M43: ='F55'!M43 -> #DIV/0! | O43: ='F55'!O43 -> #DIV/0!
A44: 其中：税金及附加 | E44: ='F55'!E44 -> 0 | G44: ='F55'!G44 -> #DIV/0! | I44: 其中：税金及附加 | M44: ='F55'!M44 -> #DIV/0! | O44: ='F55'!O44 -> #DIV/0!
A45: 其他业务收支 | E45: ='F55'!E45 -> 0 | G45: ='F55'!G45 -> #DIV/0! | I45: 其他业务收支 | M45: ='F55'!M45 -> #DIV/0! | O45: ='F55'!O45 -> #DIV/0!
A46: 营业外收支 | E46: ='F55'!E46 -> 0 | G46: ='F55'!G46 -> #DIV/0! | I46: 营业外收支 | M46: ='F55'!M46 -> #DIV/0! | O46: ='F55'!O46 -> #DIV/0!
A47: 投资收益+公允价值变动损益 | E47: ='F55'!E47 -> 0 | G47: ='F55'!G47 -> #DIV/0! | I47: 投资收益+公允价值变动损益 | M47: ='F55'!M47 -> #DIV/0! | O47: ='F55'!O47 -> #DIV/0!
A48: 其他收益 | E48: ='F55'!E48 -> 0 | G48: ='F55'!G48 -> #DIV/0! | I48: 其他收益 | M48: ='F55'!M48 -> #DIV/0! | O48: ='F55'!O48 -> #DIV/0!
... A50: 其他 | E50: ='F55'!E50 -> 0 | G50: ='F55'!G50 -> #DIV/0! | I50: 其他 | M50: ='F55'!M50 -> #DIV/0! | O50: ='F55'!O50 -> #DIV/0!
A51: 五、完全成本 | B51: 元 | E51: =E36+E10 -> 0 | G51: =G36+G10 -> #DIV/0! | I51: 五、完全成本 | J51: 元 | M51: =M36+M10 -> #DIV/0! | O51: =O36+O10 -> #DIV/0!
A52: 六、利润总额 | B52: 元 | E52: =E35-E36 -> 0 | G52: =G35-G36 -> #DIV/0! | I52: 六、利润总额 | J52: 元 | M52: =M35-M36 -> #DIV/0! | O52: =O35-O36 -> #DIV/0!
A53: 七、现金流 | B53: 元 | E53: =E52+E37 -> 0 | G53: =G52+G37 -> #DIV/0! | I53: 七、现金流 | J53: 元 | M53: =M52+M37 -> #DIV/0! | O53: =O52+O37 -> #DIV/0!
A54: 加工费 | B54: 元 | E54: =E10-E11+E36-E25 -> 0 | G54: =G10-G11+G36-G25 -> #DIV/0! | I54: 加工费 | J54: 元 | M54: =M10-M11+M36-M25 -> #DIV/0! | O54: =O10-O11+O36-O25 -> #DIV/0!
A55: 其他业务收支-糖渣 | E55: ='F55'!E55 -> 0 | G55: ='F55'!G55 -> #DIV/0! | I55: 其他业务收支-糖渣 | M55: ='F55'!M55 -> #DIV/0! | O55: ='F55'!O55 -> #DIV/0!
A60: 含税与不含税校验 | E60: =E35-'F55'!E35 -> #DIV/0! | G60: =G35-'F55'!G35 -> #DIV/0! | L60: check | M60: =M35-'F55'!M35 -> #DIV/0! | O60: =O35-'F55'!O35 -> #DIV/0!

Sheet F60-含税
A1: =CONCATENATE("果葡糖浆F60综合成本利润表_含税(2025年"&mth&"月)") -> 果葡糖浆F60综合成本利润表_含税(2025年8月) | I1: =CONCATENATE("果葡糖浆F60综合成本利润表_含税(2025年1-"&mth&"月)") -> 果葡糖浆F60综合成本利润表_含税(2025年1-8月)
A3: 产量 | E3: 本月产量 | F3: ='F60'!F3 -> 0 | G3: 吨 | M3: 本年产量 | N3: ='F60'!N3 -> 6845.043 | O3: 吨
B4: 单位 | C4: 单价 | D4: 单耗 | E4: 单位成本 | F4: 总耗量 | G4: 总成本 | J4: 单位 | K4: 单价 | L4: 单耗 | M4: 单位成本 | N4: 总耗量 | O4: 总成本
A5: 一、收入 | E5: =E6-E7 -> 0 | G5: =G6-G7 -> 0 | I5: 一、收入 | M5: =M6-M7 -> 3547.5558 | O5: =O6-O7 -> 24283172
A6: （一）销售价格 | E6: =OFFSET(销售收入及运费!C90,0,mth-1,1,1) -> 0 | G6: =E6*F3 -> 0 | I6: （一）销售价格 | M6: =销售收入及运费!O90 -> 4353.556 | O6: =M6*$N$3 -> 29800278
A7: （二）物流费 | E7: =OFFSET(销售收入及运费!C188,0,mth-1,1,1) -> 0 | G7: =F3*E7 -> 0 | I7: （二）物流费 | M7: =销售收入及运费!O188 -> 806.00016 | O7: =M7*$N$3 -> 5517105.8
A8: 1、运费 | E8: ='F60'!E8*1.09 -> #DIV/0! | G8: ='F60'!G8*1.09 -> #DIV/0! | I8: 1、运费 | M8: ='F60'!M8*1.09 -> 230.25543 | O8: ='F60'!O8*1.09 -> 1576108.4
A9: 2、包装费、租赁费等 | E9: ='F60'!E9*1.13 -> #DIV/0! | G9: ='F60'!G9*1.13 -> #DIV/0! | I9: 2、包装费、租赁费等 | M9: ='F60'!M9*1.13 -> 575.74473 | O9: ='F60'!O9*1.13 -> 3940997.4
A10: 二、变动成本 | E10: =E11+E13+E26+E31+E34+E25 -> 0 | G10: =G11+G13+G26+G31+G34+G25 -> #DIV/0! | I10: 二、变动成本 | M10: =M11+M13+M26+M31+M34+M25 -> #DIV/0! | O10: =O11+O13+O26+O31+O34+O25 -> #DIV/0!
A11: (一)淀粉 | B11: 吨 | C11: =C12 -> 0 | D11: =IF(C11=0,0,E11/C11) -> 0 | E11: =E12 -> 0 | F11: =F12 -> 0 | G11: =G12 -> 0 | I11: (一)淀粉 | J11: 吨 | K11: =IF(N11=0,0,O11/N11) -> 2827.7557 | L11: =IF(K11=0,0,M11/K11) -> 0.82529689 | M11: =M12 -> 2333.738 | N11: =N12 -> 5649.1927 | O11: =O12 -> 15974537
A12: 1、淀粉(14%) | B12: 吨 | C12: ='F60'!C12*1.13 -> 0 | D12: ='F60'!D12 -> 0 | E12: ='F60'!E12*1.13 -> 0 | F12: ='F60'!F12 -> 0 | G12: ='F60'!G12*1.13 -> 0 | I12: 1、淀粉(14%) | J12: 吨 | K12: =分配表!O74 -> 2827.7557 | L12: ='F60'!L12 -> 0.82529689 | M12: =K12*L12 -> 2333.738 | N12: =L12*N3 -> 5649.1927 | O12: =K12*N12 -> 15974537
A13: (二)辅助材料 | E13: =SUM(E14:E24) -> 0 | G13: =SUM(G14:G24) -> #DIV/0! | I13: (二)辅助材料 | M13: =SUM(M14:M24) -> #DIV/0! | O13: =SUM(O14:O24) -> #DIV/0!
A14: 盐酸(折百) | B14: 公斤 | C14: ='F60'!C14*1.13 -> 0 | D14: ='F60'!D14 -> 0 | E14: ='F60'!E14*1.13 -> 0 | F14: ='F60'!F14 -> 0 | G14: ='F60'!G14*1.13 -> 0 | I14: 盐酸(折百) | J14: 公斤 | K14: =分配表!O191 -> 1.1680073 | L14: ='F60'!L14 -> 4.448574 | M14: ='F60'!M14*1.13 -> 5.1959668 | N14: ='F60'!N14 -> 30450.68 | O14: ='F60'!O14*1.13 -> 35566.616
A15: 氢氧化钠(折百) | B15: 公斤 | C15: ='F60'!C15*1.13 -> 0 | D15: ='F60'!D15 -> 0 | E15: ='F60'!E15*1.13 -> 0 | F15: ='F60'!F15 -> 0 | G15: ='F60'!G15*1.13 -> 0 | I15: 氢氧化钠(折百) | J15: 公斤 | K15: =分配表!O192 -> 3.5767931 | L15: ='F60'!L15 -> 4.9385811 | M15: ='F60'!M15*1.13 -> 17.664283 | N15: ='F60'!N15 -> 33804.8 | O15: ='F60'!O15*1.13 -> 120912.78
A16: 硅藻土 | B16: 公斤 | C16: ='F60'!C16*1.13 -> 0 | D16: ='F60'!D16 -> 0 | E16: ='F60'!E16*1.13 -> 0 | F16: ='F60'!F16 -> 0 | G16: ='F60'!G16*1.13 -> 0 | I16: 硅藻土 | J16: 公斤 | K16: =分配表!O193 -> 2.9435031 | L16: ='F60'!L16 -> 0.74784044 | M16: ='F60'!M16*1.13 -> 2.2012707 | N16: ='F60'!N16 -> 5119 | O16: ='F60'!O16*1.13 -> 15067.793
A17: 活性炭 | B17: 公斤 | C17: ='F60'!C17*1.13 -> 0 | D17: ='F60'!D17 -> 0 | E17: ='F60'!E17*1.13 -> 0 | F17: ='F60'!F17 -> 0 | G17: ='F60'!G17*1.13 -> 0 | I17: 活性炭 | J17: 公斤 | K17: =分配表!O195 -> 8.0000627 | L17: ='F60'!L17 -> 1.5528025 | M17: ='F60'!M17*1.13 -> 12.422517 | N17: ='F60'!N17 -> 10629 | O17: ='F60'!O17*1.13 -> 85032.666
A18: 淀粉酶 | B18: 公斤 | C18: ='F60'!C18*1.13 -> 0 | D18: ='F60'!D18 -> 0 | E18: ='F60'!E18*1.13 -> 0 | F18: ='F60'!F18 -> 0 | G18: ='F60'!G18*1.13 -> 0 | I18: 淀粉酶 | J18: 公斤 | K18: =分配表!O196 -> 54.015593 | L18: ='F60'!L18 -> 0.080642298 | M18: ='F60'!M18*1.13 -> 4.3559415 | N18: ='F60'!N18 -> 552 | O18: ='F60'!O18*1.13 -> 29816.607
A19: 复合糖化酶 | B19: 公斤 | C19: ='F60'!C19*1.13 -> 0 | D19: ='F60'!D19 -> 0 | E19: ='F60'!E19*1.13 -> 0 | F19: ='F60'!F19 -> 0 | G19: ='F60'!G19*1.13 -> 0 | I19: 复合糖化酶 | J19: 公斤 | K19: =分配表!O197 -> 36.383097 | L19: ='F60'!L19 -> 0.15660968 | M19: ='F60'!M19*1.13 -> 5.6979453 | N19: ='F60'!N19 -> 1072 | O19: ='F60'!O19*1.13 -> 39002.68
A20: 异构酶 | B20: 公斤 | C20: ='F60'!C20*1.13 -> 0 | D20: ='F60'!D20 -> 0 | E20: ='F60'!E20*1.13 -> 0 | F20: ='F60'!F20 -> 0 | G20: ='F60'!G20*1.13 -> 0 | I20: 异构酶 | J20: 公斤 | K20: =分配表!O198 -> 246.99203 | L20: ='F60'!L20 -> 0.095499765 | M20: ='F60'!M20*1.13 -> 23.587681 | N20: ='F60'!N20 -> 653.7 | O20: ='F60'!O20*1.13 -> 161458.69
A21: 硫酸镁(食品级) | B21: 公斤 | C21: ='F60'!C21*1.13 -> 0 | D21: ='F60'!D21 -> 0 | E21: ='F60'!E21*1.13 -> 0 | F21: ='F60'!F21 -> 0 | G21: ='F60'!G21*1.13 -> 0 | I21: 硫酸镁(食品级) | J21: 公斤 | K21: =分配表!O199 -> 1.106806 | L21: ='F60'!L21 -> 0.48341552 | M21: ='F60'!M21*1.13 -> 0.5350472 | N21: ='F60'!N21 -> 3309 | O21: ='F60'!O21*1.13 -> 3662.4211
A22: 焦亚硫酸钠(食品级) | B22: 公斤 | C22: ='F60'!C22*1.13 -> 0 | D22: ='F60'!D22 -> 0 | E22: ='F60'!E22*1.13 -> 0 | F22: ='F60'!F22 -> 0 | G22: ='F60'!G22*1.13 -> 0 | I22: 焦亚硫酸钠(食品级) | J22: 公斤 | K22: =分配表!O200 -> 2.0973705 | L22: ='F60'!L22 -> 0.28429332 | M22: ='F60'!M22*1.13 -> 0.59626843 | N22: ='F60'!N22 -> 1946 | O22: ='F60'!O22*1.13 -> 4081.4831
A23: 树脂 | B23: 公斤 | C23: ='F60'!C23*1.13 -> 0 | D23: ='F60'!D23 -> 0 | E23: ='F60'!E23*1.13 -> 0 | F23: ='F60'!F23 -> 0 | G23: ='F60'!G23*1.13 -> #DIV/0! | I23: 树脂 | J23: 公斤 | K23: =分配表!O201 -> 0 | L23: ='F60'!L23 -> 0 | M23: ='F60'!M23*1.13 -> #DIV/0! | N23: ='F60'!N23 -> 0 | O23: ='F60'!O23*1.13 -> #DIV/0!
A24: 其他 | E24: ='F60'!E24*1.13 -> 0 | G24: ='F60'!G24*1.13 -> #DIV/0! | I24: 其他 | M24: ='F60'!M24*1.13 -> #DIV/0! | O24: ='F60'!O24*1.13 -> #DIV/0!
A25: (三)包装物 | I25: (三)包装物
A26: (四)动力能源 | E26: =SUM(E27:E30) -> 0 | G26: =SUM(G27:G30) -> 0 | I26: (四)动力能源 | M26: =SUM(M27:M30) -> #DIV/0! | O26: =SUM(O27:O30) -> #DIV/0!
A27: 1、蒸汽 | B27: 吨 | C27: =OFFSET(分配表!C306,0,mth-1,1,1) -> 0 | D27: ='F60'!D27 -> 0 | E27: =C27*D27 -> 0 | F27: ='F60'!F27 -> 0 | G27: =E27*F$3 -> 0 | I27: 1、蒸汽 | J27: 吨 | K27: =分配表!O306 -> 408.53094 | L27: ='F60'!L27 -> 0.30291994 | M27: =K27*L27 -> 123.75217 | N27: ='F60'!N27 -> 2073.5 | O27: =M27*N$3 -> 847088.9
A28: 2、电 | B28: 度 | C28: ='F60'!C28*1.13 -> 0 | D28: ='F60'!D28 -> 0 | E28: ='F60'!E28*1.13 -> 0 | F28: ='F60'!F28 -> #DIV/0! | G28: ='F60'!G28*1.13 -> 0 | I28: 2、电 | J28: 度 | K28: ='F60'!K28*1.13 -> 0.76911958 | L28: ='F60'!L28 -> #DIV/0! | M28: ='F60'!M28*1.13 -> #DIV/0! | N28: ='F60'!N28 -> #DIV/0! | O28: ='F60'!O28*1.13 -> #DIV/0!
A29: 3、水 | B29: 吨 | C29: =3.32+0.9*2.97 -> 5.993 | D29: ='F60'!D29 -> 0 | E29: =D29*C29 -> 0 | F29: ='F60'!F29 -> #DIV/0! | G29: =E29*F3 -> 0 | I29: 3、水 | J29: 吨 | K29: =3.32+0.9*2.97 -> 5.993 | L29: ='F60'!L29 -> #DIV/0! | M29: =L29*K29 -> #DIV/0! | N29: ='F60'!N29 -> #DIV/0! | O29: =M29*N3 -> #DIV/0!
A30: 4、其他 | B30: 吨 | C30: ='F60'!C30*1.13 -> 0 | D30: ='F60'!D30 -> 0 | E30: ='F60'!E30*1.13 -> 0 | F30: ='F60'!F30 -> 0 | G30: ='F60'!G30*1.13 -> 0 | I30: 4、其他 | J30: 吨 | K30: ='F60'!K30*1.13 -> 0 | L30: ='F60'!L30 -> 0 | M30: ='F60'!M30*1.13 -> 0 | N30: ='F60'!N30 -> 0 | O30: ='F60'!O30*1.13 -> 0
A31: (五)排污费 | E31: =IF(VALUE($F$3)=0,0,G31/$F$3) -> 0 | G31: ='F60'!G31*1.13 -> #DIV/0! | I31: (五)排污费 | K31: =IF(N31=0,0,O31/N31) -> 0 | L31: =IF(K31=0,0,M31/K31) -> 0 | M31: =IF(N$3=0,0,O31/N$3) -> #DIV/0! | O31: ='F60'!O31*1.13 -> #DIV/0!
A32: 1.污水处理 | E32: =E31 -> 0 | G32: =G31 -> #DIV/0! | I32: 1.污水处理 | M32: =M31 -> #DIV/0! | O32: =O31 -> #DIV/0!
A33: 2.污水固定成本 | I33: 2.污水固定成本
A34: (六)增值税 | E34: =IF(VALUE(F$3)=0,0,G34/F$3) -> 0 | G34: =SUM(G5,-G11,-G13,-G26,-G31,-G25)-SUM('F60'!G5,-'F60'!G11-'F60'!G13-'F60'!G26-'F60'!G31,-'F60'!G25) -> #DIV/0! | I34: (六)增值税 | M34: =IF(N$3=0,0,O34/N$3) -> #DIV/0! | O34: =SUM(O5,-O11,-O13,-O26,-O31,-O25)-SUM('F60'!O5,-'F60'!O11-'F60'!O13-'F60'!O26-'F60'!O31,-'F60'!O25) -> #DIV/0!
A35: 三、边际贡献 | E35: =E5-E10 -> 0 | G35: =G5-G10 -> #DIV/0! | I35: 三、边际贡献 | M35: =M5-M10 -> #DIV/0! | O35: =O5-O10 -> #DIV/0!
A36: 四、固定成本 | E36: =SUM(E37:E43) -> 0 | G36: =SUM(G37:G43) -> #DIV/0! | I36: 四、固定成本 | M36: =IF(N$3=0,0,O36/N$3) -> #DIV/0! | O36: =SUM(O37:O43) -> #DIV/0!
A37: （一）折旧与摊销 | E37: ='F60'!E37 -> 0 | G37: ='F60'!G37 -> #DIV/0! | I37: （一）折旧与摊销 | M37: ='F60'!M37 -> #DIV/0! | O37: ='F60'!O37 -> #DIV/0!
A38: （二）工资 | E38: ='F60'!E38 -> 0 | G38: ='F60'!G38 -> #DIV/0! | I38: （二）工资 | M38: ='F60'!M38 -> #DIV/0! | O38: ='F60'!O38 -> #DIV/0!
A39: （三）制造费用 | E39: ='F60'!E39 -> 0 | G39: ='F60'!G39 -> #DIV/0! | I39: （三）制造费用 | M39: ='F60'!M39 -> #DIV/0! | O39: ='F60'!O39 -> #DIV/0!
A40: （四）销售费用 | E40: ='F60'!E40 -> 0 | G40: ='F60'!G40 -> #DIV/0! | I40: （四）销售费用 | M40: ='F60'!M40 -> #DIV/0! | O40: ='F60'!O40 -> #DIV/0!
A41: （五）管理费用 | E41: ='F60'!E41 -> 0 | G41: ='F60'!G41 -> #DIV/0! | I41: （五）管理费用 | M41: ='F60'!M41 -> #DIV/0! | O41: ='F60'!O41 -> #DIV/0!
A42: （六）财务费用 | E42: ='F60'!E42 -> 0 | G42: ='F60'!G42 -> #DIV/0! | I42: （六）财务费用 | M42: ='F60'!M42 -> #DIV/0! | O42: ='F60'!O42 -> #DIV/0!
A43: （七）其他 | E43: ='F60'!E43 -> 0 | G43: ='F60'!G43 -> #DIV/0! | I43: （七） 其他 | M43: ='F60'!M43 -> #DIV/0! | O43: ='F60'!O43 -> #DIV/0!
A44: 其中：税金及附加 | E44: ='F60'!E44 -> 0 | G44: ='F60'!G44 -> #DIV/0! | I44: 其中：税金及附加 | M44: ='F60'!M44 -> #DIV/0! | O44: ='F60'!O44 -> #DIV/0!
A45: 其他业务收支 | E45: ='F60'!E45 -> 0 | G45: ='F60'!G45 -> #DIV/0! | I45: 其他业务收支 | M45: ='F60'!M45 -> #DIV/0! | O45: ='F60'!O45 -> #DIV/0!
A46: 营业外收支 | E46: ='F60'!E46 -> 0 | G46: ='F60'!G46 -> #DIV/0! | I46: 营业外收支 | M46: ='F60'!M46 -> #DIV/0! | O46: ='F60'!O46 -> #DIV/0!
A47: 投资收益+公允价值变动损益 | E47: ='F60'!E47 -> 0 | G47: ='F60'!G47 -> #DIV/0! | I47: 投资收益+公允价值变动损益 | M47: ='F60'!M47 -> #DIV/0! | O47: ='F60'!O47 -> #DIV/0!
A48: 其他收益 | E48: ='F60'!E48 -> 0 | G48: ='F60'!G48 -> #DIV/0! | I48: 其他收益 | M48: ='F60'!M48 -> #DIV/0! | O48: ='F60'!O48 -> #DIV/0!
... A50: 其他 | E50: ='F60'!E50 -> 0 | G50: ='F60'!G50 -> #DIV/0! | I50: 其他 | M50: ='F60'!M50 -> #DIV/0! | O50: ='F60'!O50 -> #DIV/0!
A51: 五、完全成本 | B51: 元 | E51: =E36+E10 -> 0 | G51: =G36+G10 -> #DIV/0! | I51: 五、完全成本 | J51: 元 | M51: =M36+M10 -> #DIV/0! | O51: =O36+O10 -> #DIV/0!
A52: 六、利润总额 | B52: 元 | E52: =E35-E36 -> 0 | G52: =G35-G36 -> #DIV/0! | I52: 六、利润总额 | J52: 元 | M52: =M35-M36 -> #DIV/0! | O52: =O35-O36 -> #DIV/0!
A53: 七、现金流 | B53: 元 | E53: =E52+E37 -> 0 | G53: =G52+G37 -> #DIV/0! | I53: 七、现金流 | J53: 元 | M53: =M52+M37 -> #DIV/0! | O53: =O52+O37 -> #DIV/0!
A54: 加工费 | B54: 元 | E54: =E10-E11+E36-E25 -> 0 | G54: =G10-G11+G36-G25 -> #DIV/0! | I54: 加工费 | J54: 元 | M54: =M10-M11+M36-M25 -> #DIV/0! | O54: =O10-O11+O36-O25 -> #DIV/0!
A55: 其他业务收支-糖渣 | E55: ='F60'!E55 -> 0 | G55: ='F60'!G55 -> #DIV/0! | I55: 其他业务收支-糖渣 | M55: ='F60'!M55 -> #DIV/0! | O55: ='F60'!O55 -> #DIV/0!
A58: 含税与不含税校验 | E58: =E35-'F60'!E35 -> #DIV/0! | G58: =G35-'F60'!G35 -> #DIV/0! | L58: check | M58: =M35-'F60'!M35 -> #DIV/0! | O58: =O35-'F60'!O35 -> #DIV/0!

Sheet F90-含税 
A1: =CONCATENATE("果葡糖浆F90综合成本利润表_含税(2025年"&mth&"月)") -> 果葡糖浆F90综合成本利润表_含税(2025年8月) | I1: =CONCATENATE("果葡糖浆F90综合成本利润表_含税(2025年1-"&mth&"月)") -> 果葡糖浆F90综合成本利润表_含税(2025年1-8月)
A3: 产量 | E3: 本月产量 | F3: ='F90'!F3 -> 0 | G3: 吨 | M3: 本年产量 | N3: ='F90'!N3 -> 36.72 | O3: 吨
B4: 单位 | C4: 单价 | D4: 单耗 | E4: 单位成本 | F4: 总耗量 | G4: 总成本 | J4: 单位 | K4: 单价 | L4: 单耗 | M4: 单位成本 | N4: 总耗量 | O4: 总成本
A5: 一、收入 | E5: =E6-E7 -> 0 | G5: =G6-G7 -> 0 | I5: 一、收入 | M5: =M6-M7 -> 4099.5682 | O5: =O6-O7 -> 150536.14
A6: （一）销售价格 | E6: =OFFSET(销售收入及运费!C96,0,mth-1,1,1) -> 0 | G6: =E6*F3 -> 0 | I6: （一）销售价格 | M6: =销售收入及运费!O96 -> 4158.0893 | O6: =M6*$N$3 -> 152685.04
A7: （二）物流费 | E7: =OFFSET(销售收入及运费!C194,0,mth-1,1,1) -> 0 | G7: ='F90'!G7*1.09 -> 0 | I7: （二）物流费 | M7: =销售收入及运费!O194 -> 58.521092 | O7: =M7*$N$3 -> 2148.8945
A8: 1、运费 | E8: ='F90'!E8*1.09 -> 0 | G8: ='F90'!G8*1.09 -> 0 | I8: 1、运费 | M8: ='F90'!M8*1.09 -> 58.521092 | O8: ='F90'!O8*1.09 -> 2148.8945
A9: 2、包装费、租赁费等 | E9: ='F90'!E9*1.13 -> 0 | G9: ='F90'!G9*1.13 -> 0 | I9: 2、包装费、租赁费等 | M9: ='F90'!M9*1.13 -> 0 | O9: ='F90'!O9*1.13 -> 0
A10: 二、变动成本 | E10: =E11+E13+E26+E31+E34+E25 -> 0 | G10: =G11+G13+G26+G31+G34+G25 -> #DIV/0! | I10: 二、变动成本 | M10: =M11+M13+M26+M31+M34+M25 -> #DIV/0! | O10: =O11+O13+O26+O31+O34+O25 -> #DIV/0!
A11: (一)淀粉 | B11: 吨 | C11: =C12 -> 0 | D11: =IF(C11=0,0,E11/C11) -> 0 | E11: =E12 -> 0 | F11: =F12 -> 0 | G11: =G12 -> 0 | I11: (一)淀粉 | J11: 吨 | K11: =IF(N11=0,0,O11/N11) -> 2774.878 | L11: =IF(K11=0,0,M11/K11) -> 0.81284707 | M11: =M12 -> 2255.5515 | N11: =N12 -> 29.847744 | O11: =O12 -> 82823.849
A12: 1、淀粉(14%) | B12: 吨 | C12: ='F90'!C12*1.13 -> 0 | D12: ='F90'!D12 -> 0 | E12: ='F90'!E12*1.13 -> 0 | F12: ='F90'!F12 -> 0 | G12: ='F90'!G12*1.13 -> 0 | I12: 1、淀粉(14%) | J12: 吨 | K12: =分配表!O75 -> 2774.878 | L12: ='F90'!L12 -> 0.81284707 | M12: =K12*L12 -> 2255.5515 | N12: =L12*N3 -> 29.847744 | O12: =K12*N12 -> 82823.849
A13: (二)辅助材料 | E13: =SUM(E14:E24) -> 0 | G13: =SUM(G14:G24) -> #DIV/0! | I13: (二)辅助材料 | M13: =SUM(M14:M24) -> #DIV/0! | O13: =SUM(O14:O24) -> #DIV/0!
A14: 盐酸(折百) | B14: 公斤 | C14: ='F90'!C14*1.13 -> 0 | D14: ='F90'!D14 -> 0 | E14: ='F90'!E14*1.13 -> 0 | F14: ='F90'!F14 -> 0 | G14: ='F90'!G14*1.13 -> 0 | I14: 盐酸(折百) | J14: 公斤 | K14: =分配表!O191 -> 1.1680073 | L14: ='F90'!L14 -> 4.3055556 | M14: ='F90'!M14*1.13 -> 5.0289202 | N14: ='F90'!N14 -> 158.1 | O14: ='F90'!O14*1.13 -> 184.66195
A15: 氢氧化钠(折百) | B15: 公斤 | C15: ='F90'!C15*1.13 -> 0 | D15: ='F90'!D15 -> 0 | E15: ='F90'!E15*1.13 -> 0 | F15: ='F90'!F15 -> 0 | G15: ='F90'!G15*1.13 -> 0 | I15: 氢氧化钠(折百) | J15: 公斤 | K15: =分配表!O192 -> 3.5767931 | L15: ='F90'!L15 -> 4.9673203 | M15: ='F90'!M15*1.13 -> 17.767077 | N15: ='F90'!N15 -> 182.4 | O15: ='F90'!O15*1.13 -> 652.40706
A16: 硅藻土 | B16: 公斤 | C16: ='F90'!C16*1.13 -> 0 | D16: ='F90'!D16 -> 0 | E16: ='F90'!E16*1.13 -> 0 | F16: ='F90'!F16 -> 0 | G16: ='F90'!G16*1.13 -> 0 | I16: 硅藻土 | J16: 公斤 | K16: =分配表!O193 -> 2.9435031 | L16: ='F90'!L16 -> 0.84422658 | M16: ='F90'!M16*1.13 -> 2.4849836 | N16: ='F90'!N16 -> 31 | O16: ='F90'!O16*1.13 -> 91.248597
A17: 活性炭 | B17: 公斤 | C17: ='F90'!C17*1.13 -> 0 | D17: ='F90'!D17 -> 0 | E17: ='F90'!E17*1.13 -> 0 | F17: ='F90'!F17 -> 0 | G17: ='F90'!G17*1.13 -> 0 | I17: 活性炭 | J17: 公斤 | K17: =分配表!O195 -> 8.0000627 | L17: ='F90'!L17 -> 1.7701525 | M17: ='F90'!M17*1.13 -> 14.161331 | N17: ='F90'!N17 -> 65 | O17: ='F90'!O17*1.13 -> 520.00407
A18: 淀粉酶 | B18: 公斤 | C18: ='F90'!C18*1.13 -> 0 | D18: ='F90'!D18 -> 0 | E18: ='F90'!E18*1.13 -> 0 | F18: ='F90'!F18 -> 0 | G18: ='F90'!G18*1.13 -> 0 | I18: 淀粉酶 | J18: 公斤 | K18: =分配表!O196 -> 54.015593 | L18: ='F90'!L18 -> 0.087145969 | M18: ='F90'!M18*1.13 -> 4.7072412 | N18: ='F90'!N18 -> 3.2 | O18: ='F90'!O18*1.13 -> 172.8499
A19: 复合糖化酶 | B19: 公斤 | C19: ='F90'!C19*1.13 -> 0 | D19: ='F90'!D19 -> 0 | E19: ='F90'!E19*1.13 -> 0 | F19: ='F90'!F19 -> 0 | G19: ='F90'!G19*1.13 -> 0 | I19: 复合糖化酶 | J19: 公斤 | K19: =分配表!O197 -> 36.383097 | L19: ='F90'!L19 -> 0.14978214 | M19: ='F90'!M19*1.13 -> 5.449538 | N19: ='F90'!N19 -> 5.5 | O19: ='F90'!O19*1.13 -> 200.10703
A20: 异构酶 | B20: 公斤 | C20: ='F90'!C20*1.13 -> 0 | D20: ='F90'!D20 -> 0 | E20: ='F90'!E20*1.13 -> 0 | F20: ='F90'!F20 -> 0 | G20: ='F90'!G20*1.13 -> 0 | I20: 异构酶 | J20: 公斤 | K20: =分配表!O198 -> 246.99203 | L20: ='F90'!L20 -> 0.089869281 | M20: ='F90'!M20*1.13 -> 22.196996 | N20: ='F90'!N20 -> 3.3 | O20: ='F90'!O20*1.13 -> 815.07371
A21: 硫酸镁(食品级) | B21: 公斤 | C21: ='F90'!C21*1.13 -> 0 | D21: ='F90'!D21 -> 0 | E21: ='F90'!E21*1.13 -> 0 | F21: ='F90'!F21 -> 0 | G21: ='F90'!G21*1.13 -> 0 | I21: 硫酸镁(食品级) | J21: 公斤 | K21: =分配表!O199 -> 1.106806 | L21: ='F90'!L21 -> 0.43572985 | M21: ='F90'!M21*1.13 -> 0.48226841 | N21: ='F90'!N21 -> 16 | O21: ='F90'!O21*1.13 -> 17.708896
A22: 焦亚硫酸钠(食品级) | B22: 公斤 | C22: ='F90'!C22*1.13 -> 0 | D22: ='F90'!D22 -> 0 | E22: ='F90'!E22*1.13 -> 0 | F22: ='F90'!F22 -> 0 | G22: ='F90'!G22*1.13 -> 0 | I22: 焦亚硫酸钠(食品级) | J22: 公斤 | K22: =分配表!O200 -> 2.0973705 | L22: ='F90'!L22 -> 0.29956427 | M22: ='F90'!M22*1.13 -> 0.62829727 | N22: ='F90'!N22 -> 11 | O22: ='F90'!O22*1.13 -> 23.071076
A23: 树脂 | B23: 公斤 | C23: ='F90'!C23*1.13 -> 0 | D23: ='F90'!D23 -> 0 | E23: ='F90'!E23*1.13 -> 0 | F23: ='F90'!F23 -> 0 | G23: ='F90'!G23*1.13 -> #DIV/0! | I23: 树脂 | J23: 公斤 | K23: =分配表!O201 -> 0 | L23: ='F90'!L23 -> 0 | M23: ='F90'!M23*1.13 -> #DIV/0! | N23: ='F90'!N23 -> 0 | O23: ='F90'!O23*1.13 -> #DIV/0!
A24: 其他 | E24: ='F90'!E24*1.13 -> 0 | G24: ='F90'!G24*1.13 -> #DIV/0! | I24: 其他 | M24: ='F90'!M24*1.13 -> #DIV/0! | O24: ='F90'!O24*1.13 -> #DIV/0!
A25: (三)包装物 | I25: (三)包装物
A26: (四)动力能源 | E26: =SUM(E27:E30) -> 0 | G26: =SUM(G27:G30) -> 0 | I26: (四)动力能源 | M26: =SUM(M27:M30) -> #DIV/0! | O26: =SUM(O27:O30) -> #DIV/0!
A27: 1、蒸汽 | B27: 吨 | C27: =OFFSET(分配表!C306,0,mth-1,1,1) -> 0 | D27: ='F90'!D27 -> 0 | E27: =C27*D27 -> 0 | F27: ='F90'!F27 -> 0 | G27: =E27*F$3 -> 0 | I27: 1、蒸汽 | J27: 吨 | K27: =分配表!O306 -> 408.53094 | L27: ='F90'!L27 -> 0.81699346 | M27: =K27*L27 -> 333.76711 | N27: ='F90'!N27 -> 30 | O27: =M27*N$3 -> 12255.928
A28: 2、电 | B28: 度 | C28: ='F90'!C28*1.13 -> 0 | D28: ='F90'!D28 -> 0 | E28: ='F90'!E28*1.13 -> 0 | F28: ='F90'!F28 -> #DIV/0! | G28: ='F90'!G28*1.13 -> 0 | I28: 2、电 | J28: 度 | K28: ='F90'!K28*1.13 -> 0.76911958 | L28: ='F90'!L28 -> #DIV/0! | M28: ='F90'!M28*1.13 -> #DIV/0! | N28: ='F90'!N28 -> #DIV/0! | O28: ='F90'!O28*1.13 -> #DIV/0!
A29: 3、水 | B29: 吨 | C29: =3.32+0.9*2.97 -> 5.993 | D29: ='F90'!D29 -> 0 | E29: =D29*C29 -> 0 | F29: ='F90'!F29 -> #DIV/0! | G29: =E29*F3 -> 0 | I29: 3、水 | J29: 吨 | K29: =3.32+0.9*2.97 -> 5.993 | L29: ='F90'!L29 -> #DIV/0! | M29: =L29*K29 -> #DIV/0! | N29: ='F90'!N29 -> #DIV/0! | O29: =M29*N3 -> #DIV/0!
A30: 4、其他 | B30: 吨 | C30: ='F90'!C30*1.13 -> 0 | D30: ='F90'!D30 -> 0 | E30: ='F90'!E30*1.13 -> 0 | F30: ='F90'!F30 -> 0 | G30: ='F90'!G30*1.13 -> 0 | I30: 4、其他 | J30: 吨 | K30: ='F90'!K30*1.13 -> 0 | L30: ='F90'!L30 -> 0 | M30: ='F90'!M30*1.13 -> 0 | N30: ='F90'!N30 -> 0 | O30: ='F90'!O30*1.13 -> 0
A31: (五)排污费 | E31: =IF(VALUE($F$3)=0,0,G31/$F$3) -> 0 | G31: ='F90'!G31*1.13 -> #DIV/0! | I31: (五)排污费 | K31: =IF(N31=0,0,O31/N31) -> 0 | L31: =IF(K31=0,0,M31/K31) -> 0 | M31: =IF(N$3=0,0,O31/N$3) -> #DIV/0! | O31: ='F90'!O31*1.13 -> #DIV/0!
A32: 1.污水处理 | E32: =E31 -> 0 | G32: =G31 -> #DIV/0! | I32: 1.污水处理 | M32: =M31 -> #DIV/0! | O32: =O31 -> #DIV/0!
A33: 2.污水固定成本 | I33: 2.污水固定成本
A34: (六)增值税 | E34: =IF(VALUE(F$3)=0,0,G34/F$3) -> 0 | G34: =SUM(G5,-G11,-G13,-G26,-G31,-G25)-SUM('F90'!G5,-'F90'!G11-'F90'!G13-'F90'!G26-'F90'!G31,-'F90'!G25) -> #DIV/0! | I34: (六)增值税 | M34: =IF(N$3=0,0,O34/N$3) -> #DIV/0! | O34: =SUM(O5,-O11,-O13,-O26,-O31,-O25)-SUM('F90'!O5,-'F90'!O11-'F90'!O13-'F90'!O26-'F90'!O31,-'F90'!O25) -> #DIV/0!
A35: 三、边际贡献 | E35: =E5-E10 -> 0 | G35: =G5-G10 -> #DIV/0! | I35: 三、边际贡献 | M35: =M5-M10 -> #DIV/0! | O35: =O5-O10 -> #DIV/0!
A36: 四、固定成本 | E36: =SUM(E37:E43) -> 0 | G36: =SUM(G37:G43) -> #DIV/0! | I36: 四、固定成本 | M36: =IF(N$3=0,0,O36/N$3) -> #DIV/0! | O36: =SUM(O37:O43) -> #DIV/0!
A37: （一）折旧与摊销 | E37: ='F90'!E37 -> 0 | G37: ='F90'!G37 -> #DIV/0! | I37: （一）折旧与摊销 | M37: ='F90'!M37 -> #DIV/0! | O37: ='F90'!O37 -> #DIV/0!
A38: （二）工资 | E38: ='F90'!E38 -> 0 | G38: ='F90'!G38 -> #DIV/0! | I38: （二）工资 | M38: ='F90'!M38 -> #DIV/0! | O38: ='F90'!O38 -> #DIV/0!
A39: （三）制造费用 | E39: ='F90'!E39 -> 0 | G39: ='F90'!G39 -> #DIV/0! | I39: （三）制造费用 | M39: ='F90'!M39 -> #DIV/0! | O39: ='F90'!O39 -> #DIV/0!
A40: （四）销售费用 | E40: ='F90'!E40 -> 0 | G40: ='F90'!G40 -> #DIV/0! | I40: （四）销售费用 | M40: ='F90'!M40 -> #DIV/0! | O40: ='F90'!O40 -> #DIV/0!
A41: （五）管理费用 | E41: ='F90'!E41 -> 0 | G41: ='F90'!G41 -> #DIV/0! | I41: （五）管理费用 | M41: ='F90'!M41 -> #DIV/0! | O41: ='F90'!O41 -> #DIV/0!
A42: （六）财务费用 | E42: ='F90'!E42 -> 0 | G42: ='F90'!G42 -> #DIV/0! | I42: （六）财务费用 | M42: ='F90'!M42 -> #DIV/0! | O42: ='F90'!O42 -> #DIV/0!
A43: （七）其他 | E43: ='F90'!E43 -> 0 | G43: ='F90'!G43 -> #DIV/0! | I43: （七） 其他 | M43: ='F90'!M43 -> #DIV/0! | O43: ='F90'!O43 -> #DIV/0!
A44: 其中：税金及附加 | E44: ='F90'!E44 -> 0 | G44: ='F90'!G44 -> #DIV/0! | I44: 其中：税金及附加 | M44: ='F90'!M44 -> #DIV/0! | O44: ='F90'!O44 -> #DIV/0!
A45: 其他业务收支 | E45: ='F90'!E45 -> 0 | G45: ='F90'!G45 -> #DIV/0! | I45: 其他业务收支 | M45: ='F90'!M45 -> #DIV/0! | O45: ='F90'!O45 -> #DIV/0!
A46: 营业外收支 | E46: ='F90'!E46 -> 0 | G46: ='F90'!G46 -> #DIV/0! | I46: 营业外收支 | M46: ='F90'!M46 -> #DIV/0! | O46: ='F90'!O46 -> #DIV/0!
A47: 投资收益+公允价值变动损益 | E47: ='F90'!E47 -> 0 | G47: ='F90'!G47 -> #DIV/0! | I47: 投资收益+公允价值变动损益 | M47: ='F90'!M47 -> #DIV/0! | O47: ='F90'!O47 -> #DIV/0!
A48: 其他收益 | E48: ='F90'!E48 -> 0 | G48: ='F90'!G48 -> #DIV/0! | I48: 其他收益 | M48: ='F90'!M48 -> #DIV/0! | O48: ='F90'!O48 -> #DIV/0!
... A50: 其他 | E50: ='F90'!E50 -> 0 | G50: ='F90'!G50 -> #DIV/0! | I50: 其他 | M50: ='F90'!M50 -> #DIV/0! | O50: ='F90'!O50 -> #DIV/0!
A51: 五、完全成本 | B51: 元 | E51: =E36+E10 -> 0 | G51: =G36+G10 -> #DIV/0! | I51: 五、完全成本 | J51: 元 | M51: =M36+M10 -> #DIV/0! | O51: =O36+O10 -> #DIV/0!
A52: 六、利润总额 | B52: 元 | E52: =E35-E36 -> 0 | G52: =G35-G36 -> #DIV/0! | I52: 六、利润总额 | J52: 元 | M52: =M35-M36 -> #DIV/0! | O52: =O35-O36 -> #DIV/0!
A53: 七、现金流 | B53: 元 | E53: =E52+E37 -> 0 | G53: =G52+G37 -> #DIV/0! | I53: 七、现金流 | J53: 元 | M53: =M52+M37 -> #DIV/0! | O53: =O52+O37 -> #DIV/0!
A54: 加工费 | B54: 元 | E54: =E10-E11+E36-E25 -> 0 | G54: =G10-G11+G36-G25 -> #DIV/0! | I54: 加工费 | J54: 元 | M54: =M10-M11+M36-M25 -> #DIV/0! | O54: =O10-O11+O36-O25 -> #DIV/0!
A55: 其他业务收支-糖渣 | E55: ='F90'!E55 -> 0 | G55: ='F90'!G55 -> #DIV/0! | I55: 其他业务收支-糖渣 | M55: ='F90'!M55 -> #DIV/0! | O55: ='F90'!O55 -> #DIV/0!
A58: 含税与不含税校验 | E58: =E35-'F90'!E35 -> 0 | G58: =G35-'F90'!G35 -> #DIV/0! | L58: check | M58: =M35-'F90'!M35 -> #DIV/0! | O58: =O35-'F90'!O35 -> #DIV/0!

Sheet F55小包装-含税 
A1: =CONCATENATE("果葡糖浆F55小包装综合成本利润表_含税(2024年"&mth&"月)") -> 果葡糖浆F55小包装综合成本利润表_含税(2024年8月) | I1: =CONCATENATE("果葡糖浆F55小包装综合成本利润表_含税(2024年1-"&mth&"月)") -> 果葡糖浆F55小包装综合成本利润表_含税(2024年1-8月)
E3: 本月产量 | F3: =F55小包装!F3 -> 0 | G3: 吨 | M3: 本年产量： | N3: =F55小包装!N3 -> 89.175 | O3: 吨
B4: 单位 | C4: 单价 | D4: 单耗 | E4: 单位成本 | F4: 总耗量 | G4: 总成本 | J4: 单位 | K4: 单价 | L4: 单耗 | M4: 单位成本 | N4: 总耗量 | O4: 总成本
A5: 一、收入 | E5: =E6-E7 -> 0 | G5: =G6-G7 -> 0 | I5: 一、收入 | M5: =M6-M7 -> 4172.4859 | O5: =O6-O7 -> 372081.43
A6: （一）销售价格 | E6: =OFFSET(销售收入及运费!C87,0,mth-1,1,1) -> 0 | G6: =E6*$F$3 -> 0 | I6: （一）销售价格 | M6: =销售收入及运费!O87 -> 5163.5322 | O6: =M6*$N$3 -> 460457.98
A7: （二）物流费 | E7: =OFFSET(销售收入及运费!C185,0,mth-1,1,1) -> 0 | G7: =E7*$F$3 -> 0 | I7: （二）物流费 | M7: =销售收入及运费!O185 -> 991.04624 | O7: =M7*$N$3 -> 88376.548
A8: 1、运费 | E8: =F55小包装!E8*1.09 -> #DIV/0! | G8: =E8*$F$3 -> #DIV/0! | I8: 1、运费 | M8: =F55小包装!M8*1.09 -> 102.17043 | O8: =M8*$N$3 -> 9111.0484
A9: 2、包装费、租赁费等 | E9: =F55小包装!E9*1.13 -> #DIV/0! | G9: =E9*$F$3 -> #DIV/0! | I9: 2、包装费、租赁费等 | M9: =F55小包装!M9*1.13 -> 888.8758 | O9: =M9*$N$3 -> 79265.5
A10: 二、变动成本 | E10: =E11+E13+E26+E31+E34+E25 -> #DIV/0! | G10: =G11+G13+G26+G31+G34+G25 -> #DIV/0! | I10: 二、变动成本 | M10: =M11+M13+M26+M31+M34+M25 -> #DIV/0! | O10: =O11+O13+O26+O31+O34+O25 -> #DIV/0!
A11: (一)淀粉 | B11: 吨 | C11: =C12 -> 0 | D11: =IF(C11=0,0,E11/C11) -> 0 | E11: =E12 -> 0 | F11: =F12 -> 0 | G11: =G12 -> 0 | I11: (一)淀粉 | J11: 吨 | K11: =IF(N11=0,0,O11/N11) -> 2824.3684 | L11: =IF(K11=0,0,M11/K11) -> 0.84877003 | M11: =M12 -> 2397.2392 | N11: =N12 -> 75.689067 | O11: =O12 -> 213773.81
A12: 1、淀粉(14%) | B12: 吨 | C12: =F55小包装!C12*1.13 -> 0 | D12: =F55小包装!D12 -> 0 | E12: =F55小包装!E12*1.13 -> 0 | F12: =F55小包装!F12 -> 0 | G12: =F55小包装!G12*1.13 -> 0 | I12: 1、淀粉(14%) | J12: 吨 | K12: =分配表!O71 -> 2824.3684 | L12: =F55小包装!L12 -> 0.84877003 | M12: =K12*L12 -> 2397.2392 | N12: =L12*N3 -> 75.689067 | O12: =K12*N12 -> 213773.81
A13: (二)辅助材料 | E13: =SUM(E14:E24) -> #DIV/0! | G13: =SUM(G14:G24) -> #DIV/0! | I13: (二)辅助材料 | M13: =SUM(M14:M24) -> #DIV/0! | O13: =SUM(O14:O24) -> #DIV/0!
A14: 盐酸(折百) | B14: 公斤 | C14: =F55小包装!C14*1.13 -> 0 | D14: =F55小包装!D14 -> 0 | E14: =F55小包装!E14*1.13 -> 0 | F14: =F55小包装!F14 -> 0 | G14: =F55小包装!G14*1.13 -> 0 | I14: 盐酸(折百) | J14: 公斤 | K14: =F55小包装!K14*1.13 -> 1.1680073 | L14: =F55小包装!L14 -> 4.5578743 | M14: =K14*L14 -> 5.3236304 | N14: =F55小包装!N14 -> 406.44844 | O14: =M14*$N$3 -> 474.73474
A15: 氢氧化钠(折百) | B15: 公斤 | C15: =F55小包装!C15*1.13 -> 0 | D15: =F55小包装!D15 -> 0 | E15: =F55小包装!E15*1.13 -> 0 | F15: =F55小包装!F15 -> 0 | G15: =F55小包装!G15*1.13 -> 0 | I15: 氢氧化钠(折百) | J15: 公斤 | K15: =F55小包装!K15*1.13 -> 3.5767931 | L15: =F55小包装!L15 -> 5.0625869 | M15: =K15*L15 -> 18.107826 | N15: =F55小包装!N15 -> 451.45618 | O15: =M15*$N$3 -> 1614.7654
A16: 硅藻土 | B16: 公斤 | C16: =F55小包装!C16*1.13 -> 0 | D16: =F55小包装!D16 -> 0 | E16: =F55小包装!E16*1.13 -> 0 | F16: =F55小包装!F16 -> 0 | G16: =F55小包装!G16*1.13 -> 0 | I16: 硅藻土 | J16: 公斤 | K16: =F55小包装!K16*1.13 -> 2.9435031 | L16: =F55小包装!L16 -> 0.76650844 | M16: =K16*L16 -> 2.25622 | N16: =F55小包装!N16 -> 68.35339 | O16: =M16*$N$3 -> 201.19842
A17: 活性炭 | B17: 公斤 | C17: =F55小包装!C17*1.13 -> 0 | D17: =F55小包装!D17 -> 0 | E17: =F55小包装!E17*1.13 -> 0 | F17: =F55小包装!F17 -> 0 | G17: =F55小包装!G17*1.13 -> 0 | I17: 活性炭 | J17: 公斤 | K17: =F55小包装!K17*1.13 -> 8.0000627 | L17: =F55小包装!L17 -> 1.5998718 | M17: =K17*L17 -> 12.799075 | N17: =F55小包装!N17 -> 142.66857 | O17: =M17*$N$3 -> 1141.3575
A18: 淀粉酶 | B18: 公斤 | C18: =F55小包装!C18*1.13 -> 0 | D18: =F55小包装!D18 -> 0 | E18: =F55小包装!E18*1.13 -> 0 | F18: =F55小包装!F18 -> 0 | G18: =F55小包装!G18*1.13 -> 0 | I18: 淀粉酶 | J18: 公斤 | K18: =F55小包装!K18*1.13 -> 54.015593 | L18: =F55小包装!L18 -> 0.082519047 | M18: =K18*L18 -> 4.4573152 | N18: =F55小包装!N18 -> 7.358636 | O18: =M18*$N$3 -> 397.48109
A19: 复合糖化酶 | B19: 公斤 | C19: =F55小包装!C19*1.13 -> 0 | D19: =F55小包装!D19 -> 0 | E19: =F55小包装!E19*1.13 -> 0 | F19: =F55小包装!F19 -> 0 | G19: =F55小包装!G19*1.13 -> 0 | I19: 复合糖化酶 | J19: 公斤 | K19: =F55小包装!K19*1.13 -> 36.383097 | L19: =F55小包装!L19 -> 0.16120776 | M19: =K19*L19 -> 5.8652375 | N19: =F55小包装!N19 -> 14.375702 | O19: =M19*$N$3 -> 523.03256
A20: 异构酶 | B20: 公斤 | C20: =F55小包装!C20*1.13 -> 0 | D20: =F55小包装!D20 -> 0 | E20: =F55小包装!E20*1.13 -> 0 | F20: =F55小包装!F20 -> 0 | G20: =F55小包装!G20*1.13 -> 0 | I20: 异构酶 | J20: 公斤 | K20: =F55小包装!K20*1.13 -> 246.99203 | L20: =F55小包装!L20 -> 0.097700032 | M20: =K20*L20 -> 24.131129 | N20: =F55小包装!N20 -> 8.7124004 | O20: =M20*$N$3 -> 2151.8935
A21: 硫酸镁 | B21: 公斤 | C21: =F55小包装!C21*1.13 -> 0 | D21: =F55小包装!D21 -> 0 | E21: =F55小包装!E21*1.13 -> 0 | F21: =F55小包装!F21 -> 0 | G21: =F55小包装!G21*1.13 -> 0 | I21: 硫酸镁 | J21: 公斤 | K21: =F55小包装!K21*1.13 -> 1.106806 | L21: =F55小包装!L21 -> 0.49607959 | M21: =K21*L21 -> 0.54906387 | N21: =F55小包装!N21 -> 44.237898 | O21: =M21*$N$3 -> 48.962771
A22: 焦亚硫酸钠 | B22: 公斤 | C22: =F55小包装!C22*1.13 -> 0 | D22: =F55小包装!D22 -> 0 | E22: =F55小包装!E22*1.13 -> 0 | F22: =F55小包装!F22 -> 0 | G22: =F55小包装!G22*1.13 -> 0 | I22: 焦亚硫酸钠 | J22: 公斤 | K22: =F55小包装!K22*1.13 -> 2.0973705 | L22: =F55小包装!L22 -> 0.29181585 | M22: =K22*L22 -> 0.61204596 | N22: =F55小包装!N22 -> 26.022678 | O22: =M22*$N$3 -> 54.579198
A23: 树脂 | B23: 公斤 | C23: =F55小包装!C23*1.13 -> 0 | D23: =F55小包装!D23 -> 0 | E23: =F55小包装!E23*1.13 -> 0 | F23: =F55小包装!F23 -> 0 | G23: =F55小包装!G23*1.13 -> #DIV/0! | I23: 树脂 | J23: 公斤 | K23: =F55小包装!K23*1.13 -> 0 | L23: =F55小包装!L23 -> 0 | M23: =IF($N$3=0,0,O23/$N$3) -> 0 | N23: =F55小包装!N23 -> 0 | O23: =基础表!O241 -> 0
A24: 其他 | E24: =F55小包装!E24*1.13 -> #DIV/0! | G24: =F55小包装!G24*1.13 -> #DIV/0! | I24: 其他 | M24: =IF($N$3=0,0,O24/$N$3) -> #DIV/0! | O24: =F55小包装!O24*1.13 -> #DIV/0!
A25: (三)包装物 | I25: (三)包装物
A26: (四)动力能源 | E26: =SUM(E27:E30) -> 0 | G26: =SUM(G27:G30) -> 0 | I26: (四)动力能源 | M26: =SUM(M27:M30) -> #DIV/0! | O26: =SUM(O27:O30) -> #DIV/0!
A27: 1、蒸汽 | B27: 吨 | C27: =OFFSET(分配表!C306,0,mth-1,1,1) -> 0 | D27: =F55小包装!D27 -> 0 | E27: =C27*D27 -> 0 | F27: =F55小包装!F27 -> 0 | G27: =E27*F$3 -> 0 | I27: 1、蒸汽 | J27: 吨 | K27: =分配表!O306 -> 408.53094 | L27: =IF($N$3=0,0,N27/$N$3) -> 0.30859932 | M27: =K27*L27 -> 126.07237 | N27: =F55小包装!N27 -> 27.519344 | O27: =M27*N$3 -> 11242.504
A28: 2、电 | B28: 度 | C28: =F55小包装!C28*1.13 -> 0 | D28: =F55小包装!D28 -> 0 | E28: =F55小包装!E28*1.13 -> 0 | F28: =F55小包装!F28 -> 0 | G28: =F55小包装!G28*1.13 -> 0 | I28: 2、电 | J28: 度 | K28: =分配表!O325 -> 0.76911958 | L28: =IF($N$3=0,0,N28/$N$3) -> #DIV/0! | M28: =K28*L28 -> #DIV/0! | N28: =F55小包装!N28 -> #DIV/0! | O28: =M28*N$3 -> #DIV/0!
A29: 3、水 | B29: 吨 | C29: =3.32+0.9*2.97 -> 5.993 | D29: =F55小包装!D29 -> 0 | E29: =D29*C29 -> 0 | F29: =F55小包装!F29 -> 0 | G29: =E29*F3 -> 0 | I29: 3、水 | J29: 吨 | K29: =3.32+0.9*2.97 -> 5.993 | L29: =IF($N$3=0,0,N29/$N$3) -> #DIV/0! | M29: =L29*K29 -> #DIV/0! | N29: =F55小包装!N29 -> #DIV/0! | O29: =M29*N3 -> #DIV/0!
A30: 4、其他 | B30: 吨 | C30: =F55小包装!C30*1.13 -> 0 | D30: =F55小包装!D30 -> 0 | E30: =F55小包装!E30*1.13 -> 0 | F30: =F55小包装!F30 -> 0 | G30: =F55小包装!G30*1.13 -> 0 | I30: 4、其他 | J30: 吨 | K30: =F55小包装!K30*1.13 -> 0 | L30: =IF($N$3=0,0,N30/$N$3) -> 0 | M30: =F55小包装!M30*1.13 -> 0 | N30: =F55小包装!N30 -> 0 | O30: =F55小包装!O30*1.13 -> 0
A31: (五)排污费 | E31: =IF(VALUE(F$3)=0,0,G31/F$3) -> 0 | G31: =F55小包装!G31*1.13 -> #DIV/0! | I31: (五)排污费 | K31: =IF(N31=0,0,O31/N31) -> 0 | L31: =IF(K31=0,0,M31/K31) -> 0 | M31: =IF($N$3=0,,O31/$N$3) -> #DIV/0! | O31: =F55小包装!O31*1.13 -> #DIV/0!
A32: 1.污水处理 | E32: =E31 -> 0 | G32: =G31 -> #DIV/0! | I32: 1.污水处理 | M32: =M31 -> #DIV/0! | O32: =O31 -> #DIV/0!
A33: 2.污水固定成本 | I33: 2.污水固定成本
A34: (六)增值税 | E34: =IF(VALUE(F$3)=0,0,G34/F$3) -> 0 | G34: =SUM(G5,-G11,-G13,-G26,-G31,-G25)-SUM(F55小包装!G5,-F55小包装!G11-F55小包装!G13-F55小包装!G26-F55小包装!G31,-F55小包装!G25) -> #DIV/0! | I34: (六)增值税 | M34: =IF(N$3=0,0,O34/N$3) -> #DIV/0! | O34: =SUM(O5,-O11,-O13,-O26,-O31,-O25)-SUM(F55小包装!O5,-F55小包装!O11-F55小包装!O13-F55小包装!O26-F55小包装!O31,-F55小包装!O25) -> #DIV/0!
A35: 三、边际贡献 | E35: =E5-E10 -> #DIV/0! | G35: =G5-G10 -> #DIV/0! | I35: 三、边际贡献 | M35: =M5-M10 -> #DIV/0! | O35: =O5-O10 -> #DIV/0!
A36: 四、固定成本 | E36: =SUM(E37:E43) -> 0 | G36: =SUM(G37:G43) -> #DIV/0! | I36: 四、固定成本 | M36: =IF(N$3=0,0,O36/N$3) -> #DIV/0! | O36: =SUM(O37:O43) -> #DIV/0!
A37: （一）折旧与摊销 | E37: =F55小包装!E37 -> 0 | G37: =F55小包装!G37 -> #DIV/0! | I37: （一）折旧与摊销 | M37: =F55小包装!M37 -> #DIV/0! | O37: =F55小包装!O37 -> #DIV/0!
A38: （二）工资 | E38: =F55小包装!E38 -> 0 | G38: =F55小包装!G38 -> #DIV/0! | I38: （二）工资 | M38: =F55小包装!M38 -> #DIV/0! | O38: =F55小包装!O38 -> #DIV/0!
A39: （三）制造费用 | E39: =F55小包装!E39 -> 0 | G39: =F55小包装!G39 -> #DIV/0! | I39: （三）制造费用 | M39: =F55小包装!M39 -> #DIV/0! | O39: =F55小包装!O39 -> #DIV/0!
A40: （四）销售费用 | E40: =F55小包装!E40 -> 0 | G40: =F55小包装!G40 -> #DIV/0! | I40: （四）销售费用 | M40: =F55小包装!M40 -> #DIV/0! | O40: =F55小包装!O40 -> #DIV/0!
A41: （五）管理费用 | E41: =F55小包装!E41 -> 0 | G41: =F55小包装!G41 -> #DIV/0! | I41: （五）管理费用 | M41: =F55小包装!M41 -> #DIV/0! | O41: =F55小包装!O41 -> #DIV/0!
A42: （六）财务费用 | E42: =F55小包装!E42 -> 0 | G42: =F55小包装!G42 -> #DIV/0! | I42: （六）财务费用 | M42: =F55小包装!M42 -> #DIV/0! | O42: =F55小包装!O42 -> #DIV/0!
A43: （七）其他 | E43: =F55小包装!E43 -> 0 | G43: =F55小包装!G43 -> #DIV/0! | I43: （七） 其他 | M43: =F55小包装!M43 -> #DIV/0! | O43: =F55小包装!O43 -> #DIV/0!
A44: 其中：税金及附加 | E44: =F55小包装!E44 -> 0 | G44: =F55小包装!G44 -> #DIV/0! | I44: 其中：税金及附加 | M44: =F55小包装!M44 -> #DIV/0! | O44: =F55小包装!O44 -> #DIV/0!
A45: 其他业务收支 | E45: =F55小包装!E45 -> 0 | G45: =F55小包装!G45 -> #DIV/0! | I45: 其他业务收支 | M45: =F55小包装!M45 -> #DIV/0! | O45: =F55小包装!O45 -> #DIV/0!
A46: 营业外收支 | E46: =F55小包装!E46 -> 0 | G46: =F55小包装!G46 -> #DIV/0! | I46: 营业外收支 | M46: =F55小包装!M46 -> #DIV/0! | O46: =F55小包装!O46 -> #DIV/0!
A47: 投资收益+公允价值变动损益 | E47: =F55小包装!E47 -> 0 | G47: =F55小包装!G47 -> #DIV/0! | I47: 投资收益+公允价值变动损益 | M47: =F55小包装!M47 -> #DIV/0! | O47: =F55小包装!O47 -> #DIV/0!
A48: 其他收益 | E48: =F55小包装!E48 -> 0 | G48: =F55小包装!G48 -> #DIV/0! | I48: 其他收益 | M48: =F55小包装!M48 -> #DIV/0! | O48: =F55小包装!O48 -> #DIV/0!
A49: 资产减值损失 | E49: =F55小包装!E49 -> 0 | G49: =F55小包装!G49 -> #DIV/0! | I49: 资产减值损失 | M49: =F55小包装!M49 -> #DIV/0! | O49: =F55小包装!O49 -> #DIV/0!
A50: 其他 | E50: =F55小包装!E50 -> 0 | G50: =F55小包装!G50 -> #DIV/0! | I50: 其他 | M50: =F55小包装!M50 -> #DIV/0! | O50: =F55小包装!O50 -> #DIV/0!
A51: 五、完全成本 | B51: 元 | E51: =E36+E10 -> #DIV/0! | G51: =G36+G10 -> #DIV/0! | I51: 五、完全成本 | J51: 元 | M51: =M36+M10 -> #DIV/0! | O51: =O36+O10 -> #DIV/0!
A52: 六、利润总额 | B52: 元 | E52: =E35-E36 -> #DIV/0! | G52: =G35-G36 -> #DIV/0! | I52: 六、利润总额 | J52: 元 | M52: =M35-M36 -> #DIV/0! | O52: =O35-O36 -> #DIV/0!
A53: 七、现金流 | B53: 元 | E53: =E52+E37 -> #DIV/0! | G53: =G52+G37 -> #DIV/0! | I53: 七、现金流 | J53: 元 | M53: =M52+M37 -> #DIV/0! | O53: =O52+O37 -> #DIV/0!
A54: 加工费 | B54: 元 | E54: =E10-E11+E36-E25 -> #DIV/0! | G54: =G10-G11+G36-G25 -> #DIV/0! | I54: 加工费 | J54: 元 | M54: =M10-M11+M36-M25 -> #DIV/0! | O54: =O10-O11+O36-O25 -> #DIV/0!
A55: 其他业务收支-糖渣 | E55: =F55小包装!E55 -> 0 | G55: =F55小包装!G55 -> #DIV/0! | I55: 其他业务收支-糖渣 | M55: =F55小包装!M55 -> #DIV/0! | O55: =F55小包装!O55 -> #DIV/0!
A60: 含税与不含税校验 | E60: =E35-F55小包装!E35 -> #DIV/0! | G60: =G35-F55小包装!G35 -> #DIV/0! | L60: check | M60: =M35-F55小包装!M35 -> #DIV/0! | O60: =O35-F55小包装!O35 -> #DIV/0!

Sheet 果糖汇总-含税-pt
A1: =CONCATENATE("果糖装置汇总综合成本利润表_含税(2025年"&mth&"月)") -> 果糖装置汇总综合成本利润表_含税(2025年8月) | I1: =CONCATENATE("果糖装置汇总综合成本利润表_含税(2025年1-"&mth&"月)") -> 果糖装置汇总综合成本利润表_含税(2025年1-8月)
E3: 本月折77固形物产量： | F3: =果糖汇总!F3 -> 0 | G3: 吨 | M3: 本年折77固形物产量： | N3: =果糖汇总!N3 -> 57934.763 | O3: 吨
B4: 单位 | C4: 单价 | D4: 单耗 | E4: 单位成本 | F4: 总耗量 | G4: 总成本 | J4: 单位 | K4: 单价 | L4: 单耗 | M4: 单位成本 | N4: 总耗量 | O4: 总成本
A5: 一、收入 | E5: =E6-E7 -> 0 | G5: =G6-G7 -> 0 | I5: 一、收入 | M5: =M6-M7 -> 3077.2707 | O5: =O6-O7 -> 1.7828095e+08
A6: （一）销售价格 | E6: =IF(F$3=0,0,G6/F$3) -> 0 | G6: ='F55-含税'!G6+'F60-含税'!G6+'F42-含税'!G6 -> 0 | I6: （一）销售价格 | M6: =IF($N$3=0,,O6/$N$3) -> 3228.5571 | O6: ='果糖汇总-含税'!O6 -> 1.8704569e+08
A7: （二）物流费 | E7: =IF($F$3=0,,G7/$F$3) -> 0 | G7: ='果糖汇总-含税'!G7 -> 0 | I7: （二）物流费 | M7: =IF($N$3=0,,O7/$N$3) -> 151.28642 | O7: ='果糖汇总-含税'!O7 -> 8764742.9
A8: 1、运费 | E8: ='果糖汇总-含税'!E8 -> 0 | G8: ='果糖汇总-含税'!G8 -> #DIV/0! | I8: 1、运费 | M8: ='果糖汇总-含税'!M8 -> 70.227779 | O8: ='果糖汇总-含税'!O8 -> 4068629.7
A9: 2、包装费、租赁费等 | E9: ='果糖汇总-含税'!E9 -> 0 | G9: ='果糖汇总-含税'!G9 -> #DIV/0! | I9: 2、包装费、租赁费等 | M9: ='果糖汇总-含税'!M9 -> 81.05864 | O9: ='果糖汇总-含税'!O9 -> 4696113.1
A10: 二、变动成本 | E10: =E11+E13+E25+E31+E32+E33 -> #DIV/0! | G10: =G11+G13+G25+G31+G33+G32 -> #DIV/0! | I10: 二、变动成本 | M10: =M11+M13+M25+M31+M32+M33 -> #DIV/0! | O10: =O11+O13+O25+O31+O33+O32 -> #DIV/0!
A11: (一)淀粉 | B11: 吨 | C11: =C12 -> 0 | D11: =D12 -> 0 | E11: =E12 -> 0 | F11: =F12 -> 0 | G11: =G12 -> 0 | I11: (一)淀粉 | J11: 吨 | K11: =IF(N11=0,0,O11/N11) -> 2824.3347 | L11: =IF(K11=0,0,M11/K11) -> 0.84550165 | M11: =M12 -> 2387.9796 | N11: =N12 -> 48983.938 | O11: =O12 -> 1.3834704e+08
A12: 1、淀粉(14%) | B12: 吨 | C12: =果糖汇总!C12*1.13 -> 0 | D12: =果糖汇总!D12 -> 0 | E12: =果糖汇总!E12*1.13 -> 0 | F12: =果糖汇总!F12 -> 0 | G12: =果糖汇总!G12*1.13 -> 0 | I12: 1、淀粉(14%) | J12: 吨 | K12: =果糖汇总!K12*1.13 -> 2824.3347 | L12: =果糖汇总!L12 -> 0.84550165 | M12: =果糖汇总!M12*1.13 -> 2387.9796 | N12: =果糖汇总!N12 -> 48983.938 | O12: ='果糖汇总-含税'!O12 -> 1.3834704e+08
A13: (二)辅助材料 | E13: =果糖汇总!E13*1.13 -> 0 | G13: =果糖汇总!G13*1.13 -> #DIV/0! | I13: (二)辅助材料 | M13: =果糖汇总!M13*1.13 -> #DIV/0! | O13: ='果糖汇总-含税'!O13 -> #DIV/0!
A14: 盐酸(折百) | B14: 公斤 | C14: =果糖汇总!C14*1.13 -> 0 | D14: =果糖汇总!D14 -> 0 | E14: =果糖汇总!E14*1.13 -> 0 | F14: =果糖汇总!F14 -> 0 | G14: =果糖汇总!G14*1.13 -> 0 | I14: 盐酸(折百) | J14: 公斤 | K14: =果糖汇总!K14*1.13 -> 1.1680073 | L14: =果糖汇总!L14 -> 4.5394438 | M14: =果糖汇总!M14*1.13 -> 5.3021034 | O14: ='果糖汇总-含税'!O14 -> 307176.1
A15: 氢氧化钠(折百) | B15: 公斤 | C15: =果糖汇总!C15*1.13 -> 0 | D15: =果糖汇总!D15 -> 0 | E15: =果糖汇总!E15*1.13 -> 0 | F15: =果糖汇总!F15 -> 0 | G15: =果糖汇总!G15*1.13 -> 0 | I15: 氢氧化钠(折百) | J15: 公斤 | K15: =果糖汇总!K15*1.13 -> 3.5767931 | L15: =果糖汇总!L15 -> 5.0423611 | M15: =果糖汇总!M15*1.13 -> 18.035483 | O15: ='果糖汇总-含税'!O15 -> 1044881.4
A16: 硅藻土 | B16: 公斤 | C16: =果糖汇总!C16*1.13 -> 0 | D16: =果糖汇总!D16 -> 0 | E16: =果糖汇总!E16*1.13 -> 0 | F16: =果糖汇总!F16 -> 0 | G16: =果糖汇总!G16*1.13 -> 0 | I16: 硅藻土 | J16: 公斤 | K16: =果糖汇总!K16*1.13 -> 2.9435031 | L16: =果糖汇总!L16 -> 0.76499838 | M16: =果糖汇总!M16*1.13 -> 2.2517751 | O16: ='果糖汇总-含税'!O16 -> 130456.06
A17: 活性炭 | B17: 公斤 | C17: =果糖汇总!C17*1.13 -> 0 | D17: =果糖汇总!D17 -> 0 | E17: =果糖汇总!E17*1.13 -> 0 | F17: =果糖汇总!F17 -> 0 | G17: =果糖汇总!G17*1.13 -> 0 | I17: 活性炭 | J17: 公斤 | K17: =果糖汇总!K17*1.13 -> 8.0000627 | L17: =果糖汇总!L17 -> 1.5935165 | M17: =果糖汇总!M17*1.13 -> 12.748232 | O17: ='果糖汇总-含税'!O17 -> 738565.79
A18: 淀粉酶 | B18: 公斤 | C18: =果糖汇总!C18*1.13 -> 0 | D18: =果糖汇总!D18 -> 0 | E18: =果糖汇总!E18*1.13 -> 0 | F18: =果糖汇总!F18 -> 0 | G18: =果糖汇总!G18*1.13 -> 0 | I18: 淀粉酶 | J18: 公斤 | K18: =果糖汇总!K18*1.13 -> 54.015593 | L18: =果糖汇总!L18 -> 0.08242029 | M18: =果糖汇总!M18*1.13 -> 4.4519808 | O18: ='果糖汇总-含税'!O18 -> 257924.45
A19: 复合糖化酶 | B19: 公斤 | C19: =果糖汇总!C19*1.13 -> 0 | D19: =果糖汇总!D19 -> 0 | E19: =果糖汇总!E19*1.13 -> 0 | F19: =果糖汇总!F19 -> 0 | G19: =果糖汇总!G19*1.13 -> 0 | I19: 复合糖化酶 | J19: 公斤 | K19: =果糖汇总!K19*1.13 -> 36.383097 | L19: =果糖汇总!L19 -> 0.16059442 | M19: =果糖汇总!M19*1.13 -> 5.8429226 | O19: ='果糖汇总-含税'!O19 -> 338508.34
A20: 异构酶 | B20: 公斤 | C20: =果糖汇总!C20*1.13 -> 0 | D20: =果糖汇总!D20 -> 0 | E20: =果糖汇总!E20*1.13 -> 0 | F20: =果糖汇总!F20 -> 0 | G20: =果糖汇总!G20*1.13 -> 0 | I20: 异构酶 | J20: 公斤 | K20: =果糖汇总!K20*1.13 -> 246.99203 | L20: =果糖汇总!L20 -> 0.097368137 | M20: =果糖汇总!M20*1.13 -> 24.049154 | O20: ='果糖汇总-含税'!O20 -> 1393282.1
A21: 硫酸镁 | B21: 公斤 | C21: =果糖汇总!C21*1.13 -> 0 | D21: =果糖汇总!D21 -> 0 | E21: =果糖汇总!E21*1.13 -> 0 | F21: =果糖汇总!F21 -> 0 | G21: =果糖汇总!G21*1.13 -> 0 | I21: 硫酸镁 | J21: 公斤 | K21: =果糖汇总!K21*1.13 -> 1.106806 | L21: =果糖汇总!L21 -> 0.49452174 | M21: =果糖汇总!M21*1.13 -> 0.54733963 | O21: ='果糖汇总-含税'!O21 -> 31709.992
A22: 焦亚硫酸钠 | B22: 公斤 | C22: =果糖汇总!C22*1.13 -> 0 | D22: =果糖汇总!D22 -> 0 | E22: =果糖汇总!E22*1.13 -> 0 | F22: =果糖汇总!F22 -> 0 | G22: =果糖汇总!G22*1.13 -> 0 | I22: 焦亚硫酸钠 | J22: 公斤 | K22: =果糖汇总!K22*1.13 -> 2.0973705 | L22: =果糖汇总!L22 -> 0.29084437 | M22: =果糖汇总!M22*1.13 -> 0.61000842 | O22: ='果糖汇总-含税'!O22 -> 35340.694
A23: 树脂 | B23: 公斤 | E23: =果糖汇总!E23*1.13 -> 0 | G23: =果糖汇总!G23*1.13 -> #DIV/0! | I23: 树脂 | J23: 公斤 | K23: =果糖汇总!K23*1.13 -> 0 | L23: =果糖汇总!L23 -> 0 | M23: =果糖汇总!M23*1.13 -> #DIV/0! | O23: ='果糖汇总-含税'!O23 -> #DIV/0!
A24: 其他 | E24: =果糖汇总!E24*1.13 -> 0 | G24: =果糖汇总!G24*1.13 -> #DIV/0! | I24: 其他 | K24: =果糖汇总!K24*1.13 -> 0 | L24: =果糖汇总!L24 -> 0 | M24: =果糖汇总!M24*1.13 -> #DIV/0! | O24: ='果糖汇总-含税'!O24 -> #DIV/0!
A25: (三)动力能源 | E25: =SUM(E26:E29)+E30 -> 0 | G25: =SUM(G26:G29)+G30 -> #DIV/0! | I25: (三)动力能源 | M25: =SUM(M26:M29)+M30 -> #DIV/0! | O25: =SUM(O26:O29)+O30 -> #DIV/0!
A26: 1、蒸汽 | B26: 吨 | C26: ='F55-含税'!C27 -> 0 | D26: =果糖汇总!D27 -> 0 | E26: =C26*D26 -> 0 | F26: =果糖汇总!F27 -> 0 | G26: ='F55-含税'!G27+'F42-含税'!G27+'F60-含税'!G27 -> 0 | I26: 1、蒸汽 | J26: 吨 | K26: ='F55-含税'!K27 -> 408.53094 | L26: =果糖汇总!L27 -> 0.30803612 | M26: =K26*L26 -> 125.84229 | N26: =果糖汇总!N27 -> 17846 | O26: ='果糖汇总-含税'!O27 -> 7290643.1
A27: 2、电 | B27: 度 | C27: =IF(G27=0,0,G27/F27) -> 0 | D27: =果糖汇总!D28 -> 0 | E27: =果糖汇总!E28*1.13 -> 0 | F27: =果糖汇总!F28 -> #DIV/0! | G27: =果糖汇总!G28*1.13 -> 0 | I27: 2、电 | J27: 度 | K27: =IF(O27=0,0,O27/N27) -> #DIV/0! | L27: =果糖汇总!L28 -> #DIV/0! | M27: =果糖汇总!M28*1.13 -> #DIV/0! | N27: =果糖汇总!N28 -> #DIV/0! | O27: ='果糖汇总-含税'!O28 -> #DIV/0!
A28: 3、水 | B28: 吨 | C28: =IF(G28=0,0,G28/F28) -> 0 | D28: =果糖汇总!D29 -> 0 | E28: =D28*C28 -> 0 | F28: =果糖汇总!F29 -> #DIV/0! | G28: ='F55-含税'!G29+'F60-含税'!G29+'F42-含税'!G29 -> 0 | I28: 3、水 | J28: 吨 | K28: =IF(O28=0,0,O28/N28) -> #DIV/0! | L28: =果糖汇总!L29 -> #DIV/0! | M28: =L28*K28 -> #DIV/0! | N28: =果糖汇总!N29 -> #DIV/0! | O28: ='果糖汇总-含税'!O29 -> #DIV/0!
A29: 4、其他 | B29: 吨 | I29: 4、其他 | J29: 吨
A30: 5、排污费 | E30: =果糖汇总!$E$31*1.13 -> 0 | G30: =果糖汇总!$G$31*1.13 -> #DIV/0! | I30: 5、排污费 | M30: =果糖汇总!$M$31*1.13 -> #DIV/0! | O30: =果糖汇总!$O$31*1.13 -> #DIV/0!
A31: (四)增值税 | E31: =SUM(E5,-E11,-E13,-E25)-SUM(果糖汇总!E5,-果糖汇总!E11,-果糖汇总!E13,-果糖汇总!E26,-果糖汇总!E31) -> 0 | G31: =SUM(G5,-G11,-G13,-G25)-SUM(果糖汇总!G5,-果糖汇总!G11,-果糖汇总!G13,-果糖汇总!G26,-果糖汇总!G31) -> #DIV/0! | I31: (四)增值税 | M31: =SUM(M5,-M11,-M13,-M25)-SUM(果糖汇总!M5,-果糖汇总!M11,-果糖汇总!M13,-果糖汇总!M26,-果糖汇总!M31) -> #DIV/0! | O31: =SUM(O5,-O11,-O13,-O25)-SUM(果糖汇总!O5,-果糖汇总!O11,-果糖汇总!O13,-果糖汇总!O26,-果糖汇总!O31) -> #DIV/0!
A32: (五)税金及附加 | E32: =IF(F$3=0,0,G32/F$3) -> 0 | G32: =果糖汇总!G44 -> #DIV/0! | I32: (五)税金及附加 | M32: =IF(N$3=0,0,O32/N$3) -> #DIV/0! | O32: =果糖汇总!O44 -> #DIV/0!
A33: (六)糖渣 | E33: =G33/F3 -> #DIV/0! | G33: ='果糖汇总-含税'!G55 -> #DIV/0! | I33: (六)糖渣 | M33: =O33/N3 -> #DIV/0! | O33: ='果糖汇总-含税'!O55 -> #DIV/0!
A34: 三、边际贡献 | E34: =E5-E10 -> #DIV/0! | G34: =G5-G10 -> #DIV/0! | I34: 三、边际贡献 | M34: =M5-M10 -> #DIV/0! | O34: =O5-O10 -> #DIV/0!
A35: 四、固定成本 | E35: =SUM(E36:E42) -> 0 | G35: =SUM(G36:G42) -> #DIV/0! | I35: 四、固定成本 | M35: =SUM(M36:M42) -> #DIV/0! | O35: =SUM(O36:O42) -> #DIV/0!
A36: （一）折旧与摊销 | E36: =IF(F$3=0,0,G36/F$3) -> 0 | G36: =果糖汇总!G37 -> #DIV/0! | I36: （一）折旧与摊销 | M36: =IF(N$3=0,0,O36/N$3) -> #DIV/0! | O36: =果糖汇总!O37 -> #DIV/0!
A37: （二）工资 | E37: =IF(F$3=0,0,G37/F$3) -> 0 | G37: =果糖汇总!G38 -> #DIV/0! | I37: （二）工资 | M37: =IF(N$3=0,0,O37/N$3) -> #DIV/0! | O37: =果糖汇总!O38 -> #DIV/0!
A38: （三）制造费用 | E38: =IF(F$3=0,0,G38/F$3) -> 0 | G38: =果糖汇总!G39 -> #DIV/0! | I38: （三）制造费用 | M38: =IF(N$3=0,0,O38/N$3) -> #DIV/0! | O38: =果糖汇总!O39 -> #DIV/0!
A39: （四）销售费用 | E39: =IF(F$3=0,0,G39/F$3) -> 0 | G39: =果糖汇总!G40 -> #DIV/0! | I39: （四）销售费用 | M39: =IF(N$3=0,0,O39/N$3) -> #DIV/0! | O39: =果糖汇总!O40 -> #DIV/0!
A40: （五）管理费用 | E40: =IF(F$3=0,0,G40/F$3) -> 0 | G40: =果糖汇总!G41 -> #DIV/0! | I40: （五）管理费用 | M40: =IF(N$3=0,0,O40/N$3) -> #DIV/0! | O40: =果糖汇总!O41 -> #DIV/0!
A41: （六）财务费用 | E41: =IF(F$3=0,0,G41/F$3) -> 0 | G41: =果糖汇总!G42 -> #DIV/0! | I41: （六）财务费用 | M41: =IF(N$3=0,0,O41/N$3) -> #DIV/0! | O41: =果糖汇总!O42 -> #DIV/0!
A42: （七）其他 | I42: （七） 其他
A43: 其他业务收支 | I43: 其他业务收支
A44: 营业外收支 | E44: =IF(F$3=0,0,G44/F$3) -> 0 | G44: =果糖汇总!G46 -> #DIV/0! | I44: 营业外收支 | M44: =IF(N$3=0,0,O44/N$3) -> #DIV/0! | O44: =果糖汇总!O46 -> #DIV/0!
A45: 投资收益+公允价值变动损益 | E45: =IF(F$3=0,0,G45/F$3) -> 0 | G45: =果糖汇总!G47 -> #DIV/0! | I45: 投资收益+公允价值变动损益 | M45: =IF(N$3=0,0,O45/N$3) -> #DIV/0! | O45: =果糖汇总!O47 -> #DIV/0!
A46: 其他收益 | E46: =IF(F$3=0,0,G46/F$3) -> 0 | G46: =果糖汇总!G48 -> #DIV/0! | I46: 其他收益 | M46: =IF(N$3=0,0,O46/N$3) -> #DIV/0! | O46: =果糖汇总!O48 -> #DIV/0!
A47: 资产减值损失 | E47: =IF(F$3=0,0,G47/F$3) -> 0 | G47: =果糖汇总!G49 -> #DIV/0! | I47: 资产减值损失 | M47: =IF(N$3=0,0,O47/N$3) -> #DIV/0! | O47: =果糖汇总!O49 -> #DIV/0!
A48: 其他 | E48: =IF(F$3=0,0,G48/F$3) -> 0 | G48: =果糖汇总!G50 -> #DIV/0! | I48: 其他 | M48: =IF(N$3=0,0,O48/N$3) -> #DIV/0! | O48: =果糖汇总!O50 -> #DIV/0!
A49: 五、完全成本 | B49: 元 | E49: =E35+E10 -> #DIV/0! | G49: =G35+G10 -> #DIV/0! | I49: 五、完全成本 | J49: 元 | M49: =M35+M10 -> #DIV/0! | O49: =O35+O10 -> #DIV/0!
A50: 六、利润总额 | B50: 元 | E50: =E34-E35 -> #DIV/0! | G50: =G34-G35 -> #DIV/0! | I50: 六、利润总额 | J50: 元 | M50: =M34-M35 -> #DIV/0! | O50: =O34-O35 -> #DIV/0!
A51: 七、现金流 | B51: 元 | E51: =E50+E36 -> #DIV/0! | G51: =G50+G36 -> #DIV/0! | I51: 七、现金流 | J51: 元 | M51: =M50+M36 -> #DIV/0! | O51: =O50+O36 -> #DIV/0!
A52: 加工费 | B52: 元 | E52: =E10-E11+E35 -> #DIV/0! | G52: =G10-G11+G35 -> #DIV/0! | I52: 加工费 | J52: 元 | M52: =M10-M11+M35 -> #DIV/0! | O52: =O10-O11+O35 -> #DIV/0!

Sheet 专用糖-含税-pt
A1: =CONCATENATE("专用糖综合成本利润表_含税(2025年"&mth&"月)") -> 专用糖综合成本利润表_含税(2025年8月) | I1: =CONCATENATE("专用糖综合成本利润表_含税(2025年1-"&mth&"月)") -> 专用糖综合成本利润表_含税(2025年1-8月)
